Workbook

Sheet 00_РЕЗЮМЕ
A1: VARSHAVKA — Сценарий S03
A2: Банкетный день: дневная работа до 17:00; а-ля карт 20%; бизнес-ланч, доставка и самовывоз 100%; ужины гостиницы 50% от завтраков.
A4: ПАСПОРТ МОДЕЛИ
A5: Начало периода | B5: 01.09.2026 | D5: Окончание периода | E5: 31.08.2027
A6: Площадь кафе, м² | B6: ='01_ВВОД'!$D$7 | D6: Посадочных мест | E6: ='01_ВВОД'!$D$10
A7: Аренда, руб./мес. | B7: ='01_ВВОД'!$D$9 | D7: Банкетов за год | E7: ='01_ВВОД'!$D$52
A9: КЛЮЧЕВЫЕ РЕЗУЛЬТАТЫ
A10: Показатель | B10: За операционный год | C10: Среднее за месяц | E10: Показатель | F10: Значение
A11: Доходы кафе | B11: ='07_PNL_НАЛОГИ'!P6 | C11: ='07_PNL_НАЛОГИ'!Q6 | E11: Валовая маржа кафе | F11: =IF('07_PNL_НАЛОГИ'!P6=0,0,'07_PNL_НАЛОГИ'!P8/'07_PNL_НАЛОГИ'!P6)
A12: Прибыль кафе до налога | B12: ='07_PNL_НАЛОГИ'!P20 | C12: ='07_PNL_НАЛОГИ'!Q20 | E12: Маржинальность кафе | F12: =IF('07_PNL_НАЛОГИ'!P6=0,0,'07_PNL_НАЛОГИ'!P10/'07_PNL_НАЛОГИ'!P6)
A13: Чистый результат кафе | B13: ='07_PNL_НАЛОГИ'!P40 | C13: ='07_PNL_НАЛОГИ'!Q40 | E13: ФОТ / доходы кафе | F13: =IF('07_PNL_НАЛОГИ'!P6=0,0,'07_PNL_НАЛОГИ'!P11/'07_PNL_НАЛОГИ'!P6)
A14: Доходы банкетов | B14: ='07_PNL_НАЛОГИ'!P25 | C14: ='07_PNL_НАЛОГИ'!Q25 | E14: Чистая рентабельность кафе | F14: =IF('07_PNL_НАЛОГИ'!P6=0,0,'07_PNL_НАЛОГИ'!P40/'07_PNL_НАЛОГИ'!P6)
A15: Прибыль банкетов до налога | B15: ='07_PNL_НАЛОГИ'!P29 | C15: ='07_PNL_НАЛОГИ'!Q29 | E15: Рентабельность банкетов до налога | F15: =IF('07_PNL_НАЛОГИ'!P25=0,0,'07_PNL_НАЛОГИ'!P29/'07_PNL_НАЛОГИ'!P25)
A16: Чистый результат банкетов | B16: ='07_PNL_НАЛОГИ'!P41 | C16: ='07_PNL_НАЛОГИ'!Q41 | E16: Упущенные доходы кафе из-за банкетов | F16: ='03_ДОХОДЫ'!P30
A17: Совокупные доходы проекта | B17: ='07_PNL_НАЛОГИ'!P33 | C17: ='07_PNL_НАЛОГИ'!Q33 | E17: Доходы кафе на 1 м² | F17: =IF('01_ВВОД'!$D$7=0,0,'07_PNL_НАЛОГИ'!P6/'01_ВВОД'!$D$7)
A18: Налог к уплате | B18: ='07_PNL_НАЛОГИ'!P37 | C18: ='07_PNL_НАЛОГИ'!Q37 | E18: Гостиничных заказов за год | F18: ='03_ДОХОДЫ'!P22
A19: Чистая прибыль проекта | B19: ='07_PNL_НАЛОГИ'!P42 | C19: ='07_PNL_НАЛОГИ'!Q42
A22: ПОМЕСЯЧНЫЙ ЧИСТЫЙ РЕЗУЛЬТАТ
A23: Показатель | B23: Сен-26 | C23: Окт-26 | D23: Ноя-26 | E23: Дек-26 | F23: Янв-27 | G23: Фев-27 | H23: Мар-27 | I23: Апр-27 | J23: Май-27 | K23: Июн-27 | L23: Июл-27 | M23: Авг-27
A24: Кафе | B24: ='07_PNL_НАЛОГИ'!D40 | C24: ='07_PNL_НАЛОГИ'!E40 | D24: ='07_PNL_НАЛОГИ'!F40 | E24: ='07_PNL_НАЛОГИ'!G40 | F24: ='07_PNL_НАЛОГИ'!H40 | G24: ='07_PNL_НАЛОГИ'!I40 | H24: ='07_PNL_НАЛОГИ'!J40 | I24: ='07_PNL_НАЛОГИ'!K40 | ... M24: ='07_PNL_НАЛОГИ'!O40
A25: Банкеты | B25: ='07_PNL_НАЛОГИ'!D41 | C25: ='07_PNL_НАЛОГИ'!E41 | D25: ='07_PNL_НАЛОГИ'!F41 | E25: ='07_PNL_НАЛОГИ'!G41 | F25: ='07_PNL_НАЛОГИ'!H41 | G25: ='07_PNL_НАЛОГИ'!I41 | H25: ='07_PNL_НАЛОГИ'!J41 | I25: ='07_PNL_НАЛОГИ'!K41 | ... M25: ='07_PNL_НАЛОГИ'!O41
A26: Проект | B26: ='07_PNL_НАЛОГИ'!D42 | C26: ='07_PNL_НАЛОГИ'!E42 | D26: ='07_PNL_НАЛОГИ'!F42 | E26: ='07_PNL_НАЛОГИ'!G42 | F26: ='07_PNL_НАЛОГИ'!H42 | G26: ='07_PNL_НАЛОГИ'!I42 | H26: ='07_PNL_НАЛОГИ'!J42 | I26: ='07_PNL_НАЛОГИ'!K42 | ... M26: ='07_PNL_НАЛОГИ'!O42
A29: ВАЖНЫЕ ДОПУЩЕНИЯ
A30: 1 | B30: Праздничные переносы 2027 года в календаре требуют обновления после официального утверждения.
A31: 2 | B31: НДС в модели установлен 0%; налоговую схему необходимо подтвердить отдельно.
A32: 3 | B32: Оценочные расходы USALI выделены в 01_ВВОД и могут быть заменены без изменения формул.
A33: 4 | B33: Налог УСН рассчитан консолидированно; распределение между кафе и банкетами — управленческое, по выручке.

Sheet 01_ВВОД
A1: VARSHAVKA — исходные данные операционной модели
A2: Операционный год: сентябрь 2026 — август 2027. Синие ячейки — изменяемые входные данные; жёлтая/оранжевая заливка — допущения, требующие проверки.
A4: Код | B4: Раздел | C4: Параметр | D4: Значение | E4: Ед. | F4: Статус | G4: Источник / комментарий
A5: START_DATE | B5: Проект | C5: Начало операционной деятельности | D5: 46266 | E5: дата | F5: Подтверждено | G5: Пользователь
A6: END_DATE | B6: Проект | C6: Окончание операционного года | D6: 46630 | E6: дата | F6: Расчёт | G6: 12 месяцев от старта
A7: AREA | B7: Объект | C7: Площадь помещений №19, №20, №39 | D7: 80.9 | E7: м² | F7: Подтверждено | G7: Схема помещений №19, №20, №39; https://drive.google.com/drive/folders/1VLrgg-vLogvAVUFPkVmkNqlbE9rJ0BNx?usp=drive_link
A8: RENT_RATE | B8: Объект | C8: Ставка аренды | D8: 1000 | E8: руб./м²/мес. | F8: Подтверждено | G8: Пользователь
A9: RENT_MONTH | B9: Объект | C9: Арендный платёж в месяц | D9: =D7*D8 | E9: руб./мес. | F9: Расчёт | G9: Площадь × ставка
A10: SEATS | B10: Объект | C10: Расчётное число посадочных мест | D10: 20 | E10: мест | F10: Подтверждено | G10: Пользователь
A11: MAX_SEATS | B11: Объект | C11: Максимальное число мест | D11: 26 | E11: мест | F11: Подтверждено | G11: Пользователь
A12: USN_RATE | B12: Налоги | C12: УСН «Доходы минус расходы» | D12: 0.15 | E12: % | F12: Подтверждено | G12: Пользователь; справочно: https://www.nalog.gov.ru/rn77/taxation/taxes/usn/
A13: MIN_TAX_RATE | B13: Налоги | C13: Минимальный налог УСН | D13: 0.01 | E13: % | F13: Методика | G13: https://www.nalog.gov.ru/rn77/taxation/taxes/usn/
A14: ACQ_RATE | B14: Налоги и комиссии | C14: Эквайринг | D14: 0.015 | E14: % выручки | F14: Подтверждено | G14: Пользователь
A15: VAT_RATE | B15: Налоги | C15: НДС в модели | D15: 0 | E15: % | F15: Требует решения | G15: Пока 0%; проверить: https://www.nalog.gov.ru/rn77/taxation/taxes/nds_usn/
A16: SPOILAGE_RATE | B16: Себестоимость | C16: Списания и порча | D16: 0.015 | E16: % food cost | F16: Допущение | G16: Рабочий резерв
A17: INV_DIFF_RATE | B17: Себестоимость | C17: Инвентаризационные расхождения | D17: 0.005 | E17: % food cost | F17: Допущение | G17: Рабочий резерв
A18: ALA_CHECK | B18: А-ля карт | C18: Средний чек на гостя | D18: 1000 | E18: руб./гость | F18: Подтверждено | G18: Пользователь
A19: ALA_MON_THU | B19: А-ля карт | C19: Гостей понедельник–четверг | D19: 32 | E19: гостей/день | F19: Подтверждено | G19: Пользователь
A20: ALA_FRI | B20: А-ля карт | C20: Гостей в пятницу | D20: 45 | E20: гостей/день | F20: Подтверждено | G20: Пользователь
A21: ALA_SAT | B21: А-ля карт | C21: Гостей в субботу | D21: 80 | E21: гостей/день | F21: Подтверждено | G21: Пользователь
... A27: LUNCH_DISCOUNT | B27: Бизнес-ланч | C27: Скидка к а-ля карт | D27: 0.25 | E27: % | F27: Подтверждено | G27: Пользователь, 17.07.2026; скидка 25% от среднего чека a-la carte
A28: LUNCH_CHECK | B28: Бизнес-ланч | C28: Средний чек после скидки | D28: =D18*(1-D27) | E28: руб./гость | F28: Расчёт | G28: Средний чек a-la carte × (1 − скидка) = 1 000 × 75% = 750 руб.
A29: LUNCH_COGS | B29: Бизнес-ланч | C29: Эффективный food cost | D29: =D24/(1-D27) | E29: % выручки | F29: Расчёт | G29: 30% / (1 − 25%)
A30: LUNCH_CASHLESS | B30: Бизнес-ланч | C30: Доля безналичной оплаты | D30: 1 | E30: % | F30: Допущение | G30: До уточнения — 100%
A31: DELIV_CHECK | B31: Доставка | C31: Средний чек | D31: 1200 | E31: руб./заказ | F31: Подтверждено | G31: Пользователь
A32: DELIV_WEEKDAY | B32: Доставка | C32: Заказов в будний день | D32: 15 | E32: заказов/день | F32: Подтверждено | G32: Пользователь
A33: DELIV_WEEKEND | B33: Доставка | C33: Заказов в субботу/воскресенье | D33: 30 | E33: заказов/день | F33: Подтверждено | G33: Пользователь
A34: DELIV_HOL | B34: Доставка | C34: Заказов в праздничный день | D34: 30 | E34: заказов/день | F34: Допущение | G34: Как выходной
A35: DELIV_COGS | B35: Доставка | C35: Food cost | D35: 0.3 | E35: % выручки | F35: Подтверждено | G35: Пользователь
A36: DELIV_COURIER | B36: Доставка | C36: Оплата доставщику | D36: 200 | E36: руб./заказ | F36: Подтверждено | G36: Пользователь
A37: DELIV_PACK | B37: Доставка | C37: Упаковка | D37: 65 | E37: руб./заказ | F37: Допущение | G37: Середина диапазона 50–80 руб.; заменить на факт
A38: DELIV_CASHLESS | B38: Доставка | C38: Доля безналичной оплаты | D38: 1 | E38: % | F38: Допущение | G38: До уточнения — 100%
A39: PICK_CHECK | B39: Самовывоз | C39: Средний чек | D39: 400 | E39: руб./заказ | F39: Подтверждено | G39: Пользователь
A40: PICK_ORDERS | B40: Самовывоз | C40: Заказов в календарный день | D40: 12 | E40: заказов/день | F40: Подтверждено | G40: Пользователь
A41: PICK_DISCOUNT | B41: Самовывоз | C41: Скидка к а-ля карт | D41: 0.3 | E41: % | F41: Подтверждено | G41: Пользователь
A42: PICK_COGS | B42: Самовывоз | C42: Эффективный food cost | D42: =D24/(1-D41) | E42: % выручки | F42: Расчёт | G42: 30% / (1 − 30%)
A43: PICK_PACK | B43: Самовывоз | C43: Упаковка | D43: 40 | E43: руб./заказ | F43: Допущение | G43: Середина диапазона 30–50 руб.; заменить на факт
A44: PICK_CASHLESS | B44: Самовывоз | C44: Доля безналичной оплаты | D44: 1 | E44: % | F44: Допущение | G44: До уточнения — 100%
A45: HOTEL_CHECK | B45: Гостиничный канал | C45: Средний чек | D45: 550 | E45: руб./заказ | F45: Подтверждено | G45: Пользователь; сумма с НДС
A46: HOTEL_ORDERS | B46: Гостиничный канал | C46: Заказов каждый календарный день | D46: 20 | E46: заказов/день | F46: Подтверждено | G46: Работает все 365 дней, включая банкеты
A47: HOTEL_COGS | B47: Гостиничный канал | C47: Food cost | D47: 0.5 | E47: % выручки | F47: Подтверждено | G47: Пользователь
A48: HOTEL_PACK | B48: Гостиничный канал | C48: Упаковка / расходники | D48: 0 | E48: руб./заказ | F48: Требует уточнения | G48: Пока 0
A49: HOTEL_CASHLESS | B49: Гостиничный канал | C49: Доля безналичной оплаты | D49: 1 | E49: % | F49: Допущение | G49: До уточнения — 100%
A50: BANQ_START | B50: Банкеты | C50: Начало банкетов | D50: 46327 | E50: дата | F50: Подтверждено | G50: Сентябрь–октябрь без банкетов
A51: BANQ_PER_MONTH | B51: Банкеты | C51: Банкетов в месяц с ноября | D51: 6 | E51: банкетов/мес. | F51: Подтверждено | G51: 60 банкетов за 10 месяцев
A52: BANQ_TOTAL | B52: Банкеты | C52: Банкетов за операционный год | D52: 60 | E52: банкетов/год | F52: Подтверждено | G52: Пользователь
A53: BANQ_PART | B53: Банкеты | C53: Участников на банкет | D53: 20 | E53: чел. | F53: Подтверждено | G53: Пользователь
A54: BANQ_CHECK | B54: Банкеты | C54: Средний чек на человека | D54: 3000 | E54: руб./чел. | F54: Подтверждено | G54: Пользователь
... A116: STAFF_MEALS | B116: F&B Departmental | C116: Питание персонала | D116: 15000 | E116: руб./мес. | F116: Требует уточнения | G116: Строка предусмотрена; пока 0
A117: СЦЕНАРИЙ S03 — ПЕРЕСМОТР УЖИНОВ И OPEX
A118: S03_BANQ_ALA_SHARE | B118: Сценарий S03 | C118: Доля а-ля карт в банкетный день | D118: 0.2 | E118: % обычного объёма | F118: Подтверждено | G118: Наследовано из S02 / Issue #4; включено в S03 / Issue #9
A119: S03_DAY_END | B119: Сценарий S03 | C119: Окончание дневной работы в банкетный день | D119: 17 | E119: час | F119: Подтверждено | G119: Наследовано из S02 / Issue #4; включено в S03 / Issue #9
A120: S03_DINNER_RATIO | B120: Гостиница — ужины | C120: Количество ужинов к завтракам | D120: 0.5 | E120: % завтраков | F120: Подтверждено | G120: Наследовано из S02 / Issue #4; включено в S03 / Issue #9
A121: S03_DINNER_CHECK | B121: Гостиница — ужины | C121: Средний чек ужина | D121: 1000 | E121: руб./ужин | F121: Рабочее допущение | G121: Средний чек ужина 1 000 руб.; требуется бизнес-подтверждение.
A122: S03_DINNER_COGS | B122: Гостиница — ужины | C122: Food cost ужина — как a-la carte | D122: =D24 | E122: % выручки | F122: Расчёт | G122: Автоматически связано с ALA_COGS: food cost ужина равен food cost a-la carte.
A123: S03_DINNER_PACK | B123: Гостиница — ужины | C123: Упаковка / расходники ужина | D123: 0 | E123: руб./ужин | F123: Рабочее допущение | G123: Наследовано из S02; требует подтверждения.
A124: S03_DINNER_CASHLESS | B124: Гостиница — ужины | C124: Доля безналичной оплаты ужина | D124: 1 | E124: % | F124: Рабочее допущение | G124: Наследовано из S02; требует подтверждения.

Sheet 02_КАЛЕНДАРЬ
A1: Календарь операционной модели: 01.09.2026–31.08.2027
A2: Банкеты: с ноября по 6 в месяц. В банкетный день завтраки, бизнес-ланч, доставка и самовывоз работают на 100%; а-ля карт — 20% до 17:00. Ужины гостиницы — 50% от завтраков ежедневно.
A4: Дата | B4: № месяца | C4: Месяц | D4: № дня недели | E4: День недели | F4: Праздник 1/0 | G4: Статус праздника | H4: Банкет 1/0 | I4: Категория банкета | J4: Кафе открыто | K4: Рабочий день | L4: Норма а-ля карт | M4: Гости а-ля карт | N4: Гости бизнес-ланча | O4: Норма доставки | P4: Заказы доставки | Q4: Самовывоз | R4: Завтраки гостиницы | S4: Банкеты | T4: Активные продажи кафе в банкет | U4: Ужины гостиницы
A5: 46266 | B5: 1 | C5: Сен-26 | D5: 2 | E5: Вт | F5: 0 | H5: 0 | J5: =1 | K5: =IF(AND(D5<=5,F5=0),1,0) | L5: =IF(F5=1,'01_ВВОД'!$D$23,CHOOSE(D5,'01_ВВОД'!$D$19,'01_ВВОД'!$D$19,'01_ВВОД'!$D$19,'01_ВВОД'!$D$19,'01_ВВОД'!$D$20,'01_ВВОД'!$D$21,'01_ВВОД'!$D$22)) | M5: =L5*IF(H5=1,'01_ВВОД'!$D$118,1) | N5: =IF(K5=1,'01_ВВОД'!$D$26,0) | O5: =IF(F5=1,'01_ВВОД'!$D$34,IF(D5<=5,'01_ВВОД'!$D$32,'01_ВВОД'!$D$33)) | P5: =O5 | Q5: ='01_ВВОД'!$D$40 | R5: ='01_ВВОД'!$D$46 | S5: =H5 | T5: =IF(H5=1,M5+N5+P5+Q5,0) | U5: =R5*'01_ВВОД'!$D$120
A6: 46267 | B6: 1 | C6: Сен-26 | D6: 3 | E6: Ср | F6: 0 | H6: 0 | J6: =1 | K6: =IF(AND(D6<=5,F6=0),1,0) | L6: =IF(F6=1,'01_ВВОД'!$D$23,CHOOSE(D6,'01_ВВОД'!$D$19,'01_ВВОД'!$D$19,'01_ВВОД'!$D$19,'01_ВВОД'!$D$19,'01_ВВОД'!$D$20,'01_ВВОД'!$D$21,'01_ВВОД'!$D$22)) | M6: =L6*IF(H6=1,'01_ВВОД'!$D$118,1) | N6: =IF(K6=1,'01_ВВОД'!$D$26,0) | O6: =IF(F6=1,'01_ВВОД'!$D$34,IF(D6<=5,'01_ВВОД'!$D$32,'01_ВВОД'!$D$33)) | P6: =O6 | Q6: ='01_ВВОД'!$D$40 | R6: ='01_ВВОД'!$D$46 | S6: =H6 | T6: =IF(H6=1,M6+N6+P6+Q6,0) | U6: =R6*'01_ВВОД'!$D$120
A7: 46268 | B7: 1 | C7: Сен-26 | D7: 4 | E7: Чт | F7: 0 | H7: 0 | J7: =1 | K7: =IF(AND(D7<=5,F7=0),1,0) | L7: =IF(F7=1,'01_ВВОД'!$D$23,CHOOSE(D7,'01_ВВОД'!$D$19,'01_ВВОД'!$D$19,'01_ВВОД'!$D$19,'01_ВВОД'!$D$19,'01_ВВОД'!$D$20,'01_ВВОД'!$D$21,'01_ВВОД'!$D$22)) | M7: =L7*IF(H7=1,'01_ВВОД'!$D$118,1) | N7: =IF(K7=1,'01_ВВОД'!$D$26,0) | O7: =IF(F7=1,'01_ВВОД'!$D$34,IF(D7<=5,'01_ВВОД'!$D$32,'01_ВВОД'!$D$33)) | P7: =O7 | Q7: ='01_ВВОД'!$D$40 | R7: ='01_ВВОД'!$D$46 | S7: =H7 | T7: =IF(H7=1,M7+N7+P7+Q7,0) | U7: =R7*'01_ВВОД'!$D$120
A8: 46269 | B8: 1 | C8: Сен-26 | D8: 5 | E8: Пт | F8: 0 | H8: 0 | J8: =1 | K8: =IF(AND(D8<=5,F8=0),1,0) | L8: =IF(F8=1,'01_ВВОД'!$D$23,CHOOSE(D8,'01_ВВОД'!$D$19,'01_ВВОД'!$D$19,'01_ВВОД'!$D$19,'01_ВВОД'!$D$19,'01_ВВОД'!$D$20,'01_ВВОД'!$D$21,'01_ВВОД'!$D$22)) | M8: =L8*IF(H8=1,'01_ВВОД'!$D$118,1) | N8: =IF(K8=1,'01_ВВОД'!$D$26,0) | O8: =IF(F8=1,'01_ВВОД'!$D$34,IF(D8<=5,'01_ВВОД'!$D$32,'01_ВВОД'!$D$33)) | P8: =O8 | Q8: ='01_ВВОД'!$D$40 | R8: ='01_ВВОД'!$D$46 | S8: =H8 | T8: =IF(H8=1,M8+N8+P8+Q8,0) | U8: =R8*'01_ВВОД'!$D$120
A9: 46270 | B9: 1 | C9: Сен-26 | D9: 6 | E9: Сб | F9: 0 | H9: 0 | J9: =1 | K9: =IF(AND(D9<=5,F9=0),1,0) | L9: =IF(F9=1,'01_ВВОД'!$D$23,CHOOSE(D9,'01_ВВОД'!$D$19,'01_ВВОД'!$D$19,'01_ВВОД'!$D$19,'01_ВВОД'!$D$19,'01_ВВОД'!$D$20,'01_ВВОД'!$D$21,'01_ВВОД'!$D$22)) | M9: =L9*IF(H9=1,'01_ВВОД'!$D$118,1) | N9: =IF(K9=1,'01_ВВОД'!$D$26,0) | O9: =IF(F9=1,'01_ВВОД'!$D$34,IF(D9<=5,'01_ВВОД'!$D$32,'01_ВВОД'!$D$33)) | P9: =O9 | Q9: ='01_ВВОД'!$D$40 | R9: ='01_ВВОД'!$D$46 | S9: =H9 | T9: =IF(H9=1,M9+N9+P9+Q9,0) | U9: =R9*'01_ВВОД'!$D$120
A10: 46271 | B10: 1 | C10: Сен-26 | D10: 7 | E10: Вс | F10: 0 | H10: 0 | J10: =1 | K10: =IF(AND(D10<=5,F10=0),1,0) | L10: =IF(F10=1,'01_ВВОД'!$D$23,CHOOSE(D10,'01_ВВОД'!$D$19,'01_ВВОД'!$D$19,'01_ВВОД'!$D$19,'01_ВВОД'!$D$19,'01_ВВОД'!$D$20,'01_ВВОД'!$D$21,'01_ВВОД'!$D$22)) | M10: =L10*IF(H10=1,'01_ВВОД'!$D$118,1) | N10: =IF(K10=1,'01_ВВОД'!$D$26,0) | O10: =IF(F10=1,'01_ВВОД'!$D$34,IF(D10<=5,'01_ВВОД'!$D$32,'01_ВВОД'!$D$33)) | P10: =O10 | Q10: ='01_ВВОД'!$D$40 | R10: ='01_ВВОД'!$D$46 | S10: =H10 | T10: =IF(H10=1,M10+N10+P10+Q10,0) | U10: =R10*'01_ВВОД'!$D$120
A11: 46272 | B11: 1 | C11: Сен-26 | D11: 1 | E11: Пн | F11: 0 | H11: 0 | J11: =1 | K11: =IF(AND(D11<=5,F11=0),1,0) | L11: =IF(F11=1,'01_ВВОД'!$D$23,CHOOSE(D11,'01_ВВОД'!$D$19,'01_ВВОД'!$D$19,'01_ВВОД'!$D$19,'01_ВВОД'!$D$19,'01_ВВОД'!$D$20,'01_ВВОД'!$D$21,'01_ВВОД'!$D$22)) | M11: =L11*IF(H11=1,'01_ВВОД'!$D$118,1) | N11: =IF(K11=1,'01_ВВОД'!$D$26,0) | O11: =IF(F11=1,'01_ВВОД'!$D$34,IF(D11<=5,'01_ВВОД'!$D$32,'01_ВВОД'!$D$33)) | P11: =O11 | Q11: ='01_ВВОД'!$D$40 | R11: ='01_ВВОД'!$D$46 | S11: =H11 | T11: =IF(H11=1,M11+N11+P11+Q11,0) | U11: =R11*'01_ВВОД'!$D$120
A12: 46273 | B12: 1 | C12: Сен-26 | D12: 2 | E12: Вт | F12: 0 | H12: 0 | J12: =1 | K12: =IF(AND(D12<=5,F12=0),1,0) | L12: =IF(F12=1,'01_ВВОД'!$D$23,CHOOSE(D12,'01_ВВОД'!$D$19,'01_ВВОД'!$D$19,'01_ВВОД'!$D$19,'01_ВВОД'!$D$19,'01_ВВОД'!$D$20,'01_ВВОД'!$D$21,'01_ВВОД'!$D$22)) | M12: =L12*IF(H12=1,'01_ВВОД'!$D$118,1) | N12: =IF(K12=1,'01_ВВОД'!$D$26,0) | O12: =IF(F12=1,'01_ВВОД'!$D$34,IF(D12<=5,'01_ВВОД'!$D$32,'01_ВВОД'!$D$33)) | P12: =O12 | Q12: ='01_ВВОД'!$D$40 | R12: ='01_ВВОД'!$D$46 | S12: =H12 | T12: =IF(H12=1,M12+N12+P12+Q12,0) | U12: =R12*'01_ВВОД'!$D$120
A13: 46274 | B13: 1 | C13: Сен-26 | D13: 3 | E13: Ср | F13: 0 | H13: 0 | J13: =1 | K13: =IF(AND(D13<=5,F13=0),1,0) | L13: =IF(F13=1,'01_ВВОД'!$D$23,CHOOSE(D13,'01_ВВОД'!$D$19,'01_ВВОД'!$D$19,'01_ВВОД'!$D$19,'01_ВВОД'!$D$19,'01_ВВОД'!$D$20,'01_ВВОД'!$D$21,'01_ВВОД'!$D$22)) | M13: =L13*IF(H13=1,'01_ВВОД'!$D$118,1) | N13: =IF(K13=1,'01_ВВОД'!$D$26,0) | O13: =IF(F13=1,'01_ВВОД'!$D$34,IF(D13<=5,'01_ВВОД'!$D$32,'01_ВВОД'!$D$33)) | P13: =O13 | Q13: ='01_ВВОД'!$D$40 | R13: ='01_ВВОД'!$D$46 | S13: =H13 | T13: =IF(H13=1,M13+N13+P13+Q13,0) | U13: =R13*'01_ВВОД'!$D$120
A14: 46275 | B14: 1 | C14: Сен-26 | D14: 4 | E14: Чт | F14: 0 | H14: 0 | J14: =1 | K14: =IF(AND(D14<=5,F14=0),1,0) | L14: =IF(F14=1,'01_ВВОД'!$D$23,CHOOSE(D14,'01_ВВОД'!$D$19,'01_ВВОД'!$D$19,'01_ВВОД'!$D$19,'01_ВВОД'!$D$19,'01_ВВОД'!$D$20,'01_ВВОД'!$D$21,'01_ВВОД'!$D$22)) | M14: =L14*IF(H14=1,'01_ВВОД'!$D$118,1) | N14: =IF(K14=1,'01_ВВОД'!$D$26,0) | O14: =IF(F14=1,'01_ВВОД'!$D$34,IF(D14<=5,'01_ВВОД'!$D$32,'01_ВВОД'!$D$33)) | P14: =O14 | Q14: ='01_ВВОД'!$D$40 | R14: ='01_ВВОД'!$D$46 | S14: =H14 | T14: =IF(H14=1,M14+N14+P14+Q14,0) | U14: =R14*'01_ВВОД'!$D$120
A15: 46276 | B15: 1 | C15: Сен-26 | D15: 5 | E15: Пт | F15: 0 | H15: 0 | J15: =1 | K15: =IF(AND(D15<=5,F15=0),1,0) | L15: =IF(F15=1,'01_ВВОД'!$D$23,CHOOSE(D15,'01_ВВОД'!$D$19,'01_ВВОД'!$D$19,'01_ВВОД'!$D$19,'01_ВВОД'!$D$19,'01_ВВОД'!$D$20,'01_ВВОД'!$D$21,'01_ВВОД'!$D$22)) | M15: =L15*IF(H15=1,'01_ВВОД'!$D$118,1) | N15: =IF(K15=1,'01_ВВОД'!$D$26,0) | O15: =IF(F15=1,'01_ВВОД'!$D$34,IF(D15<=5,'01_ВВОД'!$D$32,'01_ВВОД'!$D$33)) | P15: =O15 | Q15: ='01_ВВОД'!$D$40 | R15: ='01_ВВОД'!$D$46 | S15: =H15 | T15: =IF(H15=1,M15+N15+P15+Q15,0) | U15: =R15*'01_ВВОД'!$D$120
A16: 46277 | B16: 1 | C16: Сен-26 | D16: 6 | E16: Сб | F16: 0 | H16: 0 | J16: =1 | K16: =IF(AND(D16<=5,F16=0),1,0) | L16: =IF(F16=1,'01_ВВОД'!$D$23,CHOOSE(D16,'01_ВВОД'!$D$19,'01_ВВОД'!$D$19,'01_ВВОД'!$D$19,'01_ВВОД'!$D$19,'01_ВВОД'!$D$20,'01_ВВОД'!$D$21,'01_ВВОД'!$D$22)) | M16: =L16*IF(H16=1,'01_ВВОД'!$D$118,1) | N16: =IF(K16=1,'01_ВВОД'!$D$26,0) | O16: =IF(F16=1,'01_ВВОД'!$D$34,IF(D16<=5,'01_ВВОД'!$D$32,'01_ВВОД'!$D$33)) | P16: =O16 | Q16: ='01_ВВОД'!$D$40 | R16: ='01_ВВОД'!$D$46 | S16: =H16 | T16: =IF(H16=1,M16+N16+P16+Q16,0) | U16: =R16*'01_ВВОД'!$D$120
... A68: 46329 | B68: 3 | C68: Ноя-26 | D68: 2 | E68: Вт | F68: 0 | H68: 0 | J68: =1 | K68: =IF(AND(D68<=5,F68=0),1,0) | L68: =IF(F68=1,'01_ВВОД'!$D$23,CHOOSE(D68,'01_ВВОД'!$D$19,'01_ВВОД'!$D$19,'01_ВВОД'!$D$19,'01_ВВОД'!$D$19,'01_ВВОД'!$D$20,'01_ВВОД'!$D$21,'01_ВВОД'!$D$22)) | M68: =L68*IF(H68=1,'01_ВВОД'!$D$118,1) | N68: =IF(K68=1,'01_ВВОД'!$D$26,0) | O68: =IF(F68=1,'01_ВВОД'!$D$34,IF(D68<=5,'01_ВВОД'!$D$32,'01_ВВОД'!$D$33)) | P68: =O68 | Q68: ='01_ВВОД'!$D$40 | R68: ='01_ВВОД'!$D$46 | S68: =H68 | T68: =IF(H68=1,M68+N68+P68+Q68,0) | U68: =R68*'01_ВВОД'!$D$120
A69: 46330 | B69: 3 | C69: Ноя-26 | D69: 3 | E69: Ср | F69: 1 | G69: Подтверждено для 2026 | H69: 0 | J69: =1 | K69: =IF(AND(D69<=5,F69=0),1,0) | L69: =IF(F69=1,'01_ВВОД'!$D$23,CHOOSE(D69,'01_ВВОД'!$D$19,'01_ВВОД'!$D$19,'01_ВВОД'!$D$19,'01_ВВОД'!$D$19,'01_ВВОД'!$D$20,'01_ВВОД'!$D$21,'01_ВВОД'!$D$22)) | M69: =L69*IF(H69=1,'01_ВВОД'!$D$118,1) | N69: =IF(K69=1,'01_ВВОД'!$D$26,0) | O69: =IF(F69=1,'01_ВВОД'!$D$34,IF(D69<=5,'01_ВВОД'!$D$32,'01_ВВОД'!$D$33)) | P69: =O69 | Q69: ='01_ВВОД'!$D$40 | R69: ='01_ВВОД'!$D$46 | S69: =H69 | T69: =IF(H69=1,M69+N69+P69+Q69,0) | U69: =R69*'01_ВВОД'!$D$120
A70: 46331 | B70: 3 | C70: Ноя-26 | D70: 4 | E70: Чт | F70: 0 | H70: 0 | J70: =1 | K70: =IF(AND(D70<=5,F70=0),1,0) | L70: =IF(F70=1,'01_ВВОД'!$D$23,CHOOSE(D70,'01_ВВОД'!$D$19,'01_ВВОД'!$D$19,'01_ВВОД'!$D$19,'01_ВВОД'!$D$19,'01_ВВОД'!$D$20,'01_ВВОД'!$D$21,'01_ВВОД'!$D$22)) | M70: =L70*IF(H70=1,'01_ВВОД'!$D$118,1) | N70: =IF(K70=1,'01_ВВОД'!$D$26,0) | O70: =IF(F70=1,'01_ВВОД'!$D$34,IF(D70<=5,'01_ВВОД'!$D$32,'01_ВВОД'!$D$33)) | P70: =O70 | Q70: ='01_ВВОД'!$D$40 | R70: ='01_ВВОД'!$D$46 | S70: =H70 | T70: =IF(H70=1,M70+N70+P70+Q70,0) | U70: =R70*'01_ВВОД'!$D$120
A71: 46332 | B71: 3 | C71: Ноя-26 | D71: 5 | E71: Пт | F71: 0 | H71: 0 | J71: =1 | K71: =IF(AND(D71<=5,F71=0),1,0) | L71: =IF(F71=1,'01_ВВОД'!$D$23,CHOOSE(D71,'01_ВВОД'!$D$19,'01_ВВОД'!$D$19,'01_ВВОД'!$D$19,'01_ВВОД'!$D$19,'01_ВВОД'!$D$20,'01_ВВОД'!$D$21,'01_ВВОД'!$D$22)) | M71: =L71*IF(H71=1,'01_ВВОД'!$D$118,1) | N71: =IF(K71=1,'01_ВВОД'!$D$26,0) | O71: =IF(F71=1,'01_ВВОД'!$D$34,IF(D71<=5,'01_ВВОД'!$D$32,'01_ВВОД'!$D$33)) | P71: =O71 | Q71: ='01_ВВОД'!$D$40 | R71: ='01_ВВОД'!$D$46 | S71: =H71 | T71: =IF(H71=1,M71+N71+P71+Q71,0) | U71: =R71*'01_ВВОД'!$D$120
A72: 46333 | B72: 3 | C72: Ноя-26 | D72: 6 | E72: Сб | F72: 0 | H72: 1 | I72: Пт–Вс | J72: =1 | K72: =IF(AND(D72<=5,F72=0),1,0) | L72: =IF(F72=1,'01_ВВОД'!$D$23,CHOOSE(D72,'01_ВВОД'!$D$19,'01_ВВОД'!$D$19,'01_ВВОД'!$D$19,'01_ВВОД'!$D$19,'01_ВВОД'!$D$20,'01_ВВОД'!$D$21,'01_ВВОД'!$D$22)) | M72: =L72*IF(H72=1,'01_ВВОД'!$D$118,1) | N72: =IF(K72=1,'01_ВВОД'!$D$26,0) | O72: =IF(F72=1,'01_ВВОД'!$D$34,IF(D72<=5,'01_ВВОД'!$D$32,'01_ВВОД'!$D$33)) | P72: =O72 | Q72: ='01_ВВОД'!$D$40 | R72: ='01_ВВОД'!$D$46 | S72: =H72 | T72: =IF(H72=1,M72+N72+P72+Q72,0) | U72: =R72*'01_ВВОД'!$D$120
A73: 46334 | B73: 3 | C73: Ноя-26 | D73: 7 | E73: Вс | F73: 0 | H73: 0 | J73: =1 | K73: =IF(AND(D73<=5,F73=0),1,0) | L73: =IF(F73=1,'01_ВВОД'!$D$23,CHOOSE(D73,'01_ВВОД'!$D$19,'01_ВВОД'!$D$19,'01_ВВОД'!$D$19,'01_ВВОД'!$D$19,'01_ВВОД'!$D$20,'01_ВВОД'!$D$21,'01_ВВОД'!$D$22)) | M73: =L73*IF(H73=1,'01_ВВОД'!$D$118,1) | N73: =IF(K73=1,'01_ВВОД'!$D$26,0) | O73: =IF(F73=1,'01_ВВОД'!$D$34,IF(D73<=5,'01_ВВОД'!$D$32,'01_ВВОД'!$D$33)) | P73: =O73 | Q73: ='01_ВВОД'!$D$40 | R73: ='01_ВВОД'!$D$46 | S73: =H73 | T73: =IF(H73=1,M73+N73+P73+Q73,0) | U73: =R73*'01_ВВОД'!$D$120
A74: 46335 | B74: 3 | C74: Ноя-26 | D74: 1 | E74: Пн | F74: 0 | H74: 0 | J74: =1 | K74: =IF(AND(D74<=5,F74=0),1,0) | L74: =IF(F74=1,'01_ВВОД'!$D$23,CHOOSE(D74,'01_ВВОД'!$D$19,'01_ВВОД'!$D$19,'01_ВВОД'!$D$19,'01_ВВОД'!$D$19,'01_ВВОД'!$D$20,'01_ВВОД'!$D$21,'01_ВВОД'!$D$22)) | M74: =L74*IF(H74=1,'01_ВВОД'!$D$118,1) | N74: =IF(K74=1,'01_ВВОД'!$D$26,0) | O74: =IF(F74=1,'01_ВВОД'!$D$34,IF(D74<=5,'01_ВВОД'!$D$32,'01_ВВОД'!$D$33)) | P74: =O74 | Q74: ='01_ВВОД'!$D$40 | R74: ='01_ВВОД'!$D$46 | S74: =H74 | T74: =IF(H74=1,M74+N74+P74+Q74,0) | U74: =R74*'01_ВВОД'!$D$120
A75: 46336 | B75: 3 | C75: Ноя-26 | D75: 2 | E75: Вт | F75: 0 | H75: 0 | J75: =1 | K75: =IF(AND(D75<=5,F75=0),1,0) | L75: =IF(F75=1,'01_ВВОД'!$D$23,CHOOSE(D75,'01_ВВОД'!$D$19,'01_ВВОД'!$D$19,'01_ВВОД'!$D$19,'01_ВВОД'!$D$19,'01_ВВОД'!$D$20,'01_ВВОД'!$D$21,'01_ВВОД'!$D$22)) | M75: =L75*IF(H75=1,'01_ВВОД'!$D$118,1) | N75: =IF(K75=1,'01_ВВОД'!$D$26,0) | O75: =IF(F75=1,'01_ВВОД'!$D$34,IF(D75<=5,'01_ВВОД'!$D$32,'01_ВВОД'!$D$33)) | P75: =O75 | Q75: ='01_ВВОД'!$D$40 | R75: ='01_ВВОД'!$D$46 | S75: =H75 | T75: =IF(H75=1,M75+N75+P75+Q75,0) | U75: =R75*'01_ВВОД'!$D$120
A76: 46337 | B76: 3 | C76: Ноя-26 | D76: 3 | E76: Ср | F76: 0 | H76: 0 | J76: =1 | K76: =IF(AND(D76<=5,F76=0),1,0) | L76: =IF(F76=1,'01_ВВОД'!$D$23,CHOOSE(D76,'01_ВВОД'!$D$19,'01_ВВОД'!$D$19,'01_ВВОД'!$D$19,'01_ВВОД'!$D$19,'01_ВВОД'!$D$20,'01_ВВОД'!$D$21,'01_ВВОД'!$D$22)) | M76: =L76*IF(H76=1,'01_ВВОД'!$D$118,1) | N76: =IF(K76=1,'01_ВВОД'!$D$26,0) | O76: =IF(F76=1,'01_ВВОД'!$D$34,IF(D76<=5,'01_ВВОД'!$D$32,'01_ВВОД'!$D$33)) | P76: =O76 | Q76: ='01_ВВОД'!$D$40 | R76: ='01_ВВОД'!$D$46 | S76: =H76 | T76: =IF(H76=1,M76+N76+P76+Q76,0) | U76: =R76*'01_ВВОД'!$D$120
A77: 46338 | B77: 3 | C77: Ноя-26 | D77: 4 | E77: Чт | F77: 0 | H77: 0 | J77: =1 | K77: =IF(AND(D77<=5,F77=0),1,0) | L77: =IF(F77=1,'01_ВВОД'!$D$23,CHOOSE(D77,'01_ВВОД'!$D$19,'01_ВВОД'!$D$19,'01_ВВОД'!$D$19,'01_ВВОД'!$D$19,'01_ВВОД'!$D$20,'01_ВВОД'!$D$21,'01_ВВОД'!$D$22)) | M77: =L77*IF(H77=1,'01_ВВОД'!$D$118,1) | N77: =IF(K77=1,'01_ВВОД'!$D$26,0) | O77: =IF(F77=1,'01_ВВОД'!$D$34,IF(D77<=5,'01_ВВОД'!$D$32,'01_ВВОД'!$D$33)) | P77: =O77 | Q77: ='01_ВВОД'!$D$40 | R77: ='01_ВВОД'!$D$46 | S77: =H77 | T77: =IF(H77=1,M77+N77+P77+Q77,0) | U77: =R77*'01_ВВОД'!$D$120
A78: 46339 | B78: 3 | C78: Ноя-26 | D78: 5 | E78: Пт | F78: 0 | H78: 1 | I78: Пт–Вс | J78: =1 | K78: =IF(AND(D78<=5,F78=0),1,0) | L78: =IF(F78=1,'01_ВВОД'!$D$23,CHOOSE(D78,'01_ВВОД'!$D$19,'01_ВВОД'!$D$19,'01_ВВОД'!$D$19,'01_ВВОД'!$D$19,'01_ВВОД'!$D$20,'01_ВВОД'!$D$21,'01_ВВОД'!$D$22)) | M78: =L78*IF(H78=1,'01_ВВОД'!$D$118,1) | N78: =IF(K78=1,'01_ВВОД'!$D$26,0) | O78: =IF(F78=1,'01_ВВОД'!$D$34,IF(D78<=5,'01_ВВОД'!$D$32,'01_ВВОД'!$D$33)) | P78: =O78 | Q78: ='01_ВВОД'!$D$40 | R78: ='01_ВВОД'!$D$46 | S78: =H78 | T78: =IF(H78=1,M78+N78+P78+Q78,0) | U78: =R78*'01_ВВОД'!$D$120
A79: 46340 | B79: 3 | C79: Ноя-26 | D79: 6 | E79: Сб | F79: 0 | H79: 0 | J79: =1 | K79: =IF(AND(D79<=5,F79=0),1,0) | L79: =IF(F79=1,'01_ВВОД'!$D$23,CHOOSE(D79,'01_ВВОД'!$D$19,'01_ВВОД'!$D$19,'01_ВВОД'!$D$19,'01_ВВОД'!$D$19,'01_ВВОД'!$D$20,'01_ВВОД'!$D$21,'01_ВВОД'!$D$22)) | M79: =L79*IF(H79=1,'01_ВВОД'!$D$118,1) | N79: =IF(K79=1,'01_ВВОД'!$D$26,0) | O79: =IF(F79=1,'01_ВВОД'!$D$34,IF(D79<=5,'01_ВВОД'!$D$32,'01_ВВОД'!$D$33)) | P79: =O79 | Q79: ='01_ВВОД'!$D$40 | R79: ='01_ВВОД'!$D$46 | S79: =H79 | T79: =IF(H79=1,M79+N79+P79+Q79,0) | U79: =R79*'01_ВВОД'!$D$120
A80: 46341 | B80: 3 | C80: Ноя-26 | D80: 7 | E80: Вс | F80: 0 | H80: 1 | I80: Пт–Вс | J80: =1 | K80: =IF(AND(D80<=5,F80=0),1,0) | L80: =IF(F80=1,'01_ВВОД'!$D$23,CHOOSE(D80,'01_ВВОД'!$D$19,'01_ВВОД'!$D$19,'01_ВВОД'!$D$19,'01_ВВОД'!$D$19,'01_ВВОД'!$D$20,'01_ВВОД'!$D$21,'01_ВВОД'!$D$22)) | M80: =L80*IF(H80=1,'01_ВВОД'!$D$118,1) | N80: =IF(K80=1,'01_ВВОД'!$D$26,0) | O80: =IF(F80=1,'01_ВВОД'!$D$34,IF(D80<=5,'01_ВВОД'!$D$32,'01_ВВОД'!$D$33)) | P80: =O80 | Q80: ='01_ВВОД'!$D$40 | R80: ='01_ВВОД'!$D$46 | S80: =H80 | T80: =IF(H80=1,M80+N80+P80+Q80,0) | U80: =R80*'01_ВВОД'!$D$120
A81: 46342 | B81: 3 | C81: Ноя-26 | D81: 1 | E81: Пн | F81: 0 | H81: 1 | I81: Пн–Чт | J81: =1 | K81: =IF(AND(D81<=5,F81=0),1,0) | L81: =IF(F81=1,'01_ВВОД'!$D$23,CHOOSE(D81,'01_ВВОД'!$D$19,'01_ВВОД'!$D$19,'01_ВВОД'!$D$19,'01_ВВОД'!$D$19,'01_ВВОД'!$D$20,'01_ВВОД'!$D$21,'01_ВВОД'!$D$22)) | M81: =L81*IF(H81=1,'01_ВВОД'!$D$118,1) | N81: =IF(K81=1,'01_ВВОД'!$D$26,0) | O81: =IF(F81=1,'01_ВВОД'!$D$34,IF(D81<=5,'01_ВВОД'!$D$32,'01_ВВОД'!$D$33)) | P81: =O81 | Q81: ='01_ВВОД'!$D$40 | R81: ='01_ВВОД'!$D$46 | S81: =H81 | T81: =IF(H81=1,M81+N81+P81+Q81,0) | U81: =R81*'01_ВВОД'!$D$120
A82: 46343 | B82: 3 | C82: Ноя-26 | D82: 2 | E82: Вт | F82: 0 | H82: 0 | J82: =1 | K82: =IF(AND(D82<=5,F82=0),1,0) | L82: =IF(F82=1,'01_ВВОД'!$D$23,CHOOSE(D82,'01_ВВОД'!$D$19,'01_ВВОД'!$D$19,'01_ВВОД'!$D$19,'01_ВВОД'!$D$19,'01_ВВОД'!$D$20,'01_ВВОД'!$D$21,'01_ВВОД'!$D$22)) | M82: =L82*IF(H82=1,'01_ВВОД'!$D$118,1) | N82: =IF(K82=1,'01_ВВОД'!$D$26,0) | O82: =IF(F82=1,'01_ВВОД'!$D$34,IF(D82<=5,'01_ВВОД'!$D$32,'01_ВВОД'!$D$33)) | P82: =O82 | Q82: ='01_ВВОД'!$D$40 | R82: ='01_ВВОД'!$D$46 | S82: =H82 | T82: =IF(H82=1,M82+N82+P82+Q82,0) | U82: =R82*'01_ВВОД'!$D$120
A83: 46344 | B83: 3 | C83: Ноя-26 | D83: 3 | E83: Ср | F83: 0 | H83: 0 | J83: =1 | K83: =IF(AND(D83<=5,F83=0),1,0) | L83: =IF(F83=1,'01_ВВОД'!$D$23,CHOOSE(D83,'01_ВВОД'!$D$19,'01_ВВОД'!$D$19,'01_ВВОД'!$D$19,'01_ВВОД'!$D$19,'01_ВВОД'!$D$20,'01_ВВОД'!$D$21,'01_ВВОД'!$D$22)) | M83: =L83*IF(H83=1,'01_ВВОД'!$D$118,1) | N83: =IF(K83=1,'01_ВВОД'!$D$26,0) | O83: =IF(F83=1,'01_ВВОД'!$D$34,IF(D83<=5,'01_ВВОД'!$D$32,'01_ВВОД'!$D$33)) | P83: =O83 | Q83: ='01_ВВОД'!$D$40 | R83: ='01_ВВОД'!$D$46 | S83: =H83 | T83: =IF(H83=1,M83+N83+P83+Q83,0) | U83: =R83*'01_ВВОД'!$D$120
A84: 46345 | B84: 3 | C84: Ноя-26 | D84: 4 | E84: Чт | F84: 0 | H84: 0 | J84: =1 | K84: =IF(AND(D84<=5,F84=0),1,0) | L84: =IF(F84=1,'01_ВВОД'!$D$23,CHOOSE(D84,'01_ВВОД'!$D$19,'01_ВВОД'!$D$19,'01_ВВОД'!$D$19,'01_ВВОД'!$D$19,'01_ВВОД'!$D$20,'01_ВВОД'!$D$21,'01_ВВОД'!$D$22)) | M84: =L84*IF(H84=1,'01_ВВОД'!$D$118,1) | N84: =IF(K84=1,'01_ВВОД'!$D$26,0) | O84: =IF(F84=1,'01_ВВОД'!$D$34,IF(D84<=5,'01_ВВОД'!$D$32,'01_ВВОД'!$D$33)) | P84: =O84 | Q84: ='01_ВВОД'!$D$40 | R84: ='01_ВВОД'!$D$46 | S84: =H84 | T84: =IF(H84=1,M84+N84+P84+Q84,0) | U84: =R84*'01_ВВОД'!$D$120
A85: 46346 | B85: 3 | C85: Ноя-26 | D85: 5 | E85: Пт | F85: 0 | H85: 1 | I85: Пт–Вс | J85: =1 | K85: =IF(AND(D85<=5,F85=0),1,0) | L85: =IF(F85=1,'01_ВВОД'!$D$23,CHOOSE(D85,'01_ВВОД'!$D$19,'01_ВВОД'!$D$19,'01_ВВОД'!$D$19,'01_ВВОД'!$D$19,'01_ВВОД'!$D$20,'01_ВВОД'!$D$21,'01_ВВОД'!$D$22)) | M85: =L85*IF(H85=1,'01_ВВОД'!$D$118,1) | N85: =IF(K85=1,'01_ВВОД'!$D$26,0) | O85: =IF(F85=1,'01_ВВОД'!$D$34,IF(D85<=5,'01_ВВОД'!$D$32,'01_ВВОД'!$D$33)) | P85: =O85 | Q85: ='01_ВВОД'!$D$40 | R85: ='01_ВВОД'!$D$46 | S85: =H85 | T85: =IF(H85=1,M85+N85+P85+Q85,0) | U85: =R85*'01_ВВОД'!$D$120
A86: 46347 | B86: 3 | C86: Ноя-26 | D86: 6 | E86: Сб | F86: 0 | H86: 0 | J86: =1 | K86: =IF(AND(D86<=5,F86=0),1,0) | L86: =IF(F86=1,'01_ВВОД'!$D$23,CHOOSE(D86,'01_ВВОД'!$D$19,'01_ВВОД'!$D$19,'01_ВВОД'!$D$19,'01_ВВОД'!$D$19,'01_ВВОД'!$D$20,'01_ВВОД'!$D$21,'01_ВВОД'!$D$22)) | M86: =L86*IF(H86=1,'01_ВВОД'!$D$118,1) | N86: =IF(K86=1,'01_ВВОД'!$D$26,0) | O86: =IF(F86=1,'01_ВВОД'!$D$34,IF(D86<=5,'01_ВВОД'!$D$32,'01_ВВОД'!$D$33)) | P86: =O86 | Q86: ='01_ВВОД'!$D$40 | R86: ='01_ВВОД'!$D$46 | S86: =H86 | T86: =IF(H86=1,M86+N86+P86+Q86,0) | U86: =R86*'01_ВВОД'!$D$120
A87: 46348 | B87: 3 | C87: Ноя-26 | D87: 7 | E87: Вс | F87: 0 | H87: 0 | J87: =1 | K87: =IF(AND(D87<=5,F87=0),1,0) | L87: =IF(F87=1,'01_ВВОД'!$D$23,CHOOSE(D87,'01_ВВОД'!$D$19,'01_ВВОД'!$D$19,'01_ВВОД'!$D$19,'01_ВВОД'!$D$19,'01_ВВОД'!$D$20,'01_ВВОД'!$D$21,'01_ВВОД'!$D$22)) | M87: =L87*IF(H87=1,'01_ВВОД'!$D$118,1) | N87: =IF(K87=1,'01_ВВОД'!$D$26,0) | O87: =IF(F87=1,'01_ВВОД'!$D$34,IF(D87<=5,'01_ВВОД'!$D$32,'01_ВВОД'!$D$33)) | P87: =O87 | Q87: ='01_ВВОД'!$D$40 | R87: ='01_ВВОД'!$D$46 | S87: =H87 | T87: =IF(H87=1,M87+N87+P87+Q87,0) | U87: =R87*'01_ВВОД'!$D$120
A88: 46349 | B88: 3 | C88: Ноя-26 | D88: 1 | E88: Пн | F88: 0 | H88: 0 | J88: =1 | K88: =IF(AND(D88<=5,F88=0),1,0) | L88: =IF(F88=1,'01_ВВОД'!$D$23,CHOOSE(D88,'01_ВВОД'!$D$19,'01_ВВОД'!$D$19,'01_ВВОД'!$D$19,'01_ВВОД'!$D$19,'01_ВВОД'!$D$20,'01_ВВОД'!$D$21,'01_ВВОД'!$D$22)) | M88: =L88*IF(H88=1,'01_ВВОД'!$D$118,1) | N88: =IF(K88=1,'01_ВВОД'!$D$26,0) | O88: =IF(F88=1,'01_ВВОД'!$D$34,IF(D88<=5,'01_ВВОД'!$D$32,'01_ВВОД'!$D$33)) | P88: =O88 | Q88: ='01_ВВОД'!$D$40 | R88: ='01_ВВОД'!$D$46 | S88: =H88 | T88: =IF(H88=1,M88+N88+P88+Q88,0) | U88: =R88*'01_ВВОД'!$D$120
A89: 46350 | B89: 3 | C89: Ноя-26 | D89: 2 | E89: Вт | F89: 0 | H89: 0 | J89: =1 | K89: =IF(AND(D89<=5,F89=0),1,0) | L89: =IF(F89=1,'01_ВВОД'!$D$23,CHOOSE(D89,'01_ВВОД'!$D$19,'01_ВВОД'!$D$19,'01_ВВОД'!$D$19,'01_ВВОД'!$D$19,'01_ВВОД'!$D$20,'01_ВВОД'!$D$21,'01_ВВОД'!$D$22)) | M89: =L89*IF(H89=1,'01_ВВОД'!$D$118,1) | N89: =IF(K89=1,'01_ВВОД'!$D$26,0) | O89: =IF(F89=1,'01_ВВОД'!$D$34,IF(D89<=5,'01_ВВОД'!$D$32,'01_ВВОД'!$D$33)) | P89: =O89 | Q89: ='01_ВВОД'!$D$40 | R89: ='01_ВВОД'!$D$46 | S89: =H89 | T89: =IF(H89=1,M89+N89+P89+Q89,0) | U89: =R89*'01_ВВОД'!$D$120
A90: 46351 | B90: 3 | C90: Ноя-26 | D90: 3 | E90: Ср | F90: 0 | H90: 0 | J90: =1 | K90: =IF(AND(D90<=5,F90=0),1,0) | L90: =IF(F90=1,'01_ВВОД'!$D$23,CHOOSE(D90,'01_ВВОД'!$D$19,'01_ВВОД'!$D$19,'01_ВВОД'!$D$19,'01_ВВОД'!$D$19,'01_ВВОД'!$D$20,'01_ВВОД'!$D$21,'01_ВВОД'!$D$22)) | M90: =L90*IF(H90=1,'01_ВВОД'!$D$118,1) | N90: =IF(K90=1,'01_ВВОД'!$D$26,0) | O90: =IF(F90=1,'01_ВВОД'!$D$34,IF(D90<=5,'01_ВВОД'!$D$32,'01_ВВОД'!$D$33)) | P90: =O90 | Q90: ='01_ВВОД'!$D$40 | R90: ='01_ВВОД'!$D$46 | S90: =H90 | T90: =IF(H90=1,M90+N90+P90+Q90,0) | U90: =R90*'01_ВВОД'!$D$120
A91: 46352 | B91: 3 | C91: Ноя-26 | D91: 4 | E91: Чт | F91: 0 | H91: 0 | J91: =1 | K91: =IF(AND(D91<=5,F91=0),1,0) | L91: =IF(F91=1,'01_ВВОД'!$D$23,CHOOSE(D91,'01_ВВОД'!$D$19,'01_ВВОД'!$D$19,'01_ВВОД'!$D$19,'01_ВВОД'!$D$19,'01_ВВОД'!$D$20,'01_ВВОД'!$D$21,'01_ВВОД'!$D$22)) | M91: =L91*IF(H91=1,'01_ВВОД'!$D$118,1) | N91: =IF(K91=1,'01_ВВОД'!$D$26,0) | O91: =IF(F91=1,'01_ВВОД'!$D$34,IF(D91<=5,'01_ВВОД'!$D$32,'01_ВВОД'!$D$33)) | P91: =O91 | Q91: ='01_ВВОД'!$D$40 | R91: ='01_ВВОД'!$D$46 | S91: =H91 | T91: =IF(H91=1,M91+N91+P91+Q91,0) | U91: =R91*'01_ВВОД'!$D$120
A92: 46353 | B92: 3 | C92: Ноя-26 | D92: 5 | E92: Пт | F92: 0 | H92: 0 | J92: =1 | K92: =IF(AND(D92<=5,F92=0),1,0) | L92: =IF(F92=1,'01_ВВОД'!$D$23,CHOOSE(D92,'01_ВВОД'!$D$19,'01_ВВОД'!$D$19,'01_ВВОД'!$D$19,'01_ВВОД'!$D$19,'01_ВВОД'!$D$20,'01_ВВОД'!$D$21,'01_ВВОД'!$D$22)) | M92: =L92*IF(H92=1,'01_ВВОД'!$D$118,1) | N92: =IF(K92=1,'01_ВВОД'!$D$26,0) | O92: =IF(F92=1,'01_ВВОД'!$D$34,IF(D92<=5,'01_ВВОД'!$D$32,'01_ВВОД'!$D$33)) | P92: =O92 | Q92: ='01_ВВОД'!$D$40 | R92: ='01_ВВОД'!$D$46 | S92: =H92 | T92: =IF(H92=1,M92+N92+P92+Q92,0) | U92: =R92*'01_ВВОД'!$D$120
A93: 46354 | B93: 3 | C93: Ноя-26 | D93: 6 | E93: Сб | F93: 0 | H93: 0 | J93: =1 | K93: =IF(AND(D93<=5,F93=0),1,0) | L93: =IF(F93=1,'01_ВВОД'!$D$23,CHOOSE(D93,'01_ВВОД'!$D$19,'01_ВВОД'!$D$19,'01_ВВОД'!$D$19,'01_ВВОД'!$D$19,'01_ВВОД'!$D$20,'01_ВВОД'!$D$21,'01_ВВОД'!$D$22)) | M93: =L93*IF(H93=1,'01_ВВОД'!$D$118,1) | N93: =IF(K93=1,'01_ВВОД'!$D$26,0) | O93: =IF(F93=1,'01_ВВОД'!$D$34,IF(D93<=5,'01_ВВОД'!$D$32,'01_ВВОД'!$D$33)) | P93: =O93 | Q93: ='01_ВВОД'!$D$40 | R93: ='01_ВВОД'!$D$46 | S93: =H93 | T93: =IF(H93=1,M93+N93+P93+Q93,0) | U93: =R93*'01_ВВОД'!$D$120
A94: 46355 | B94: 3 | C94: Ноя-26 | D94: 7 | E94: Вс | F94: 0 | H94: 0 | J94: =1 | K94: =IF(AND(D94<=5,F94=0),1,0) | L94: =IF(F94=1,'01_ВВОД'!$D$23,CHOOSE(D94,'01_ВВОД'!$D$19,'01_ВВОД'!$D$19,'01_ВВОД'!$D$19,'01_ВВОД'!$D$19,'01_ВВОД'!$D$20,'01_ВВОД'!$D$21,'01_ВВОД'!$D$22)) | M94: =L94*IF(H94=1,'01_ВВОД'!$D$118,1) | N94: =IF(K94=1,'01_ВВОД'!$D$26,0) | O94: =IF(F94=1,'01_ВВОД'!$D$34,IF(D94<=5,'01_ВВОД'!$D$32,'01_ВВОД'!$D$33)) | P94: =O94 | Q94: ='01_ВВОД'!$D$40 | R94: ='01_ВВОД'!$D$46 | S94: =H94 | T94: =IF(H94=1,M94+N94+P94+Q94,0) | U94: =R94*'01_ВВОД'!$D$120
A95: 46356 | B95: 3 | C95: Ноя-26 | D95: 1 | E95: Пн | F95: 0 | H95: 1 | I95: Пн–Чт | J95: =1 | K95: =IF(AND(D95<=5,F95=0),1,0) | L95: =IF(F95=1,'01_ВВОД'!$D$23,CHOOSE(D95,'01_ВВОД'!$D$19,'01_ВВОД'!$D$19,'01_ВВОД'!$D$19,'01_ВВОД'!$D$19,'01_ВВОД'!$D$20,'01_ВВОД'!$D$21,'01_ВВОД'!$D$22)) | M95: =L95*IF(H95=1,'01_ВВОД'!$D$118,1) | N95: =IF(K95=1,'01_ВВОД'!$D$26,0) | O95: =IF(F95=1,'01_ВВОД'!$D$34,IF(D95<=5,'01_ВВОД'!$D$32,'01_ВВОД'!$D$33)) | P95: =O95 | Q95: ='01_ВВОД'!$D$40 | R95: ='01_ВВОД'!$D$46 | S95: =H95 | T95: =IF(H95=1,M95+N95+P95+Q95,0) | U95: =R95*'01_ВВОД'!$D$120
A96: 46357 | B96: 4 | C96: Дек-26 | D96: 2 | E96: Вт | F96: 0 | H96: 0 | J96: =1 | K96: =IF(AND(D96<=5,F96=0),1,0) | L96: =IF(F96=1,'01_ВВОД'!$D$23,CHOOSE(D96,'01_ВВОД'!$D$19,'01_ВВОД'!$D$19,'01_ВВОД'!$D$19,'01_ВВОД'!$D$19,'01_ВВОД'!$D$20,'01_ВВОД'!$D$21,'01_ВВОД'!$D$22)) | M96: =L96*IF(H96=1,'01_ВВОД'!$D$118,1) | N96: =IF(K96=1,'01_ВВОД'!$D$26,0) | O96: =IF(F96=1,'01_ВВОД'!$D$34,IF(D96<=5,'01_ВВОД'!$D$32,'01_ВВОД'!$D$33)) | P96: =O96 | Q96: ='01_ВВОД'!$D$40 | R96: ='01_ВВОД'!$D$46 | S96: =H96 | T96: =IF(H96=1,M96+N96+P96+Q96,0) | U96: =R96*'01_ВВОД'!$D$120
A97: 46358 | B97: 4 | C97: Дек-26 | D97: 3 | E97: Ср | F97: 0 | H97: 0 | J97: =1 | K97: =IF(AND(D97<=5,F97=0),1,0) | L97: =IF(F97=1,'01_ВВОД'!$D$23,CHOOSE(D97,'01_ВВОД'!$D$19,'01_ВВОД'!$D$19,'01_ВВОД'!$D$19,'01_ВВОД'!$D$19,'01_ВВОД'!$D$20,'01_ВВОД'!$D$21,'01_ВВОД'!$D$22)) | M97: =L97*IF(H97=1,'01_ВВОД'!$D$118,1) | N97: =IF(K97=1,'01_ВВОД'!$D$26,0) | O97: =IF(F97=1,'01_ВВОД'!$D$34,IF(D97<=5,'01_ВВОД'!$D$32,'01_ВВОД'!$D$33)) | P97: =O97 | Q97: ='01_ВВОД'!$D$40 | R97: ='01_ВВОД'!$D$46 | S97: =H97 | T97: =IF(H97=1,M97+N97+P97+Q97,0) | U97: =R97*'01_ВВОД'!$D$120
A98: 46359 | B98: 4 | C98: Дек-26 | D98: 4 | E98: Чт | F98: 0 | H98: 0 | J98: =1 | K98: =IF(AND(D98<=5,F98=0),1,0) | L98: =IF(F98=1,'01_ВВОД'!$D$23,CHOOSE(D98,'01_ВВОД'!$D$19,'01_ВВОД'!$D$19,'01_ВВОД'!$D$19,'01_ВВОД'!$D$19,'01_ВВОД'!$D$20,'01_ВВОД'!$D$21,'01_ВВОД'!$D$22)) | M98: =L98*IF(H98=1,'01_ВВОД'!$D$118,1) | N98: =IF(K98=1,'01_ВВОД'!$D$26,0) | O98: =IF(F98=1,'01_ВВОД'!$D$34,IF(D98<=5,'01_ВВОД'!$D$32,'01_ВВОД'!$D$33)) | P98: =O98 | Q98: ='01_ВВОД'!$D$40 | R98: ='01_ВВОД'!$D$46 | S98: =H98 | T98: =IF(H98=1,M98+N98+P98+Q98,0) | U98: =R98*'01_ВВОД'!$D$120
A99: 46360 | B99: 4 | C99: Дек-26 | D99: 5 | E99: Пт | F99: 0 | H99: 0 | J99: =1 | K99: =IF(AND(D99<=5,F99=0),1,0) | L99: =IF(F99=1,'01_ВВОД'!$D$23,CHOOSE(D99,'01_ВВОД'!$D$19,'01_ВВОД'!$D$19,'01_ВВОД'!$D$19,'01_ВВОД'!$D$19,'01_ВВОД'!$D$20,'01_ВВОД'!$D$21,'01_ВВОД'!$D$22)) | M99: =L99*IF(H99=1,'01_ВВОД'!$D$118,1) | N99: =IF(K99=1,'01_ВВОД'!$D$26,0) | O99: =IF(F99=1,'01_ВВОД'!$D$34,IF(D99<=5,'01_ВВОД'!$D$32,'01_ВВОД'!$D$33)) | P99: =O99 | Q99: ='01_ВВОД'!$D$40 | R99: ='01_ВВОД'!$D$46 | S99: =H99 | T99: =IF(H99=1,M99+N99+P99+Q99,0) | U99: =R99*'01_ВВОД'!$D$120
A100: 46361 | B100: 4 | C100: Дек-26 | D100: 6 | E100: Сб | F100: 0 | H100: 1 | I100: Пт–Вс | J100: =1 | K100: =IF(AND(D100<=5,F100=0),1,0) | L100: =IF(F100=1,'01_ВВОД'!$D$23,CHOOSE(D100,'01_ВВОД'!$D$19,'01_ВВОД'!$D$19,'01_ВВОД'!$D$19,'01_ВВОД'!$D$19,'01_ВВОД'!$D$20,'01_ВВОД'!$D$21,'01_ВВОД'!$D$22)) | M100: =L100*IF(H100=1,'01_ВВОД'!$D$118,1) | N100: =IF(K100=1,'01_ВВОД'!$D$26,0) | O100: =IF(F100=1,'01_ВВОД'!$D$34,IF(D100<=5,'01_ВВОД'!$D$32,'01_ВВОД'!$D$33)) | P100: =O100 | Q100: ='01_ВВОД'!$D$40 | R100: ='01_ВВОД'!$D$46 | S100: =H100 | T100: =IF(H100=1,M100+N100+P100+Q100,0) | U100: =R100*'01_ВВОД'!$D$120
A101: 46362 | B101: 4 | C101: Дек-26 | D101: 7 | E101: Вс | F101: 0 | H101: 0 | J101: =1 | K101: =IF(AND(D101<=5,F101=0),1,0) | L101: =IF(F101=1,'01_ВВОД'!$D$23,CHOOSE(D101,'01_ВВОД'!$D$19,'01_ВВОД'!$D$19,'01_ВВОД'!$D$19,'01_ВВОД'!$D$19,'01_ВВОД'!$D$20,'01_ВВОД'!$D$21,'01_ВВОД'!$D$22)) | M101: =L101*IF(H101=1,'01_ВВОД'!$D$118,1) | N101: =IF(K101=1,'01_ВВОД'!$D$26,0) | O101: =IF(F101=1,'01_ВВОД'!$D$34,IF(D101<=5,'01_ВВОД'!$D$32,'01_ВВОД'!$D$33)) | P101: =O101 | Q101: ='01_ВВОД'!$D$40 | R101: ='01_ВВОД'!$D$46 | S101: =H101 | T101: =IF(H101=1,M101+N101+P101+Q101,0) | U101: =R101*'01_ВВОД'!$D$120
A102: 46363 | B102: 4 | C102: Дек-26 | D102: 1 | E102: Пн | F102: 0 | H102: 0 | J102: =1 | K102: =IF(AND(D102<=5,F102=0),1,0) | L102: =IF(F102=1,'01_ВВОД'!$D$23,CHOOSE(D102,'01_ВВОД'!$D$19,'01_ВВОД'!$D$19,'01_ВВОД'!$D$19,'01_ВВОД'!$D$19,'01_ВВОД'!$D$20,'01_ВВОД'!$D$21,'01_ВВОД'!$D$22)) | M102: =L102*IF(H102=1,'01_ВВОД'!$D$118,1) | N102: =IF(K102=1,'01_ВВОД'!$D$26,0) | O102: =IF(F102=1,'01_ВВОД'!$D$34,IF(D102<=5,'01_ВВОД'!$D$32,'01_ВВОД'!$D$33)) | P102: =O102 | Q102: ='01_ВВОД'!$D$40 | R102: ='01_ВВОД'!$D$46 | S102: =H102 | T102: =IF(H102=1,M102+N102+P102+Q102,0) | U102: =R102*'01_ВВОД'!$D$120
A103: 46364 | B103: 4 | C103: Дек-26 | D103: 2 | E103: Вт | F103: 0 | H103: 1 | I103: Пн–Чт | J103: =1 | K103: =IF(AND(D103<=5,F103=0),1,0) | L103: =IF(F103=1,'01_ВВОД'!$D$23,CHOOSE(D103,'01_ВВОД'!$D$19,'01_ВВОД'!$D$19,'01_ВВОД'!$D$19,'01_ВВОД'!$D$19,'01_ВВОД'!$D$20,'01_ВВОД'!$D$21,'01_ВВОД'!$D$22)) | M103: =L103*IF(H103=1,'01_ВВОД'!$D$118,1) | N103: =IF(K103=1,'01_ВВОД'!$D$26,0) | O103: =IF(F103=1,'01_ВВОД'!$D$34,IF(D103<=5,'01_ВВОД'!$D$32,'01_ВВОД'!$D$33)) | P103: =O103 | Q103: ='01_ВВОД'!$D$40 | R103: ='01_ВВОД'!$D$46 | S103: =H103 | T103: =IF(H103=1,M103+N103+P103+Q103,0) | U103: =R103*'01_ВВОД'!$D$120
A104: 46365 | B104: 4 | C104: Дек-26 | D104: 3 | E104: Ср | F104: 0 | H104: 0 | J104: =1 | K104: =IF(AND(D104<=5,F104=0),1,0) | L104: =IF(F104=1,'01_ВВОД'!$D$23,CHOOSE(D104,'01_ВВОД'!$D$19,'01_ВВОД'!$D$19,'01_ВВОД'!$D$19,'01_ВВОД'!$D$19,'01_ВВОД'!$D$20,'01_ВВОД'!$D$21,'01_ВВОД'!$D$22)) | M104: =L104*IF(H104=1,'01_ВВОД'!$D$118,1) | N104: =IF(K104=1,'01_ВВОД'!$D$26,0) | O104: =IF(F104=1,'01_ВВОД'!$D$34,IF(D104<=5,'01_ВВОД'!$D$32,'01_ВВОД'!$D$33)) | P104: =O104 | Q104: ='01_ВВОД'!$D$40 | R104: ='01_ВВОД'!$D$46 | S104: =H104 | T104: =IF(H104=1,M104+N104+P104+Q104,0) | U104: =R104*'01_ВВОД'!$D$120
A105: 46366 | B105: 4 | C105: Дек-26 | D105: 4 | E105: Чт | F105: 0 | H105: 1 | I105: Пн–Чт | J105: =1 | K105: =IF(AND(D105<=5,F105=0),1,0) | L105: =IF(F105=1,'01_ВВОД'!$D$23,CHOOSE(D105,'01_ВВОД'!$D$19,'01_ВВОД'!$D$19,'01_ВВОД'!$D$19,'01_ВВОД'!$D$19,'01_ВВОД'!$D$20,'01_ВВОД'!$D$21,'01_ВВОД'!$D$22)) | M105: =L105*IF(H105=1,'01_ВВОД'!$D$118,1) | N105: =IF(K105=1,'01_ВВОД'!$D$26,0) | O105: =IF(F105=1,'01_ВВОД'!$D$34,IF(D105<=5,'01_ВВОД'!$D$32,'01_ВВОД'!$D$33)) | P105: =O105 | Q105: ='01_ВВОД'!$D$40 | R105: ='01_ВВОД'!$D$46 | S105: =H105 | T105: =IF(H105=1,M105+N105+P105+Q105,0) | U105: =R105*'01_ВВОД'!$D$120
A106: 46367 | B106: 4 | C106: Дек-26 | D106: 5 | E106: Пт | F106: 0 | H106: 0 | J106: =1 | K106: =IF(AND(D106<=5,F106=0),1,0) | L106: =IF(F106=1,'01_ВВОД'!$D$23,CHOOSE(D106,'01_ВВОД'!$D$19,'01_ВВОД'!$D$19,'01_ВВОД'!$D$19,'01_ВВОД'!$D$19,'01_ВВОД'!$D$20,'01_ВВОД'!$D$21,'01_ВВОД'!$D$22)) | M106: =L106*IF(H106=1,'01_ВВОД'!$D$118,1) | N106: =IF(K106=1,'01_ВВОД'!$D$26,0) | O106: =IF(F106=1,'01_ВВОД'!$D$34,IF(D106<=5,'01_ВВОД'!$D$32,'01_ВВОД'!$D$33)) | P106: =O106 | Q106: ='01_ВВОД'!$D$40 | R106: ='01_ВВОД'!$D$46 | S106: =H106 | T106: =IF(H106=1,M106+N106+P106+Q106,0) | U106: =R106*'01_ВВОД'!$D$120
A107: 46368 | B107: 4 | C107: Дек-26 | D107: 6 | E107: Сб | F107: 0 | H107: 0 | J107: =1 | K107: =IF(AND(D107<=5,F107=0),1,0) | L107: =IF(F107=1,'01_ВВОД'!$D$23,CHOOSE(D107,'01_ВВОД'!$D$19,'01_ВВОД'!$D$19,'01_ВВОД'!$D$19,'01_ВВОД'!$D$19,'01_ВВОД'!$D$20,'01_ВВОД'!$D$21,'01_ВВОД'!$D$22)) | M107: =L107*IF(H107=1,'01_ВВОД'!$D$118,1) | N107: =IF(K107=1,'01_ВВОД'!$D$26,0) | O107: =IF(F107=1,'01_ВВОД'!$D$34,IF(D107<=5,'01_ВВОД'!$D$32,'01_ВВОД'!$D$33)) | P107: =O107 | Q107: ='01_ВВОД'!$D$40 | R107: ='01_ВВОД'!$D$46 | S107: =H107 | T107: =IF(H107=1,M107+N107+P107+Q107,0) | U107: =R107*'01_ВВОД'!$D$120
A108: 46369 | B108: 4 | C108: Дек-26 | D108: 7 | E108: Вс | F108: 0 | H108: 1 | I108: Пт–Вс | J108: =1 | K108: =IF(AND(D108<=5,F108=0),1,0) | L108: =IF(F108=1,'01_ВВОД'!$D$23,CHOOSE(D108,'01_ВВОД'!$D$19,'01_ВВОД'!$D$19,'01_ВВОД'!$D$19,'01_ВВОД'!$D$19,'01_ВВОД'!$D$20,'01_ВВОД'!$D$21,'01_ВВОД'!$D$22)) | M108: =L108*IF(H108=1,'01_ВВОД'!$D$118,1) | N108: =IF(K108=1,'01_ВВОД'!$D$26,0) | O108: =IF(F108=1,'01_ВВОД'!$D$34,IF(D108<=5,'01_ВВОД'!$D$32,'01_ВВОД'!$D$33)) | P108: =O108 | Q108: ='01_ВВОД'!$D$40 | R108: ='01_ВВОД'!$D$46 | S108: =H108 | T108: =IF(H108=1,M108+N108+P108+Q108,0) | U108: =R108*'01_ВВОД'!$D$120
A109: 46370 | B109: 4 | C109: Дек-26 | D109: 1 | E109: Пн | F109: 0 | H109: 0 | J109: =1 | K109: =IF(AND(D109<=5,F109=0),1,0) | L109: =IF(F109=1,'01_ВВОД'!$D$23,CHOOSE(D109,'01_ВВОД'!$D$19,'01_ВВОД'!$D$19,'01_ВВОД'!$D$19,'01_ВВОД'!$D$19,'01_ВВОД'!$D$20,'01_ВВОД'!$D$21,'01_ВВОД'!$D$22)) | M109: =L109*IF(H109=1,'01_ВВОД'!$D$118,1) | N109: =IF(K109=1,'01_ВВОД'!$D$26,0) | O109: =IF(F109=1,'01_ВВОД'!$D$34,IF(D109<=5,'01_ВВОД'!$D$32,'01_ВВОД'!$D$33)) | P109: =O109 | Q109: ='01_ВВОД'!$D$40 | R109: ='01_ВВОД'!$D$46 | S109: =H109 | T109: =IF(H109=1,M109+N109+P109+Q109,0) | U109: =R109*'01_ВВОД'!$D$120
A110: 46371 | B110: 4 | C110: Дек-26 | D110: 2 | E110: Вт | F110: 0 | H110: 0 | J110: =1 | K110: =IF(AND(D110<=5,F110=0),1,0) | L110: =IF(F110=1,'01_ВВОД'!$D$23,CHOOSE(D110,'01_ВВОД'!$D$19,'01_ВВОД'!$D$19,'01_ВВОД'!$D$19,'01_ВВОД'!$D$19,'01_ВВОД'!$D$20,'01_ВВОД'!$D$21,'01_ВВОД'!$D$22)) | M110: =L110*IF(H110=1,'01_ВВОД'!$D$118,1) | N110: =IF(K110=1,'01_ВВОД'!$D$26,0) | O110: =IF(F110=1,'01_ВВОД'!$D$34,IF(D110<=5,'01_ВВОД'!$D$32,'01_ВВОД'!$D$33)) | P110: =O110 | Q110: ='01_ВВОД'!$D$40 | R110: ='01_ВВОД'!$D$46 | S110: =H110 | T110: =IF(H110=1,M110+N110+P110+Q110,0) | U110: =R110*'01_ВВОД'!$D$120
A111: 46372 | B111: 4 | C111: Дек-26 | D111: 3 | E111: Ср | F111: 0 | H111: 0 | J111: =1 | K111: =IF(AND(D111<=5,F111=0),1,0) | L111: =IF(F111=1,'01_ВВОД'!$D$23,CHOOSE(D111,'01_ВВОД'!$D$19,'01_ВВОД'!$D$19,'01_ВВОД'!$D$19,'01_ВВОД'!$D$19,'01_ВВОД'!$D$20,'01_ВВОД'!$D$21,'01_ВВОД'!$D$22)) | M111: =L111*IF(H111=1,'01_ВВОД'!$D$118,1) | N111: =IF(K111=1,'01_ВВОД'!$D$26,0) | O111: =IF(F111=1,'01_ВВОД'!$D$34,IF(D111<=5,'01_ВВОД'!$D$32,'01_ВВОД'!$D$33)) | P111: =O111 | Q111: ='01_ВВОД'!$D$40 | R111: ='01_ВВОД'!$D$46 | S111: =H111 | T111: =IF(H111=1,M111+N111+P111+Q111,0) | U111: =R111*'01_ВВОД'!$D$120
A112: 46373 | B112: 4 | C112: Дек-26 | D112: 4 | E112: Чт | F112: 0 | H112: 0 | J112: =1 | K112: =IF(AND(D112<=5,F112=0),1,0) | L112: =IF(F112=1,'01_ВВОД'!$D$23,CHOOSE(D112,'01_ВВОД'!$D$19,'01_ВВОД'!$D$19,'01_ВВОД'!$D$19,'01_ВВОД'!$D$19,'01_ВВОД'!$D$20,'01_ВВОД'!$D$21,'01_ВВОД'!$D$22)) | M112: =L112*IF(H112=1,'01_ВВОД'!$D$118,1) | N112: =IF(K112=1,'01_ВВОД'!$D$26,0) | O112: =IF(F112=1,'01_ВВОД'!$D$34,IF(D112<=5,'01_ВВОД'!$D$32,'01_ВВОД'!$D$33)) | P112: =O112 | Q112: ='01_ВВОД'!$D$40 | R112: ='01_ВВОД'!$D$46 | S112: =H112 | T112: =IF(H112=1,M112+N112+P112+Q112,0) | U112: =R112*'01_ВВОД'!$D$120
A113: 46374 | B113: 4 | C113: Дек-26 | D113: 5 | E113: Пт | F113: 0 | H113: 1 | I113: Пт–Вс | J113: =1 | K113: =IF(AND(D113<=5,F113=0),1,0) | L113: =IF(F113=1,'01_ВВОД'!$D$23,CHOOSE(D113,'01_ВВОД'!$D$19,'01_ВВОД'!$D$19,'01_ВВОД'!$D$19,'01_ВВОД'!$D$19,'01_ВВОД'!$D$20,'01_ВВОД'!$D$21,'01_ВВОД'!$D$22)) | M113: =L113*IF(H113=1,'01_ВВОД'!$D$118,1) | N113: =IF(K113=1,'01_ВВОД'!$D$26,0) | O113: =IF(F113=1,'01_ВВОД'!$D$34,IF(D113<=5,'01_ВВОД'!$D$32,'01_ВВОД'!$D$33)) | P113: =O113 | Q113: ='01_ВВОД'!$D$40 | R113: ='01_ВВОД'!$D$46 | S113: =H113 | T113: =IF(H113=1,M113+N113+P113+Q113,0) | U113: =R113*'01_ВВОД'!$D$120
A114: 46375 | B114: 4 | C114: Дек-26 | D114: 6 | E114: Сб | F114: 0 | H114: 0 | J114: =1 | K114: =IF(AND(D114<=5,F114=0),1,0) | L114: =IF(F114=1,'01_ВВОД'!$D$23,CHOOSE(D114,'01_ВВОД'!$D$19,'01_ВВОД'!$D$19,'01_ВВОД'!$D$19,'01_ВВОД'!$D$19,'01_ВВОД'!$D$20,'01_ВВОД'!$D$21,'01_ВВОД'!$D$22)) | M114: =L114*IF(H114=1,'01_ВВОД'!$D$118,1) | N114: =IF(K114=1,'01_ВВОД'!$D$26,0) | O114: =IF(F114=1,'01_ВВОД'!$D$34,IF(D114<=5,'01_ВВОД'!$D$32,'01_ВВОД'!$D$33)) | P114: =O114 | Q114: ='01_ВВОД'!$D$40 | R114: ='01_ВВОД'!$D$46 | S114: =H114 | T114: =IF(H114=1,M114+N114+P114+Q114,0) | U114: =R114*'01_ВВОД'!$D$120
A115: 46376 | B115: 4 | C115: Дек-26 | D115: 7 | E115: Вс | F115: 0 | H115: 0 | J115: =1 | K115: =IF(AND(D115<=5,F115=0),1,0) | L115: =IF(F115=1,'01_ВВОД'!$D$23,CHOOSE(D115,'01_ВВОД'!$D$19,'01_ВВОД'!$D$19,'01_ВВОД'!$D$19,'01_ВВОД'!$D$19,'01_ВВОД'!$D$20,'01_ВВОД'!$D$21,'01_ВВОД'!$D$22)) | M115: =L115*IF(H115=1,'01_ВВОД'!$D$118,1) | N115: =IF(K115=1,'01_ВВОД'!$D$26,0) | O115: =IF(F115=1,'01_ВВОД'!$D$34,IF(D115<=5,'01_ВВОД'!$D$32,'01_ВВОД'!$D$33)) | P115: =O115 | Q115: ='01_ВВОД'!$D$40 | R115: ='01_ВВОД'!$D$46 | S115: =H115 | T115: =IF(H115=1,M115+N115+P115+Q115,0) | U115: =R115*'01_ВВОД'!$D$120
A116: 46377 | B116: 4 | C116: Дек-26 | D116: 1 | E116: Пн | F116: 0 | H116: 0 | J116: =1 | K116: =IF(AND(D116<=5,F116=0),1,0) | L116: =IF(F116=1,'01_ВВОД'!$D$23,CHOOSE(D116,'01_ВВОД'!$D$19,'01_ВВОД'!$D$19,'01_ВВОД'!$D$19,'01_ВВОД'!$D$19,'01_ВВОД'!$D$20,'01_ВВОД'!$D$21,'01_ВВОД'!$D$22)) | M116: =L116*IF(H116=1,'01_ВВОД'!$D$118,1) | N116: =IF(K116=1,'01_ВВОД'!$D$26,0) | O116: =IF(F116=1,'01_ВВОД'!$D$34,IF(D116<=5,'01_ВВОД'!$D$32,'01_ВВОД'!$D$33)) | P116: =O116 | Q116: ='01_ВВОД'!$D$40 | R116: ='01_ВВОД'!$D$46 | S116: =H116 | T116: =IF(H116=1,M116+N116+P116+Q116,0) | U116: =R116*'01_ВВОД'!$D$120
A117: 46378 | B117: 4 | C117: Дек-26 | D117: 2 | E117: Вт | F117: 0 | H117: 0 | J117: =1 | K117: =IF(AND(D117<=5,F117=0),1,0) | L117: =IF(F117=1,'01_ВВОД'!$D$23,CHOOSE(D117,'01_ВВОД'!$D$19,'01_ВВОД'!$D$19,'01_ВВОД'!$D$19,'01_ВВОД'!$D$19,'01_ВВОД'!$D$20,'01_ВВОД'!$D$21,'01_ВВОД'!$D$22)) | M117: =L117*IF(H117=1,'01_ВВОД'!$D$118,1) | N117: =IF(K117=1,'01_ВВОД'!$D$26,0) | O117: =IF(F117=1,'01_ВВОД'!$D$34,IF(D117<=5,'01_ВВОД'!$D$32,'01_ВВОД'!$D$33)) | P117: =O117 | Q117: ='01_ВВОД'!$D$40 | R117: ='01_ВВОД'!$D$46 | S117: =H117 | T117: =IF(H117=1,M117+N117+P117+Q117,0) | U117: =R117*'01_ВВОД'!$D$120
A118: 46379 | B118: 4 | C118: Дек-26 | D118: 3 | E118: Ср | F118: 0 | H118: 0 | J118: =1 | K118: =IF(AND(D118<=5,F118=0),1,0) | L118: =IF(F118=1,'01_ВВОД'!$D$23,CHOOSE(D118,'01_ВВОД'!$D$19,'01_ВВОД'!$D$19,'01_ВВОД'!$D$19,'01_ВВОД'!$D$19,'01_ВВОД'!$D$20,'01_ВВОД'!$D$21,'01_ВВОД'!$D$22)) | M118: =L118*IF(H118=1,'01_ВВОД'!$D$118,1) | N118: =IF(K118=1,'01_ВВОД'!$D$26,0) | O118: =IF(F118=1,'01_ВВОД'!$D$34,IF(D118<=5,'01_ВВОД'!$D$32,'01_ВВОД'!$D$33)) | P118: =O118 | Q118: ='01_ВВОД'!$D$40 | R118: ='01_ВВОД'!$D$46 | S118: =H118 | T118: =IF(H118=1,M118+N118+P118+Q118,0) | U118: =R118*'01_ВВОД'!$D$120
A119: 46380 | B119: 4 | C119: Дек-26 | D119: 4 | E119: Чт | F119: 0 | H119: 0 | J119: =1 | K119: =IF(AND(D119<=5,F119=0),1,0) | L119: =IF(F119=1,'01_ВВОД'!$D$23,CHOOSE(D119,'01_ВВОД'!$D$19,'01_ВВОД'!$D$19,'01_ВВОД'!$D$19,'01_ВВОД'!$D$19,'01_ВВОД'!$D$20,'01_ВВОД'!$D$21,'01_ВВОД'!$D$22)) | M119: =L119*IF(H119=1,'01_ВВОД'!$D$118,1) | N119: =IF(K119=1,'01_ВВОД'!$D$26,0) | O119: =IF(F119=1,'01_ВВОД'!$D$34,IF(D119<=5,'01_ВВОД'!$D$32,'01_ВВОД'!$D$33)) | P119: =O119 | Q119: ='01_ВВОД'!$D$40 | R119: ='01_ВВОД'!$D$46 | S119: =H119 | T119: =IF(H119=1,M119+N119+P119+Q119,0) | U119: =R119*'01_ВВОД'!$D$120
A120: 46381 | B120: 4 | C120: Дек-26 | D120: 5 | E120: Пт | F120: 0 | H120: 0 | J120: =1 | K120: =IF(AND(D120<=5,F120=0),1,0) | L120: =IF(F120=1,'01_ВВОД'!$D$23,CHOOSE(D120,'01_ВВОД'!$D$19,'01_ВВОД'!$D$19,'01_ВВОД'!$D$19,'01_ВВОД'!$D$19,'01_ВВОД'!$D$20,'01_ВВОД'!$D$21,'01_ВВОД'!$D$22)) | M120: =L120*IF(H120=1,'01_ВВОД'!$D$118,1) | N120: =IF(K120=1,'01_ВВОД'!$D$26,0) | O120: =IF(F120=1,'01_ВВОД'!$D$34,IF(D120<=5,'01_ВВОД'!$D$32,'01_ВВОД'!$D$33)) | P120: =O120 | Q120: ='01_ВВОД'!$D$40 | R120: ='01_ВВОД'!$D$46 | S120: =H120 | T120: =IF(H120=1,M120+N120+P120+Q120,0) | U120: =R120*'01_ВВОД'!$D$120
A121: 46382 | B121: 4 | C121: Дек-26 | D121: 6 | E121: Сб | F121: 0 | H121: 0 | J121: =1 | K121: =IF(AND(D121<=5,F121=0),1,0) | L121: =IF(F121=1,'01_ВВОД'!$D$23,CHOOSE(D121,'01_ВВОД'!$D$19,'01_ВВОД'!$D$19,'01_ВВОД'!$D$19,'01_ВВОД'!$D$19,'01_ВВОД'!$D$20,'01_ВВОД'!$D$21,'01_ВВОД'!$D$22)) | M121: =L121*IF(H121=1,'01_ВВОД'!$D$118,1) | N121: =IF(K121=1,'01_ВВОД'!$D$26,0) | O121: =IF(F121=1,'01_ВВОД'!$D$34,IF(D121<=5,'01_ВВОД'!$D$32,'01_ВВОД'!$D$33)) | P121: =O121 | Q121: ='01_ВВОД'!$D$40 | R121: ='01_ВВОД'!$D$46 | S121: =H121 | T121: =IF(H121=1,M121+N121+P121+Q121,0) | U121: =R121*'01_ВВОД'!$D$120
A122: 46383 | B122: 4 | C122: Дек-26 | D122: 7 | E122: Вс | F122: 0 | H122: 1 | I122: Пт–Вс | J122: =1 | K122: =IF(AND(D122<=5,F122=0),1,0) | L122: =IF(F122=1,'01_ВВОД'!$D$23,CHOOSE(D122,'01_ВВОД'!$D$19,'01_ВВОД'!$D$19,'01_ВВОД'!$D$19,'01_ВВОД'!$D$19,'01_ВВОД'!$D$20,'01_ВВОД'!$D$21,'01_ВВОД'!$D$22)) | M122: =L122*IF(H122=1,'01_ВВОД'!$D$118,1) | N122: =IF(K122=1,'01_ВВОД'!$D$26,0) | O122: =IF(F122=1,'01_ВВОД'!$D$34,IF(D122<=5,'01_ВВОД'!$D$32,'01_ВВОД'!$D$33)) | P122: =O122 | Q122: ='01_ВВОД'!$D$40 | R122: ='01_ВВОД'!$D$46 | S122: =H122 | T122: =IF(H122=1,M122+N122+P122+Q122,0) | U122: =R122*'01_ВВОД'!$D$120
A123: 46384 | B123: 4 | C123: Дек-26 | D123: 1 | E123: Пн | F123: 0 | H123: 0 | J123: =1 | K123: =IF(AND(D123<=5,F123=0),1,0) | L123: =IF(F123=1,'01_ВВОД'!$D$23,CHOOSE(D123,'01_ВВОД'!$D$19,'01_ВВОД'!$D$19,'01_ВВОД'!$D$19,'01_ВВОД'!$D$19,'01_ВВОД'!$D$20,'01_ВВОД'!$D$21,'01_ВВОД'!$D$22)) | M123: =L123*IF(H123=1,'01_ВВОД'!$D$118,1) | N123: =IF(K123=1,'01_ВВОД'!$D$26,0) | O123: =IF(F123=1,'01_ВВОД'!$D$34,IF(D123<=5,'01_ВВОД'!$D$32,'01_ВВОД'!$D$33)) | P123: =O123 | Q123: ='01_ВВОД'!$D$40 | R123: ='01_ВВОД'!$D$46 | S123: =H123 | T123: =IF(H123=1,M123+N123+P123+Q123,0) | U123: =R123*'01_ВВОД'!$D$120
A124: 46385 | B124: 4 | C124: Дек-26 | D124: 2 | E124: Вт | F124: 0 | H124: 0 | J124: =1 | K124: =IF(AND(D124<=5,F124=0),1,0) | L124: =IF(F124=1,'01_ВВОД'!$D$23,CHOOSE(D124,'01_ВВОД'!$D$19,'01_ВВОД'!$D$19,'01_ВВОД'!$D$19,'01_ВВОД'!$D$19,'01_ВВОД'!$D$20,'01_ВВОД'!$D$21,'01_ВВОД'!$D$22)) | M124: =L124*IF(H124=1,'01_ВВОД'!$D$118,1) | N124: =IF(K124=1,'01_ВВОД'!$D$26,0) | O124: =IF(F124=1,'01_ВВОД'!$D$34,IF(D124<=5,'01_ВВОД'!$D$32,'01_ВВОД'!$D$33)) | P124: =O124 | Q124: ='01_ВВОД'!$D$40 | R124: ='01_ВВОД'!$D$46 | S124: =H124 | T124: =IF(H124=1,M124+N124+P124+Q124,0) | U124: =R124*'01_ВВОД'!$D$120
A125: 46386 | B125: 4 | C125: Дек-26 | D125: 3 | E125: Ср | F125: 0 | H125: 0 | J125: =1 | K125: =IF(AND(D125<=5,F125=0),1,0) | L125: =IF(F125=1,'01_ВВОД'!$D$23,CHOOSE(D125,'01_ВВОД'!$D$19,'01_ВВОД'!$D$19,'01_ВВОД'!$D$19,'01_ВВОД'!$D$19,'01_ВВОД'!$D$20,'01_ВВОД'!$D$21,'01_ВВОД'!$D$22)) | M125: =L125*IF(H125=1,'01_ВВОД'!$D$118,1) | N125: =IF(K125=1,'01_ВВОД'!$D$26,0) | O125: =IF(F125=1,'01_ВВОД'!$D$34,IF(D125<=5,'01_ВВОД'!$D$32,'01_ВВОД'!$D$33)) | P125: =O125 | Q125: ='01_ВВОД'!$D$40 | R125: ='01_ВВОД'!$D$46 | S125: =H125 | T125: =IF(H125=1,M125+N125+P125+Q125,0) | U125: =R125*'01_ВВОД'!$D$120
A126: 46387 | B126: 4 | C126: Дек-26 | D126: 4 | E126: Чт | F126: 1 | G126: Подтверждено для 2026 | H126: 0 | J126: =1 | K126: =IF(AND(D126<=5,F126=0),1,0) | L126: =IF(F126=1,'01_ВВОД'!$D$23,CHOOSE(D126,'01_ВВОД'!$D$19,'01_ВВОД'!$D$19,'01_ВВОД'!$D$19,'01_ВВОД'!$D$19,'01_ВВОД'!$D$20,'01_ВВОД'!$D$21,'01_ВВОД'!$D$22)) | M126: =L126*IF(H126=1,'01_ВВОД'!$D$118,1) | N126: =IF(K126=1,'01_ВВОД'!$D$26,0) | O126: =IF(F126=1,'01_ВВОД'!$D$34,IF(D126<=5,'01_ВВОД'!$D$32,'01_ВВОД'!$D$33)) | P126: =O126 | Q126: ='01_ВВОД'!$D$40 | R126: ='01_ВВОД'!$D$46 | S126: =H126 | T126: =IF(H126=1,M126+N126+P126+Q126,0) | U126: =R126*'01_ВВОД'!$D$120
A127: 46388 | B127: 5 | C127: Янв-27 | D127: 5 | E127: Пт | F127: 1 | G127: Фиксированный праздник 2027; переносы уточнить | H127: 0 | J127: =1 | K127: =IF(AND(D127<=5,F127=0),1,0) | L127: =IF(F127=1,'01_ВВОД'!$D$23,CHOOSE(D127,'01_ВВОД'!$D$19,'01_ВВОД'!$D$19,'01_ВВОД'!$D$19,'01_ВВОД'!$D$19,'01_ВВОД'!$D$20,'01_ВВОД'!$D$21,'01_ВВОД'!$D$22)) | M127: =L127*IF(H127=1,'01_ВВОД'!$D$118,1) | N127: =IF(K127=1,'01_ВВОД'!$D$26,0) | O127: =IF(F127=1,'01_ВВОД'!$D$34,IF(D127<=5,'01_ВВОД'!$D$32,'01_ВВОД'!$D$33)) | P127: =O127 | Q127: ='01_ВВОД'!$D$40 | R127: ='01_ВВОД'!$D$46 | S127: =H127 | T127: =IF(H127=1,M127+N127+P127+Q127,0) | U127: =R127*'01_ВВОД'!$D$120
A128: 46389 | B128: 5 | C128: Янв-27 | D128: 6 | E128: Сб | F128: 1 | G128: Фиксированный праздник 2027; переносы уточнить | H128: 0 | J128: =1 | K128: =IF(AND(D128<=5,F128=0),1,0) | L128: =IF(F128=1,'01_ВВОД'!$D$23,CHOOSE(D128,'01_ВВОД'!$D$19,'01_ВВОД'!$D$19,'01_ВВОД'!$D$19,'01_ВВОД'!$D$19,'01_ВВОД'!$D$20,'01_ВВОД'!$D$21,'01_ВВОД'!$D$22)) | M128: =L128*IF(H128=1,'01_ВВОД'!$D$118,1) | N128: =IF(K128=1,'01_ВВОД'!$D$26,0) | O128: =IF(F128=1,'01_ВВОД'!$D$34,IF(D128<=5,'01_ВВОД'!$D$32,'01_ВВОД'!$D$33)) | P128: =O128 | Q128: ='01_ВВОД'!$D$40 | R128: ='01_ВВОД'!$D$46 | S128: =H128 | T128: =IF(H128=1,M128+N128+P128+Q128,0) | U128: =R128*'01_ВВОД'!$D$120
A129: 46390 | B129: 5 | C129: Янв-27 | D129: 7 | E129: Вс | F129: 1 | G129: Фиксированный праздник 2027; переносы уточнить | H129: 0 | J129: =1 | K129: =IF(AND(D129<=5,F129=0),1,0) | L129: =IF(F129=1,'01_ВВОД'!$D$23,CHOOSE(D129,'01_ВВОД'!$D$19,'01_ВВОД'!$D$19,'01_ВВОД'!$D$19,'01_ВВОД'!$D$19,'01_ВВОД'!$D$20,'01_ВВОД'!$D$21,'01_ВВОД'!$D$22)) | M129: =L129*IF(H129=1,'01_ВВОД'!$D$118,1) | N129: =IF(K129=1,'01_ВВОД'!$D$26,0) | O129: =IF(F129=1,'01_ВВОД'!$D$34,IF(D129<=5,'01_ВВОД'!$D$32,'01_ВВОД'!$D$33)) | P129: =O129 | Q129: ='01_ВВОД'!$D$40 | R129: ='01_ВВОД'!$D$46 | S129: =H129 | T129: =IF(H129=1,M129+N129+P129+Q129,0) | U129: =R129*'01_ВВОД'!$D$120
A130: 46391 | B130: 5 | C130: Янв-27 | D130: 1 | E130: Пн | F130: 1 | G130: Фиксированный праздник 2027; переносы уточнить | H130: 0 | J130: =1 | K130: =IF(AND(D130<=5,F130=0),1,0) | L130: =IF(F130=1,'01_ВВОД'!$D$23,CHOOSE(D130,'01_ВВОД'!$D$19,'01_ВВОД'!$D$19,'01_ВВОД'!$D$19,'01_ВВОД'!$D$19,'01_ВВОД'!$D$20,'01_ВВОД'!$D$21,'01_ВВОД'!$D$22)) | M130: =L130*IF(H130=1,'01_ВВОД'!$D$118,1) | N130: =IF(K130=1,'01_ВВОД'!$D$26,0) | O130: =IF(F130=1,'01_ВВОД'!$D$34,IF(D130<=5,'01_ВВОД'!$D$32,'01_ВВОД'!$D$33)) | P130: =O130 | Q130: ='01_ВВОД'!$D$40 | R130: ='01_ВВОД'!$D$46 | S130: =H130 | T130: =IF(H130=1,M130+N130+P130+Q130,0) | U130: =R130*'01_ВВОД'!$D$120
A131: 46392 | B131: 5 | C131: Янв-27 | D131: 2 | E131: Вт | F131: 1 | G131: Фиксированный праздник 2027; переносы уточнить | H131: 0 | J131: =1 | K131: =IF(AND(D131<=5,F131=0),1,0) | L131: =IF(F131=1,'01_ВВОД'!$D$23,CHOOSE(D131,'01_ВВОД'!$D$19,'01_ВВОД'!$D$19,'01_ВВОД'!$D$19,'01_ВВОД'!$D$19,'01_ВВОД'!$D$20,'01_ВВОД'!$D$21,'01_ВВОД'!$D$22)) | M131: =L131*IF(H131=1,'01_ВВОД'!$D$118,1) | N131: =IF(K131=1,'01_ВВОД'!$D$26,0) | O131: =IF(F131=1,'01_ВВОД'!$D$34,IF(D131<=5,'01_ВВОД'!$D$32,'01_ВВОД'!$D$33)) | P131: =O131 | Q131: ='01_ВВОД'!$D$40 | R131: ='01_ВВОД'!$D$46 | S131: =H131 | T131: =IF(H131=1,M131+N131+P131+Q131,0) | U131: =R131*'01_ВВОД'!$D$120
A132: 46393 | B132: 5 | C132: Янв-27 | D132: 3 | E132: Ср | F132: 1 | G132: Фиксированный праздник 2027; переносы уточнить | H132: 0 | J132: =1 | K132: =IF(AND(D132<=5,F132=0),1,0) | L132: =IF(F132=1,'01_ВВОД'!$D$23,CHOOSE(D132,'01_ВВОД'!$D$19,'01_ВВОД'!$D$19,'01_ВВОД'!$D$19,'01_ВВОД'!$D$19,'01_ВВОД'!$D$20,'01_ВВОД'!$D$21,'01_ВВОД'!$D$22)) | M132: =L132*IF(H132=1,'01_ВВОД'!$D$118,1) | N132: =IF(K132=1,'01_ВВОД'!$D$26,0) | O132: =IF(F132=1,'01_ВВОД'!$D$34,IF(D132<=5,'01_ВВОД'!$D$32,'01_ВВОД'!$D$33)) | P132: =O132 | Q132: ='01_ВВОД'!$D$40 | R132: ='01_ВВОД'!$D$46 | S132: =H132 | T132: =IF(H132=1,M132+N132+P132+Q132,0) | U132: =R132*'01_ВВОД'!$D$120
A133: 46394 | B133: 5 | C133: Янв-27 | D133: 4 | E133: Чт | F133: 1 | G133: Фиксированный праздник 2027; переносы уточнить | H133: 0 | J133: =1 | K133: =IF(AND(D133<=5,F133=0),1,0) | L133: =IF(F133=1,'01_ВВОД'!$D$23,CHOOSE(D133,'01_ВВОД'!$D$19,'01_ВВОД'!$D$19,'01_ВВОД'!$D$19,'01_ВВОД'!$D$19,'01_ВВОД'!$D$20,'01_ВВОД'!$D$21,'01_ВВОД'!$D$22)) | M133: =L133*IF(H133=1,'01_ВВОД'!$D$118,1) | N133: =IF(K133=1,'01_ВВОД'!$D$26,0) | O133: =IF(F133=1,'01_ВВОД'!$D$34,IF(D133<=5,'01_ВВОД'!$D$32,'01_ВВОД'!$D$33)) | P133: =O133 | Q133: ='01_ВВОД'!$D$40 | R133: ='01_ВВОД'!$D$46 | S133: =H133 | T133: =IF(H133=1,M133+N133+P133+Q133,0) | U133: =R133*'01_ВВОД'!$D$120
A134: 46395 | B134: 5 | C134: Янв-27 | D134: 5 | E134: Пт | F134: 1 | G134: Фиксированный праздник 2027; переносы уточнить | H134: 0 | J134: =1 | K134: =IF(AND(D134<=5,F134=0),1,0) | L134: =IF(F134=1,'01_ВВОД'!$D$23,CHOOSE(D134,'01_ВВОД'!$D$19,'01_ВВОД'!$D$19,'01_ВВОД'!$D$19,'01_ВВОД'!$D$19,'01_ВВОД'!$D$20,'01_ВВОД'!$D$21,'01_ВВОД'!$D$22)) | M134: =L134*IF(H134=1,'01_ВВОД'!$D$118,1) | N134: =IF(K134=1,'01_ВВОД'!$D$26,0) | O134: =IF(F134=1,'01_ВВОД'!$D$34,IF(D134<=5,'01_ВВОД'!$D$32,'01_ВВОД'!$D$33)) | P134: =O134 | Q134: ='01_ВВОД'!$D$40 | R134: ='01_ВВОД'!$D$46 | S134: =H134 | T134: =IF(H134=1,M134+N134+P134+Q134,0) | U134: =R134*'01_ВВОД'!$D$120
A135: 46396 | B135: 5 | C135: Янв-27 | D135: 6 | E135: Сб | F135: 0 | H135: 0 | J135: =1 | K135: =IF(AND(D135<=5,F135=0),1,0) | L135: =IF(F135=1,'01_ВВОД'!$D$23,CHOOSE(D135,'01_ВВОД'!$D$19,'01_ВВОД'!$D$19,'01_ВВОД'!$D$19,'01_ВВОД'!$D$19,'01_ВВОД'!$D$20,'01_ВВОД'!$D$21,'01_ВВОД'!$D$22)) | M135: =L135*IF(H135=1,'01_ВВОД'!$D$118,1) | N135: =IF(K135=1,'01_ВВОД'!$D$26,0) | O135: =IF(F135=1,'01_ВВОД'!$D$34,IF(D135<=5,'01_ВВОД'!$D$32,'01_ВВОД'!$D$33)) | P135: =O135 | Q135: ='01_ВВОД'!$D$40 | R135: ='01_ВВОД'!$D$46 | S135: =H135 | T135: =IF(H135=1,M135+N135+P135+Q135,0) | U135: =R135*'01_ВВОД'!$D$120
A136: 46397 | B136: 5 | C136: Янв-27 | D136: 7 | E136: Вс | F136: 0 | H136: 0 | J136: =1 | K136: =IF(AND(D136<=5,F136=0),1,0) | L136: =IF(F136=1,'01_ВВОД'!$D$23,CHOOSE(D136,'01_ВВОД'!$D$19,'01_ВВОД'!$D$19,'01_ВВОД'!$D$19,'01_ВВОД'!$D$19,'01_ВВОД'!$D$20,'01_ВВОД'!$D$21,'01_ВВОД'!$D$22)) | M136: =L136*IF(H136=1,'01_ВВОД'!$D$118,1) | N136: =IF(K136=1,'01_ВВОД'!$D$26,0) | O136: =IF(F136=1,'01_ВВОД'!$D$34,IF(D136<=5,'01_ВВОД'!$D$32,'01_ВВОД'!$D$33)) | P136: =O136 | Q136: ='01_ВВОД'!$D$40 | R136: ='01_ВВОД'!$D$46 | S136: =H136 | T136: =IF(H136=1,M136+N136+P136+Q136,0) | U136: =R136*'01_ВВОД'!$D$120
A137: 46398 | B137: 5 | C137: Янв-27 | D137: 1 | E137: Пн | F137: 0 | H137: 0 | J137: =1 | K137: =IF(AND(D137<=5,F137=0),1,0) | L137: =IF(F137=1,'01_ВВОД'!$D$23,CHOOSE(D137,'01_ВВОД'!$D$19,'01_ВВОД'!$D$19,'01_ВВОД'!$D$19,'01_ВВОД'!$D$19,'01_ВВОД'!$D$20,'01_ВВОД'!$D$21,'01_ВВОД'!$D$22)) | M137: =L137*IF(H137=1,'01_ВВОД'!$D$118,1) | N137: =IF(K137=1,'01_ВВОД'!$D$26,0) | O137: =IF(F137=1,'01_ВВОД'!$D$34,IF(D137<=5,'01_ВВОД'!$D$32,'01_ВВОД'!$D$33)) | P137: =O137 | Q137: ='01_ВВОД'!$D$40 | R137: ='01_ВВОД'!$D$46 | S137: =H137 | T137: =IF(H137=1,M137+N137+P137+Q137,0) | U137: =R137*'01_ВВОД'!$D$120
A138: 46399 | B138: 5 | C138: Янв-27 | D138: 2 | E138: Вт | F138: 0 | H138: 0 | J138: =1 | K138: =IF(AND(D138<=5,F138=0),1,0) | L138: =IF(F138=1,'01_ВВОД'!$D$23,CHOOSE(D138,'01_ВВОД'!$D$19,'01_ВВОД'!$D$19,'01_ВВОД'!$D$19,'01_ВВОД'!$D$19,'01_ВВОД'!$D$20,'01_ВВОД'!$D$21,'01_ВВОД'!$D$22)) | M138: =L138*IF(H138=1,'01_ВВОД'!$D$118,1) | N138: =IF(K138=1,'01_ВВОД'!$D$26,0) | O138: =IF(F138=1,'01_ВВОД'!$D$34,IF(D138<=5,'01_ВВОД'!$D$32,'01_ВВОД'!$D$33)) | P138: =O138 | Q138: ='01_ВВОД'!$D$40 | R138: ='01_ВВОД'!$D$46 | S138: =H138 | T138: =IF(H138=1,M138+N138+P138+Q138,0) | U138: =R138*'01_ВВОД'!$D$120
A139: 46400 | B139: 5 | C139: Янв-27 | D139: 3 | E139: Ср | F139: 0 | H139: 1 | I139: Пн–Чт | J139: =1 | K139: =IF(AND(D139<=5,F139=0),1,0) | L139: =IF(F139=1,'01_ВВОД'!$D$23,CHOOSE(D139,'01_ВВОД'!$D$19,'01_ВВОД'!$D$19,'01_ВВОД'!$D$19,'01_ВВОД'!$D$19,'01_ВВОД'!$D$20,'01_ВВОД'!$D$21,'01_ВВОД'!$D$22)) | M139: =L139*IF(H139=1,'01_ВВОД'!$D$118,1) | N139: =IF(K139=1,'01_ВВОД'!$D$26,0) | O139: =IF(F139=1,'01_ВВОД'!$D$34,IF(D139<=5,'01_ВВОД'!$D$32,'01_ВВОД'!$D$33)) | P139: =O139 | Q139: ='01_ВВОД'!$D$40 | R139: ='01_ВВОД'!$D$46 | S139: =H139 | T139: =IF(H139=1,M139+N139+P139+Q139,0) | U139: =R139*'01_ВВОД'!$D$120
A140: 46401 | B140: 5 | C140: Янв-27 | D140: 4 | E140: Чт | F140: 0 | H140: 0 | J140: =1 | K140: =IF(AND(D140<=5,F140=0),1,0) | L140: =IF(F140=1,'01_ВВОД'!$D$23,CHOOSE(D140,'01_ВВОД'!$D$19,'01_ВВОД'!$D$19,'01_ВВОД'!$D$19,'01_ВВОД'!$D$19,'01_ВВОД'!$D$20,'01_ВВОД'!$D$21,'01_ВВОД'!$D$22)) | M140: =L140*IF(H140=1,'01_ВВОД'!$D$118,1) | N140: =IF(K140=1,'01_ВВОД'!$D$26,0) | O140: =IF(F140=1,'01_ВВОД'!$D$34,IF(D140<=5,'01_ВВОД'!$D$32,'01_ВВОД'!$D$33)) | P140: =O140 | Q140: ='01_ВВОД'!$D$40 | R140: ='01_ВВОД'!$D$46 | S140: =H140 | T140: =IF(H140=1,M140+N140+P140+Q140,0) | U140: =R140*'01_ВВОД'!$D$120
A141: 46402 | B141: 5 | C141: Янв-27 | D141: 5 | E141: Пт | F141: 0 | H141: 0 | J141: =1 | K141: =IF(AND(D141<=5,F141=0),1,0) | L141: =IF(F141=1,'01_ВВОД'!$D$23,CHOOSE(D141,'01_ВВОД'!$D$19,'01_ВВОД'!$D$19,'01_ВВОД'!$D$19,'01_ВВОД'!$D$19,'01_ВВОД'!$D$20,'01_ВВОД'!$D$21,'01_ВВОД'!$D$22)) | M141: =L141*IF(H141=1,'01_ВВОД'!$D$118,1) | N141: =IF(K141=1,'01_ВВОД'!$D$26,0) | O141: =IF(F141=1,'01_ВВОД'!$D$34,IF(D141<=5,'01_ВВОД'!$D$32,'01_ВВОД'!$D$33)) | P141: =O141 | Q141: ='01_ВВОД'!$D$40 | R141: ='01_ВВОД'!$D$46 | S141: =H141 | T141: =IF(H141=1,M141+N141+P141+Q141,0) | U141: =R141*'01_ВВОД'!$D$120
A142: 46403 | B142: 5 | C142: Янв-27 | D142: 6 | E142: Сб | F142: 0 | H142: 1 | I142: Пт–Вс | J142: =1 | K142: =IF(AND(D142<=5,F142=0),1,0) | L142: =IF(F142=1,'01_ВВОД'!$D$23,CHOOSE(D142,'01_ВВОД'!$D$19,'01_ВВОД'!$D$19,'01_ВВОД'!$D$19,'01_ВВОД'!$D$19,'01_ВВОД'!$D$20,'01_ВВОД'!$D$21,'01_ВВОД'!$D$22)) | M142: =L142*IF(H142=1,'01_ВВОД'!$D$118,1) | N142: =IF(K142=1,'01_ВВОД'!$D$26,0) | O142: =IF(F142=1,'01_ВВОД'!$D$34,IF(D142<=5,'01_ВВОД'!$D$32,'01_ВВОД'!$D$33)) | P142: =O142 | Q142: ='01_ВВОД'!$D$40 | R142: ='01_ВВОД'!$D$46 | S142: =H142 | T142: =IF(H142=1,M142+N142+P142+Q142,0) | U142: =R142*'01_ВВОД'!$D$120
A143: 46404 | B143: 5 | C143: Янв-27 | D143: 7 | E143: Вс | F143: 0 | H143: 1 | I143: Пт–Вс | J143: =1 | K143: =IF(AND(D143<=5,F143=0),1,0) | L143: =IF(F143=1,'01_ВВОД'!$D$23,CHOOSE(D143,'01_ВВОД'!$D$19,'01_ВВОД'!$D$19,'01_ВВОД'!$D$19,'01_ВВОД'!$D$19,'01_ВВОД'!$D$20,'01_ВВОД'!$D$21,'01_ВВОД'!$D$22)) | M143: =L143*IF(H143=1,'01_ВВОД'!$D$118,1) | N143: =IF(K143=1,'01_ВВОД'!$D$26,0) | O143: =IF(F143=1,'01_ВВОД'!$D$34,IF(D143<=5,'01_ВВОД'!$D$32,'01_ВВОД'!$D$33)) | P143: =O143 | Q143: ='01_ВВОД'!$D$40 | R143: ='01_ВВОД'!$D$46 | S143: =H143 | T143: =IF(H143=1,M143+N143+P143+Q143,0) | U143: =R143*'01_ВВОД'!$D$120
A144: 46405 | B144: 5 | C144: Янв-27 | D144: 1 | E144: Пн | F144: 0 | H144: 0 | J144: =1 | K144: =IF(AND(D144<=5,F144=0),1,0) | L144: =IF(F144=1,'01_ВВОД'!$D$23,CHOOSE(D144,'01_ВВОД'!$D$19,'01_ВВОД'!$D$19,'01_ВВОД'!$D$19,'01_ВВОД'!$D$19,'01_ВВОД'!$D$20,'01_ВВОД'!$D$21,'01_ВВОД'!$D$22)) | M144: =L144*IF(H144=1,'01_ВВОД'!$D$118,1) | N144: =IF(K144=1,'01_ВВОД'!$D$26,0) | O144: =IF(F144=1,'01_ВВОД'!$D$34,IF(D144<=5,'01_ВВОД'!$D$32,'01_ВВОД'!$D$33)) | P144: =O144 | Q144: ='01_ВВОД'!$D$40 | R144: ='01_ВВОД'!$D$46 | S144: =H144 | T144: =IF(H144=1,M144+N144+P144+Q144,0) | U144: =R144*'01_ВВОД'!$D$120
A145: 46406 | B145: 5 | C145: Янв-27 | D145: 2 | E145: Вт | F145: 0 | H145: 0 | J145: =1 | K145: =IF(AND(D145<=5,F145=0),1,0) | L145: =IF(F145=1,'01_ВВОД'!$D$23,CHOOSE(D145,'01_ВВОД'!$D$19,'01_ВВОД'!$D$19,'01_ВВОД'!$D$19,'01_ВВОД'!$D$19,'01_ВВОД'!$D$20,'01_ВВОД'!$D$21,'01_ВВОД'!$D$22)) | M145: =L145*IF(H145=1,'01_ВВОД'!$D$118,1) | N145: =IF(K145=1,'01_ВВОД'!$D$26,0) | O145: =IF(F145=1,'01_ВВОД'!$D$34,IF(D145<=5,'01_ВВОД'!$D$32,'01_ВВОД'!$D$33)) | P145: =O145 | Q145: ='01_ВВОД'!$D$40 | R145: ='01_ВВОД'!$D$46 | S145: =H145 | T145: =IF(H145=1,M145+N145+P145+Q145,0) | U145: =R145*'01_ВВОД'!$D$120
A146: 46407 | B146: 5 | C146: Янв-27 | D146: 3 | E146: Ср | F146: 0 | H146: 0 | J146: =1 | K146: =IF(AND(D146<=5,F146=0),1,0) | L146: =IF(F146=1,'01_ВВОД'!$D$23,CHOOSE(D146,'01_ВВОД'!$D$19,'01_ВВОД'!$D$19,'01_ВВОД'!$D$19,'01_ВВОД'!$D$19,'01_ВВОД'!$D$20,'01_ВВОД'!$D$21,'01_ВВОД'!$D$22)) | M146: =L146*IF(H146=1,'01_ВВОД'!$D$118,1) | N146: =IF(K146=1,'01_ВВОД'!$D$26,0) | O146: =IF(F146=1,'01_ВВОД'!$D$34,IF(D146<=5,'01_ВВОД'!$D$32,'01_ВВОД'!$D$33)) | P146: =O146 | Q146: ='01_ВВОД'!$D$40 | R146: ='01_ВВОД'!$D$46 | S146: =H146 | T146: =IF(H146=1,M146+N146+P146+Q146,0) | U146: =R146*'01_ВВОД'!$D$120
A147: 46408 | B147: 5 | C147: Янв-27 | D147: 4 | E147: Чт | F147: 0 | H147: 0 | J147: =1 | K147: =IF(AND(D147<=5,F147=0),1,0) | L147: =IF(F147=1,'01_ВВОД'!$D$23,CHOOSE(D147,'01_ВВОД'!$D$19,'01_ВВОД'!$D$19,'01_ВВОД'!$D$19,'01_ВВОД'!$D$19,'01_ВВОД'!$D$20,'01_ВВОД'!$D$21,'01_ВВОД'!$D$22)) | M147: =L147*IF(H147=1,'01_ВВОД'!$D$118,1) | N147: =IF(K147=1,'01_ВВОД'!$D$26,0) | O147: =IF(F147=1,'01_ВВОД'!$D$34,IF(D147<=5,'01_ВВОД'!$D$32,'01_ВВОД'!$D$33)) | P147: =O147 | Q147: ='01_ВВОД'!$D$40 | R147: ='01_ВВОД'!$D$46 | S147: =H147 | T147: =IF(H147=1,M147+N147+P147+Q147,0) | U147: =R147*'01_ВВОД'!$D$120
A148: 46409 | B148: 5 | C148: Янв-27 | D148: 5 | E148: Пт | F148: 0 | H148: 1 | I148: Пт–Вс | J148: =1 | K148: =IF(AND(D148<=5,F148=0),1,0) | L148: =IF(F148=1,'01_ВВОД'!$D$23,CHOOSE(D148,'01_ВВОД'!$D$19,'01_ВВОД'!$D$19,'01_ВВОД'!$D$19,'01_ВВОД'!$D$19,'01_ВВОД'!$D$20,'01_ВВОД'!$D$21,'01_ВВОД'!$D$22)) | M148: =L148*IF(H148=1,'01_ВВОД'!$D$118,1) | N148: =IF(K148=1,'01_ВВОД'!$D$26,0) | O148: =IF(F148=1,'01_ВВОД'!$D$34,IF(D148<=5,'01_ВВОД'!$D$32,'01_ВВОД'!$D$33)) | P148: =O148 | Q148: ='01_ВВОД'!$D$40 | R148: ='01_ВВОД'!$D$46 | S148: =H148 | T148: =IF(H148=1,M148+N148+P148+Q148,0) | U148: =R148*'01_ВВОД'!$D$120
A149: 46410 | B149: 5 | C149: Янв-27 | D149: 6 | E149: Сб | F149: 0 | H149: 0 | J149: =1 | K149: =IF(AND(D149<=5,F149=0),1,0) | L149: =IF(F149=1,'01_ВВОД'!$D$23,CHOOSE(D149,'01_ВВОД'!$D$19,'01_ВВОД'!$D$19,'01_ВВОД'!$D$19,'01_ВВОД'!$D$19,'01_ВВОД'!$D$20,'01_ВВОД'!$D$21,'01_ВВОД'!$D$22)) | M149: =L149*IF(H149=1,'01_ВВОД'!$D$118,1) | N149: =IF(K149=1,'01_ВВОД'!$D$26,0) | O149: =IF(F149=1,'01_ВВОД'!$D$34,IF(D149<=5,'01_ВВОД'!$D$32,'01_ВВОД'!$D$33)) | P149: =O149 | Q149: ='01_ВВОД'!$D$40 | R149: ='01_ВВОД'!$D$46 | S149: =H149 | T149: =IF(H149=1,M149+N149+P149+Q149,0) | U149: =R149*'01_ВВОД'!$D$120
A150: 46411 | B150: 5 | C150: Янв-27 | D150: 7 | E150: Вс | F150: 0 | H150: 1 | I150: Пт–Вс | J150: =1 | K150: =IF(AND(D150<=5,F150=0),1,0) | L150: =IF(F150=1,'01_ВВОД'!$D$23,CHOOSE(D150,'01_ВВОД'!$D$19,'01_ВВОД'!$D$19,'01_ВВОД'!$D$19,'01_ВВОД'!$D$19,'01_ВВОД'!$D$20,'01_ВВОД'!$D$21,'01_ВВОД'!$D$22)) | M150: =L150*IF(H150=1,'01_ВВОД'!$D$118,1) | N150: =IF(K150=1,'01_ВВОД'!$D$26,0) | O150: =IF(F150=1,'01_ВВОД'!$D$34,IF(D150<=5,'01_ВВОД'!$D$32,'01_ВВОД'!$D$33)) | P150: =O150 | Q150: ='01_ВВОД'!$D$40 | R150: ='01_ВВОД'!$D$46 | S150: =H150 | T150: =IF(H150=1,M150+N150+P150+Q150,0) | U150: =R150*'01_ВВОД'!$D$120
A151: 46412 | B151: 5 | C151: Янв-27 | D151: 1 | E151: Пн | F151: 0 | H151: 0 | J151: =1 | K151: =IF(AND(D151<=5,F151=0),1,0) | L151: =IF(F151=1,'01_ВВОД'!$D$23,CHOOSE(D151,'01_ВВОД'!$D$19,'01_ВВОД'!$D$19,'01_ВВОД'!$D$19,'01_ВВОД'!$D$19,'01_ВВОД'!$D$20,'01_ВВОД'!$D$21,'01_ВВОД'!$D$22)) | M151: =L151*IF(H151=1,'01_ВВОД'!$D$118,1) | N151: =IF(K151=1,'01_ВВОД'!$D$26,0) | O151: =IF(F151=1,'01_ВВОД'!$D$34,IF(D151<=5,'01_ВВОД'!$D$32,'01_ВВОД'!$D$33)) | P151: =O151 | Q151: ='01_ВВОД'!$D$40 | R151: ='01_ВВОД'!$D$46 | S151: =H151 | T151: =IF(H151=1,M151+N151+P151+Q151,0) | U151: =R151*'01_ВВОД'!$D$120
A152: 46413 | B152: 5 | C152: Янв-27 | D152: 2 | E152: Вт | F152: 0 | H152: 0 | J152: =1 | K152: =IF(AND(D152<=5,F152=0),1,0) | L152: =IF(F152=1,'01_ВВОД'!$D$23,CHOOSE(D152,'01_ВВОД'!$D$19,'01_ВВОД'!$D$19,'01_ВВОД'!$D$19,'01_ВВОД'!$D$19,'01_ВВОД'!$D$20,'01_ВВОД'!$D$21,'01_ВВОД'!$D$22)) | M152: =L152*IF(H152=1,'01_ВВОД'!$D$118,1) | N152: =IF(K152=1,'01_ВВОД'!$D$26,0) | O152: =IF(F152=1,'01_ВВОД'!$D$34,IF(D152<=5,'01_ВВОД'!$D$32,'01_ВВОД'!$D$33)) | P152: =O152 | Q152: ='01_ВВОД'!$D$40 | R152: ='01_ВВОД'!$D$46 | S152: =H152 | T152: =IF(H152=1,M152+N152+P152+Q152,0) | U152: =R152*'01_ВВОД'!$D$120
...

Sheet 03_ДОХОДЫ
A1: Доходы по направлениям
A2: Сценарий S03 наследует бизнес-ланч S02. Чек ужина — 1 000 руб.; food cost ужина равен food cost a-la carte; пересмотрены OPEX-inputs.
D3: 1 | E3: 2 | F3: 3 | G3: 4 | H3: 5 | I3: 6 | J3: 7 | K3: 8 | L3: 9 | M3: 10 | N3: 11 | O3: 12
A4: Код | B4: Раздел | C4: Показатель | D4: Сен-26 | E4: Окт-26 | F4: Ноя-26 | G4: Дек-26 | H4: Янв-27 | I4: Фев-27 | J4: Мар-27 | K4: Апр-27 | L4: Май-27 | M4: Июн-27 | N4: Июл-27 | O4: Авг-27 | P4: Итого за год | Q4: Среднее за месяц | R4: Ед.
A5: БИЗНЕС 1 — КАФЕ
A6: REV.ALA.QTY | B6: Кафе — а-ля карт | C6: Гости а-ля карт | D6: =SUMIF('02_КАЛЕНДАРЬ'!$B$5:$B$369,D$3,'02_КАЛЕНДАРЬ'!$M$5:$M$369) | E6: =SUMIF('02_КАЛЕНДАРЬ'!$B$5:$B$369,E$3,'02_КАЛЕНДАРЬ'!$M$5:$M$369) | F6: =SUMIF('02_КАЛЕНДАРЬ'!$B$5:$B$369,F$3,'02_КАЛЕНДАРЬ'!$M$5:$M$369) | G6: =SUMIF('02_КАЛЕНДАРЬ'!$B$5:$B$369,G$3,'02_КАЛЕНДАРЬ'!$M$5:$M$369) | H6: =SUMIF('02_КАЛЕНДАРЬ'!$B$5:$B$369,H$3,'02_КАЛЕНДАРЬ'!$M$5:$M$369) | I6: =SUMIF('02_КАЛЕНДАРЬ'!$B$5:$B$369,I$3,'02_КАЛЕНДАРЬ'!$M$5:$M$369) | J6: =SUMIF('02_КАЛЕНДАРЬ'!$B$5:$B$369,J$3,'02_КАЛЕНДАРЬ'!$M$5:$M$369) | K6: =SUMIF('02_КАЛЕНДАРЬ'!$B$5:$B$369,K$3,'02_КАЛЕНДАРЬ'!$M$5:$M$369) | ... O6: =SUMIF('02_КАЛЕНДАРЬ'!$B$5:$B$369,O$3,'02_КАЛЕНДАРЬ'!$M$5:$M$369) | P6: =SUM(D6:O6) | Q6: =P6/12 | R6: гостей
A7: REV.ALA.CHECK | B7: Кафе — а-ля карт | C7: Средний чек | D7: ='01_ВВОД'!$D$18 | E7: ='01_ВВОД'!$D$18 | F7: ='01_ВВОД'!$D$18 | G7: ='01_ВВОД'!$D$18 | H7: ='01_ВВОД'!$D$18 | I7: ='01_ВВОД'!$D$18 | J7: ='01_ВВОД'!$D$18 | K7: ='01_ВВОД'!$D$18 | ... O7: ='01_ВВОД'!$D$18 | P7: =AVERAGE(D7:O7) | Q7: =P7 | R7: руб./гость
A8: REV.ALA | B8: Кафе — а-ля карт | C8: Доходы а-ля карт | D8: =D6*D7 | E8: =E6*E7 | F8: =F6*F7 | G8: =G6*G7 | H8: =H6*H7 | I8: =I6*I7 | J8: =J6*J7 | K8: =K6*K7 | ... O8: =O6*O7 | P8: =SUM(D8:O8) | Q8: =P8/12 | R8: руб.
A10: REV.LUNCH.QTY | B10: Кафе — бизнес-ланч | C10: Гости бизнес-ланча | D10: =SUMIF('02_КАЛЕНДАРЬ'!$B$5:$B$369,D$3,'02_КАЛЕНДАРЬ'!$N$5:$N$369) | E10: =SUMIF('02_КАЛЕНДАРЬ'!$B$5:$B$369,E$3,'02_КАЛЕНДАРЬ'!$N$5:$N$369) | F10: =SUMIF('02_КАЛЕНДАРЬ'!$B$5:$B$369,F$3,'02_КАЛЕНДАРЬ'!$N$5:$N$369) | G10: =SUMIF('02_КАЛЕНДАРЬ'!$B$5:$B$369,G$3,'02_КАЛЕНДАРЬ'!$N$5:$N$369) | H10: =SUMIF('02_КАЛЕНДАРЬ'!$B$5:$B$369,H$3,'02_КАЛЕНДАРЬ'!$N$5:$N$369) | I10: =SUMIF('02_КАЛЕНДАРЬ'!$B$5:$B$369,I$3,'02_КАЛЕНДАРЬ'!$N$5:$N$369) | J10: =SUMIF('02_КАЛЕНДАРЬ'!$B$5:$B$369,J$3,'02_КАЛЕНДАРЬ'!$N$5:$N$369) | K10: =SUMIF('02_КАЛЕНДАРЬ'!$B$5:$B$369,K$3,'02_КАЛЕНДАРЬ'!$N$5:$N$369) | ... O10: =SUMIF('02_КАЛЕНДАРЬ'!$B$5:$B$369,O$3,'02_КАЛЕНДАРЬ'!$N$5:$N$369) | P10: =SUM(D10:O10) | Q10: =P10/12 | R10: гостей
A11: REV.LUNCH.CHECK | B11: Кафе — бизнес-ланч | C11: Средний чек | D11: ='01_ВВОД'!$D$28 | E11: ='01_ВВОД'!$D$28 | F11: ='01_ВВОД'!$D$28 | G11: ='01_ВВОД'!$D$28 | H11: ='01_ВВОД'!$D$28 | I11: ='01_ВВОД'!$D$28 | J11: ='01_ВВОД'!$D$28 | K11: ='01_ВВОД'!$D$28 | ... O11: ='01_ВВОД'!$D$28 | P11: =AVERAGE(D11:O11) | Q11: =P11 | R11: руб./гость
A12: REV.LUNCH | B12: Кафе — бизнес-ланч | C12: Доходы бизнес-ланча | D12: =D10*D11 | E12: =E10*E11 | F12: =F10*F11 | G12: =G10*G11 | H12: =H10*H11 | I12: =I10*I11 | J12: =J10*J11 | K12: =K10*K11 | ... O12: =O10*O11 | P12: =SUM(D12:O12) | Q12: =P12/12 | R12: руб.
A14: REV.DEL.QTY | B14: Кафе — доставка | C14: Заказы доставки | D14: =SUMIF('02_КАЛЕНДАРЬ'!$B$5:$B$369,D$3,'02_КАЛЕНДАРЬ'!$P$5:$P$369) | E14: =SUMIF('02_КАЛЕНДАРЬ'!$B$5:$B$369,E$3,'02_КАЛЕНДАРЬ'!$P$5:$P$369) | F14: =SUMIF('02_КАЛЕНДАРЬ'!$B$5:$B$369,F$3,'02_КАЛЕНДАРЬ'!$P$5:$P$369) | G14: =SUMIF('02_КАЛЕНДАРЬ'!$B$5:$B$369,G$3,'02_КАЛЕНДАРЬ'!$P$5:$P$369) | H14: =SUMIF('02_КАЛЕНДАРЬ'!$B$5:$B$369,H$3,'02_КАЛЕНДАРЬ'!$P$5:$P$369) | I14: =SUMIF('02_КАЛЕНДАРЬ'!$B$5:$B$369,I$3,'02_КАЛЕНДАРЬ'!$P$5:$P$369) | J14: =SUMIF('02_КАЛЕНДАРЬ'!$B$5:$B$369,J$3,'02_КАЛЕНДАРЬ'!$P$5:$P$369) | K14: =SUMIF('02_КАЛЕНДАРЬ'!$B$5:$B$369,K$3,'02_КАЛЕНДАРЬ'!$P$5:$P$369) | ... O14: =SUMIF('02_КАЛЕНДАРЬ'!$B$5:$B$369,O$3,'02_КАЛЕНДАРЬ'!$P$5:$P$369) | P14: =SUM(D14:O14) | Q14: =P14/12 | R14: заказов
A15: REV.DEL.CHECK | B15: Кафе — доставка | C15: Средний чек | D15: ='01_ВВОД'!$D$31 | E15: ='01_ВВОД'!$D$31 | F15: ='01_ВВОД'!$D$31 | G15: ='01_ВВОД'!$D$31 | H15: ='01_ВВОД'!$D$31 | I15: ='01_ВВОД'!$D$31 | J15: ='01_ВВОД'!$D$31 | K15: ='01_ВВОД'!$D$31 | ... O15: ='01_ВВОД'!$D$31 | P15: =AVERAGE(D15:O15) | Q15: =P15 | R15: руб./заказ
A16: REV.DEL | B16: Кафе — доставка | C16: Доходы доставки | D16: =D14*D15 | E16: =E14*E15 | F16: =F14*F15 | G16: =G14*G15 | H16: =H14*H15 | I16: =I14*I15 | J16: =J14*J15 | K16: =K14*K15 | ... O16: =O14*O15 | P16: =SUM(D16:O16) | Q16: =P16/12 | R16: руб.
A18: REV.PICK.QTY | B18: Кафе — самовывоз | C18: Заказы самовывоза | D18: =SUMIF('02_КАЛЕНДАРЬ'!$B$5:$B$369,D$3,'02_КАЛЕНДАРЬ'!$Q$5:$Q$369) | E18: =SUMIF('02_КАЛЕНДАРЬ'!$B$5:$B$369,E$3,'02_КАЛЕНДАРЬ'!$Q$5:$Q$369) | F18: =SUMIF('02_КАЛЕНДАРЬ'!$B$5:$B$369,F$3,'02_КАЛЕНДАРЬ'!$Q$5:$Q$369) | G18: =SUMIF('02_КАЛЕНДАРЬ'!$B$5:$B$369,G$3,'02_КАЛЕНДАРЬ'!$Q$5:$Q$369) | H18: =SUMIF('02_КАЛЕНДАРЬ'!$B$5:$B$369,H$3,'02_КАЛЕНДАРЬ'!$Q$5:$Q$369) | I18: =SUMIF('02_КАЛЕНДАРЬ'!$B$5:$B$369,I$3,'02_КАЛЕНДАРЬ'!$Q$5:$Q$369) | J18: =SUMIF('02_КАЛЕНДАРЬ'!$B$5:$B$369,J$3,'02_КАЛЕНДАРЬ'!$Q$5:$Q$369) | K18: =SUMIF('02_КАЛЕНДАРЬ'!$B$5:$B$369,K$3,'02_КАЛЕНДАРЬ'!$Q$5:$Q$369) | ... O18: =SUMIF('02_КАЛЕНДАРЬ'!$B$5:$B$369,O$3,'02_КАЛЕНДАРЬ'!$Q$5:$Q$369) | P18: =SUM(D18:O18) | Q18: =P18/12 | R18: заказов
A19: REV.PICK.CHECK | B19: Кафе — самовывоз | C19: Средний чек | D19: ='01_ВВОД'!$D$39 | E19: ='01_ВВОД'!$D$39 | F19: ='01_ВВОД'!$D$39 | G19: ='01_ВВОД'!$D$39 | H19: ='01_ВВОД'!$D$39 | I19: ='01_ВВОД'!$D$39 | J19: ='01_ВВОД'!$D$39 | K19: ='01_ВВОД'!$D$39 | ... O19: ='01_ВВОД'!$D$39 | P19: =AVERAGE(D19:O19) | Q19: =P19 | R19: руб./заказ
A20: REV.PICK | B20: Кафе — самовывоз | C20: Доходы самовывоза | D20: =D18*D19 | E20: =E18*E19 | F20: =F18*F19 | G20: =G18*G19 | H20: =H18*H19 | I20: =I18*I19 | J20: =J18*J19 | K20: =K18*K19 | ... O20: =O18*O19 | P20: =SUM(D20:O20) | Q20: =P20/12 | R20: руб.
A22: REV.HOTEL.QTY | B22: Кафе — гостиница | C22: Заказы гостиничного канала | D22: =SUMIF('02_КАЛЕНДАРЬ'!$B$5:$B$369,D$3,'02_КАЛЕНДАРЬ'!$R$5:$R$369) | E22: =SUMIF('02_КАЛЕНДАРЬ'!$B$5:$B$369,E$3,'02_КАЛЕНДАРЬ'!$R$5:$R$369) | F22: =SUMIF('02_КАЛЕНДАРЬ'!$B$5:$B$369,F$3,'02_КАЛЕНДАРЬ'!$R$5:$R$369) | G22: =SUMIF('02_КАЛЕНДАРЬ'!$B$5:$B$369,G$3,'02_КАЛЕНДАРЬ'!$R$5:$R$369) | H22: =SUMIF('02_КАЛЕНДАРЬ'!$B$5:$B$369,H$3,'02_КАЛЕНДАРЬ'!$R$5:$R$369) | I22: =SUMIF('02_КАЛЕНДАРЬ'!$B$5:$B$369,I$3,'02_КАЛЕНДАРЬ'!$R$5:$R$369) | J22: =SUMIF('02_КАЛЕНДАРЬ'!$B$5:$B$369,J$3,'02_КАЛЕНДАРЬ'!$R$5:$R$369) | K22: =SUMIF('02_КАЛЕНДАРЬ'!$B$5:$B$369,K$3,'02_КАЛЕНДАРЬ'!$R$5:$R$369) | ... O22: =SUMIF('02_КАЛЕНДАРЬ'!$B$5:$B$369,O$3,'02_КАЛЕНДАРЬ'!$R$5:$R$369) | P22: =SUM(D22:O22) | Q22: =P22/12 | R22: заказов
A23: REV.HOTEL.CHECK | B23: Кафе — гостиница | C23: Средний чек | D23: ='01_ВВОД'!$D$45 | E23: ='01_ВВОД'!$D$45 | F23: ='01_ВВОД'!$D$45 | G23: ='01_ВВОД'!$D$45 | H23: ='01_ВВОД'!$D$45 | I23: ='01_ВВОД'!$D$45 | J23: ='01_ВВОД'!$D$45 | K23: ='01_ВВОД'!$D$45 | ... O23: ='01_ВВОД'!$D$45 | P23: =AVERAGE(D23:O23) | Q23: =P23 | R23: руб./заказ
A24: REV.HOTEL | B24: Кафе — гостиница | C24: Доходы гостиничного канала | D24: =D22*D23 | E24: =E22*E23 | F24: =F22*F23 | G24: =G22*G23 | H24: =H22*H23 | I24: =I22*I23 | J24: =J22*J23 | K24: =K22*K23 | ... O24: =O22*O23 | P24: =SUM(D24:O24) | Q24: =P24/12 | R24: руб.
A26: REV.CAFE | B26: Кафе | C26: ИТОГО ДОХОДЫ КАФЕ | D26: =SUM(D8,D12,D16,D20,D24,D41) | E26: =SUM(E8,E12,E16,E20,E24,E41) | F26: =SUM(F8,F12,F16,F20,F24,F41) | G26: =SUM(G8,G12,G16,G20,G24,G41) | H26: =SUM(H8,H12,H16,H20,H24,H41) | I26: =SUM(I8,I12,I16,I20,I24,I41) | J26: =SUM(J8,J12,J16,J20,J24,J41) | K26: =SUM(K8,K12,K16,K20,K24,K41) | ... O26: =SUM(O8,O12,O16,O20,O24,O41) | P26: =SUM(D26:O26) | Q26: =P26/12 | R26: руб.
A28: УПУЩЕННАЯ ВЫРУЧКА КАФЕ ИЗ-ЗА БАНКЕТНЫХ ДНЕЙ
A29: REV.CAFE.POT | B29: Кафе | C29: Потенциальные доходы кафе без банкетных закрытий | D29: =SUMIF('02_КАЛЕНДАРЬ'!$B$5:$B$369,D$3,'02_КАЛЕНДАРЬ'!$L$5:$L$369)*'01_ВВОД'!$D$18+SUMIF('02_КАЛЕНДАРЬ'!$B$5:$B$369,D$3,'02_КАЛЕНДАРЬ'!$K$5:$K$369)*'01_ВВОД'!$D$26*'01_ВВОД'!$D$28+SUMIF('02_КАЛЕНДАРЬ'!$B$5:$B$369,D$3,'02_КАЛЕНДАРЬ'!$O$5:$O$369)*'01_ВВОД'!$D$31+COUNTIF('02_КАЛЕНДАРЬ'!$B$5:$B$369,D$3)*'01_ВВОД'!$D$40*'01_ВВОД'!$D$39+D24+D41 | E29: =SUMIF('02_КАЛЕНДАРЬ'!$B$5:$B$369,E$3,'02_КАЛЕНДАРЬ'!$L$5:$L$369)*'01_ВВОД'!$D$18+SUMIF('02_КАЛЕНДАРЬ'!$B$5:$B$369,E$3,'02_КАЛЕНДАРЬ'!$K$5:$K$369)*'01_ВВОД'!$D$26*'01_ВВОД'!$D$28+SUMIF('02_КАЛЕНДАРЬ'!$B$5:$B$369,E$3,'02_КАЛЕНДАРЬ'!$O$5:$O$369)*'01_ВВОД'!$D$31+COUNTIF('02_КАЛЕНДАРЬ'!$B$5:$B$369,E$3)*'01_ВВОД'!$D$40*'01_ВВОД'!$D$39+E24+E41 | F29: =SUMIF('02_КАЛЕНДАРЬ'!$B$5:$B$369,F$3,'02_КАЛЕНДАРЬ'!$L$5:$L$369)*'01_ВВОД'!$D$18+SUMIF('02_КАЛЕНДАРЬ'!$B$5:$B$369,F$3,'02_КАЛЕНДАРЬ'!$K$5:$K$369)*'01_ВВОД'!$D$26*'01_ВВОД'!$D$28+SUMIF('02_КАЛЕНДАРЬ'!$B$5:$B$369,F$3,'02_КАЛЕНДАРЬ'!$O$5:$O$369)*'01_ВВОД'!$D$31+COUNTIF('02_КАЛЕНДАРЬ'!$B$5:$B$369,F$3)*'01_ВВОД'!$D$40*'01_ВВОД'!$D$39+F24+F41 | G29: =SUMIF('02_КАЛЕНДАРЬ'!$B$5:$B$369,G$3,'02_КАЛЕНДАРЬ'!$L$5:$L$369)*'01_ВВОД'!$D$18+SUMIF('02_КАЛЕНДАРЬ'!$B$5:$B$369,G$3,'02_КАЛЕНДАРЬ'!$K$5:$K$369)*'01_ВВОД'!$D$26*'01_ВВОД'!$D$28+SUMIF('02_КАЛЕНДАРЬ'!$B$5:$B$369,G$3,'02_КАЛЕНДАРЬ'!$O$5:$O$369)*'01_ВВОД'!$D$31+COUNTIF('02_КАЛЕНДАРЬ'!$B$5:$B$369,G$3)*'01_ВВОД'!$D$40*'01_ВВОД'!$D$39+G24+G41 | H29: =SUMIF('02_КАЛЕНДАРЬ'!$B$5:$B$369,H$3,'02_КАЛЕНДАРЬ'!$L$5:$L$369)*'01_ВВОД'!$D$18+SUMIF('02_КАЛЕНДАРЬ'!$B$5:$B$369,H$3,'02_КАЛЕНДАРЬ'!$K$5:$K$369)*'01_ВВОД'!$D$26*'01_ВВОД'!$D$28+SUMIF('02_КАЛЕНДАРЬ'!$B$5:$B$369,H$3,'02_КАЛЕНДАРЬ'!$O$5:$O$369)*'01_ВВОД'!$D$31+COUNTIF('02_КАЛЕНДАРЬ'!$B$5:$B$369,H$3)*'01_ВВОД'!$D$40*'01_ВВОД'!$D$39+H24+H41 | I29: =SUMIF('02_КАЛЕНДАРЬ'!$B$5:$B$369,I$3,'02_КАЛЕНДАРЬ'!$L$5:$L$369)*'01_ВВОД'!$D$18+SUMIF('02_КАЛЕНДАРЬ'!$B$5:$B$369,I$3,'02_КАЛЕНДАРЬ'!$K$5:$K$369)*'01_ВВОД'!$D$26*'01_ВВОД'!$D$28+SUMIF('02_КАЛЕНДАРЬ'!$B$5:$B$369,I$3,'02_КАЛЕНДАРЬ'!$O$5:$O$369)*'01_ВВОД'!$D$31+COUNTIF('02_КАЛЕНДАРЬ'!$B$5:$B$369,I$3)*'01_ВВОД'!$D$40*'01_ВВОД'!$D$39+I24+I41 | J29: =SUMIF('02_КАЛЕНДАРЬ'!$B$5:$B$369,J$3,'02_КАЛЕНДАРЬ'!$L$5:$L$369)*'01_ВВОД'!$D$18+SUMIF('02_КАЛЕНДАРЬ'!$B$5:$B$369,J$3,'02_КАЛЕНДАРЬ'!$K$5:$K$369)*'01_ВВОД'!$D$26*'01_ВВОД'!$D$28+SUMIF('02_КАЛЕНДАРЬ'!$B$5:$B$369,J$3,'02_КАЛЕНДАРЬ'!$O$5:$O$369)*'01_ВВОД'!$D$31+COUNTIF('02_КАЛЕНДАРЬ'!$B$5:$B$369,J$3)*'01_ВВОД'!$D$40*'01_ВВОД'!$D$39+J24+J41 | K29: =SUMIF('02_КАЛЕНДАРЬ'!$B$5:$B$369,K$3,'02_КАЛЕНДАРЬ'!$L$5:$L$369)*'01_ВВОД'!$D$18+SUMIF('02_КАЛЕНДАРЬ'!$B$5:$B$369,K$3,'02_КАЛЕНДАРЬ'!$K$5:$K$369)*'01_ВВОД'!$D$26*'01_ВВОД'!$D$28+SUMIF('02_КАЛЕНДАРЬ'!$B$5:$B$369,K$3,'02_КАЛЕНДАРЬ'!$O$5:$O$369)*'01_ВВОД'!$D$31+COUNTIF('02_КАЛЕНДАРЬ'!$B$5:$B$369,K$3)*'01_ВВОД'!$D$40*'01_ВВОД'!$D$39+K24+K41 | ... O29: =SUMIF('02_КАЛЕНДАРЬ'!$B$5:$B$369,O$3,'02_КАЛЕНДАРЬ'!$L$5:$L$369)*'01_ВВОД'!$D$18+SUMIF('02_КАЛЕНДАРЬ'!$B$5:$B$369,O$3,'02_КАЛЕНДАРЬ'!$K$5:$K$369)*'01_ВВОД'!$D$26*'01_ВВОД'!$D$28+SUMIF('02_КАЛЕНДАРЬ'!$B$5:$B$369,O$3,'02_КАЛЕНДАРЬ'!$O$5:$O$369)*'01_ВВОД'!$D$31+COUNTIF('02_КАЛЕНДАРЬ'!$B$5:$B$369,O$3)*'01_ВВОД'!$D$40*'01_ВВОД'!$D$39+O24+O41 | P29: =SUM(D29:O29) | Q29: =P29/12 | R29: руб.
A30: REV.CAFE.LOST | B30: Кафе | C30: Упущенные доходы кафе из-за банкетов | D30: =D29-D26 | E30: =E29-E26 | F30: =F29-F26 | G30: =G29-G26 | H30: =H29-H26 | I30: =I29-I26 | J30: =J29-J26 | K30: =K29-K26 | ... O30: =O29-O26 | P30: =SUM(D30:O30) | Q30: =P30/12 | R30: руб.
A32: БИЗНЕС 2 — БАНКЕТЫ (ОТДЕЛЬНЫЙ ДОХОД)
A33: REV.BANQ.QTY | B33: Банкеты | C33: Количество банкетов | D33: =SUMIF('02_КАЛЕНДАРЬ'!$B$5:$B$369,D$3,'02_КАЛЕНДАРЬ'!$S$5:$S$369) | E33: =SUMIF('02_КАЛЕНДАРЬ'!$B$5:$B$369,E$3,'02_КАЛЕНДАРЬ'!$S$5:$S$369) | F33: =SUMIF('02_КАЛЕНДАРЬ'!$B$5:$B$369,F$3,'02_КАЛЕНДАРЬ'!$S$5:$S$369) | G33: =SUMIF('02_КАЛЕНДАРЬ'!$B$5:$B$369,G$3,'02_КАЛЕНДАРЬ'!$S$5:$S$369) | H33: =SUMIF('02_КАЛЕНДАРЬ'!$B$5:$B$369,H$3,'02_КАЛЕНДАРЬ'!$S$5:$S$369) | I33: =SUMIF('02_КАЛЕНДАРЬ'!$B$5:$B$369,I$3,'02_КАЛЕНДАРЬ'!$S$5:$S$369) | J33: =SUMIF('02_КАЛЕНДАРЬ'!$B$5:$B$369,J$3,'02_КАЛЕНДАРЬ'!$S$5:$S$369) | K33: =SUMIF('02_КАЛЕНДАРЬ'!$B$5:$B$369,K$3,'02_КАЛЕНДАРЬ'!$S$5:$S$369) | ... O33: =SUMIF('02_КАЛЕНДАРЬ'!$B$5:$B$369,O$3,'02_КАЛЕНДАРЬ'!$S$5:$S$369) | P33: =SUM(D33:O33) | Q33: =P33/12 | R33: банкетов
A34: REV.BANQ.PART | B34: Банкеты | C34: Участников на банкет | D34: ='01_ВВОД'!$D$53 | E34: ='01_ВВОД'!$D$53 | F34: ='01_ВВОД'!$D$53 | G34: ='01_ВВОД'!$D$53 | H34: ='01_ВВОД'!$D$53 | I34: ='01_ВВОД'!$D$53 | J34: ='01_ВВОД'!$D$53 | K34: ='01_ВВОД'!$D$53 | ... O34: ='01_ВВОД'!$D$53 | P34: =AVERAGE(D34:O34) | Q34: =P34 | R34: чел.
A35: REV.BANQ.CHECK | B35: Банкеты | C35: Средний чек на человека | D35: ='01_ВВОД'!$D$54 | E35: ='01_ВВОД'!$D$54 | F35: ='01_ВВОД'!$D$54 | G35: ='01_ВВОД'!$D$54 | H35: ='01_ВВОД'!$D$54 | I35: ='01_ВВОД'!$D$54 | J35: ='01_ВВОД'!$D$54 | K35: ='01_ВВОД'!$D$54 | ... O35: ='01_ВВОД'!$D$54 | P35: =AVERAGE(D35:O35) | Q35: =P35 | R35: руб./чел.
A36: REV.BANQ | B36: Банкеты | C36: ДОХОДЫ БАНКЕТОВ | D36: =D33*D34*D35 | E36: =E33*E34*E35 | F36: =F33*F34*F35 | G36: =G33*G34*G35 | H36: =H33*H34*H35 | I36: =I33*I34*I35 | J36: =J33*J34*J35 | K36: =K33*K34*K35 | ... O36: =O33*O34*O35 | P36: =SUM(D36:O36) | Q36: =P36/12 | R36: руб.
A38: REV.PROJECT | B38: Проект | C38: СОВОКУПНЫЕ ДОХОДЫ ПРОЕКТА | D38: =D26+D36 | E38: =E26+E36 | F38: =F26+F36 | G38: =G26+G36 | H38: =H26+H36 | I38: =I26+I36 | J38: =J26+J36 | K38: =K26+K36 | ... O38: =O26+O36 | P38: =SUM(D38:O38) | Q38: =P38/12 | R38: руб.
A39: REV.DINNER.QTY | B39: Кафе — гостиница | C39: Ужины гостиницы | D39: =SUMIF('02_КАЛЕНДАРЬ'!$B$5:$B$369,D$3,'02_КАЛЕНДАРЬ'!$U$5:$U$369) | E39: =SUMIF('02_КАЛЕНДАРЬ'!$B$5:$B$369,E$3,'02_КАЛЕНДАРЬ'!$U$5:$U$369) | F39: =SUMIF('02_КАЛЕНДАРЬ'!$B$5:$B$369,F$3,'02_КАЛЕНДАРЬ'!$U$5:$U$369) | G39: =SUMIF('02_КАЛЕНДАРЬ'!$B$5:$B$369,G$3,'02_КАЛЕНДАРЬ'!$U$5:$U$369) | H39: =SUMIF('02_КАЛЕНДАРЬ'!$B$5:$B$369,H$3,'02_КАЛЕНДАРЬ'!$U$5:$U$369) | I39: =SUMIF('02_КАЛЕНДАРЬ'!$B$5:$B$369,I$3,'02_КАЛЕНДАРЬ'!$U$5:$U$369) | J39: =SUMIF('02_КАЛЕНДАРЬ'!$B$5:$B$369,J$3,'02_КАЛЕНДАРЬ'!$U$5:$U$369) | K39: =SUMIF('02_КАЛЕНДАРЬ'!$B$5:$B$369,K$3,'02_КАЛЕНДАРЬ'!$U$5:$U$369) | ... O39: =SUMIF('02_КАЛЕНДАРЬ'!$B$5:$B$369,O$3,'02_КАЛЕНДАРЬ'!$U$5:$U$369) | P39: =SUM(D39:O39) | Q39: =P39/12 | R39: ужинов
A40: REV.DINNER.CHECK | B40: Кафе — гостиница | C40: Средний чек ужина | D40: ='01_ВВОД'!$D$121 | E40: ='01_ВВОД'!$D$121 | F40: ='01_ВВОД'!$D$121 | G40: ='01_ВВОД'!$D$121 | H40: ='01_ВВОД'!$D$121 | I40: ='01_ВВОД'!$D$121 | J40: ='01_ВВОД'!$D$121 | K40: ='01_ВВОД'!$D$121 | ... O40: ='01_ВВОД'!$D$121 | P40: =AVERAGE(D40:O40) | Q40: =P40 | R40: руб./ужин
A41: REV.DINNER | B41: Кафе — гостиница | C41: Доходы ужинов гостиницы | D41: =D39*D40 | E41: =E39*E40 | F41: =F39*F40 | G41: =G39*G40 | H41: =H39*H40 | I41: =I39*I40 | J41: =J39*J40 | K41: =K39*K40 | ... O41: =O39*O40 | P41: =SUM(D41:O41) | Q41: =P41/12 | R41: руб.

Sheet 04_СЕБЕСТОИМОСТЬ
A1: Себестоимость и прямые переменные расходы
A2: Себестоимость кафе рассчитана по направлениям; упаковка, доставщик и эквайринг показаны отдельно. Списания и инвентаризационные расхождения — редактируемые рабочие резервы.
D3: 1 | E3: 2 | F3: 3 | G3: 4 | H3: 5 | I3: 6 | J3: 7 | K3: 8 | L3: 9 | M3: 10 | N3: 11 | O3: 12
A4: Код | B4: Раздел | C4: Показатель | D4: Сен-26 | E4: Окт-26 | F4: Ноя-26 | G4: Дек-26 | H4: Янв-27 | I4: Фев-27 | J4: Мар-27 | K4: Апр-27 | L4: Май-27 | M4: Июн-27 | N4: Июл-27 | O4: Авг-27 | P4: Итого за год | Q4: Среднее за месяц | R4: Ед.
A5: БИЗНЕС 1 — КАФЕ: СЕБЕСТОИМОСТЬ ПРОДУКТОВ
A6: COGS.ALA.REV | B6: А-ля карт | C6: Доходы | D6: ='03_ДОХОДЫ'!D8 | E6: ='03_ДОХОДЫ'!E8 | F6: ='03_ДОХОДЫ'!F8 | G6: ='03_ДОХОДЫ'!G8 | H6: ='03_ДОХОДЫ'!H8 | I6: ='03_ДОХОДЫ'!I8 | J6: ='03_ДОХОДЫ'!J8 | K6: ='03_ДОХОДЫ'!K8 | ... O6: ='03_ДОХОДЫ'!O8 | P6: =SUM(D6:O6) | Q6: =P6/12 | R6: руб.
A7: COGS.ALA | B7: А-ля карт | C7: Food cost 30% | D7: =D6*'01_ВВОД'!$D$24 | E7: =E6*'01_ВВОД'!$D$24 | F7: =F6*'01_ВВОД'!$D$24 | G7: =G6*'01_ВВОД'!$D$24 | H7: =H6*'01_ВВОД'!$D$24 | I7: =I6*'01_ВВОД'!$D$24 | J7: =J6*'01_ВВОД'!$D$24 | K7: =K6*'01_ВВОД'!$D$24 | ... O7: =O6*'01_ВВОД'!$D$24 | P7: =SUM(D7:O7) | Q7: =P7/12 | R7: руб.
A8: COGS.LUNCH.REV | B8: Бизнес-ланч | C8: Доходы | D8: ='03_ДОХОДЫ'!D12 | E8: ='03_ДОХОДЫ'!E12 | F8: ='03_ДОХОДЫ'!F12 | G8: ='03_ДОХОДЫ'!G12 | H8: ='03_ДОХОДЫ'!H12 | I8: ='03_ДОХОДЫ'!I12 | J8: ='03_ДОХОДЫ'!J12 | K8: ='03_ДОХОДЫ'!K12 | ... O8: ='03_ДОХОДЫ'!O12 | P8: =SUM(D8:O8) | Q8: =P8/12 | R8: руб.
A9: COGS.LUNCH | B9: Бизнес-ланч | C9: Эффективный food cost | D9: =D8*'01_ВВОД'!$D$29 | E9: =E8*'01_ВВОД'!$D$29 | F9: =F8*'01_ВВОД'!$D$29 | G9: =G8*'01_ВВОД'!$D$29 | H9: =H8*'01_ВВОД'!$D$29 | I9: =I8*'01_ВВОД'!$D$29 | J9: =J8*'01_ВВОД'!$D$29 | K9: =K8*'01_ВВОД'!$D$29 | ... O9: =O8*'01_ВВОД'!$D$29 | P9: =SUM(D9:O9) | Q9: =P9/12 | R9: руб.
A10: COGS.DEL.REV | B10: Доставка | C10: Доходы | D10: ='03_ДОХОДЫ'!D16 | E10: ='03_ДОХОДЫ'!E16 | F10: ='03_ДОХОДЫ'!F16 | G10: ='03_ДОХОДЫ'!G16 | H10: ='03_ДОХОДЫ'!H16 | I10: ='03_ДОХОДЫ'!I16 | J10: ='03_ДОХОДЫ'!J16 | K10: ='03_ДОХОДЫ'!K16 | ... O10: ='03_ДОХОДЫ'!O16 | P10: =SUM(D10:O10) | Q10: =P10/12 | R10: руб.
A11: COGS.DEL | B11: Доставка | C11: Food cost 30% | D11: =D10*'01_ВВОД'!$D$35 | E11: =E10*'01_ВВОД'!$D$35 | F11: =F10*'01_ВВОД'!$D$35 | G11: =G10*'01_ВВОД'!$D$35 | H11: =H10*'01_ВВОД'!$D$35 | I11: =I10*'01_ВВОД'!$D$35 | J11: =J10*'01_ВВОД'!$D$35 | K11: =K10*'01_ВВОД'!$D$35 | ... O11: =O10*'01_ВВОД'!$D$35 | P11: =SUM(D11:O11) | Q11: =P11/12 | R11: руб.
A12: COGS.PICK.REV | B12: Самовывоз | C12: Доходы | D12: ='03_ДОХОДЫ'!D20 | E12: ='03_ДОХОДЫ'!E20 | F12: ='03_ДОХОДЫ'!F20 | G12: ='03_ДОХОДЫ'!G20 | H12: ='03_ДОХОДЫ'!H20 | I12: ='03_ДОХОДЫ'!I20 | J12: ='03_ДОХОДЫ'!J20 | K12: ='03_ДОХОДЫ'!K20 | ... O12: ='03_ДОХОДЫ'!O20 | P12: =SUM(D12:O12) | Q12: =P12/12 | R12: руб.
A13: COGS.PICK | B13: Самовывоз | C13: Эффективный food cost | D13: =D12*'01_ВВОД'!$D$42 | E13: =E12*'01_ВВОД'!$D$42 | F13: =F12*'01_ВВОД'!$D$42 | G13: =G12*'01_ВВОД'!$D$42 | H13: =H12*'01_ВВОД'!$D$42 | I13: =I12*'01_ВВОД'!$D$42 | J13: =J12*'01_ВВОД'!$D$42 | K13: =K12*'01_ВВОД'!$D$42 | ... O13: =O12*'01_ВВОД'!$D$42 | P13: =SUM(D13:O13) | Q13: =P13/12 | R13: руб.
A14: COGS.HOTEL.REV | B14: Гостиничный канал | C14: Доходы | D14: ='03_ДОХОДЫ'!D24 | E14: ='03_ДОХОДЫ'!E24 | F14: ='03_ДОХОДЫ'!F24 | G14: ='03_ДОХОДЫ'!G24 | H14: ='03_ДОХОДЫ'!H24 | I14: ='03_ДОХОДЫ'!I24 | J14: ='03_ДОХОДЫ'!J24 | K14: ='03_ДОХОДЫ'!K24 | ... O14: ='03_ДОХОДЫ'!O24 | P14: =SUM(D14:O14) | Q14: =P14/12 | R14: руб.
A15: COGS.HOTEL | B15: Гостиничный канал | C15: Food cost 50% | D15: =D14*'01_ВВОД'!$D$47 | E15: =E14*'01_ВВОД'!$D$47 | F15: =F14*'01_ВВОД'!$D$47 | G15: =G14*'01_ВВОД'!$D$47 | H15: =H14*'01_ВВОД'!$D$47 | I15: =I14*'01_ВВОД'!$D$47 | J15: =J14*'01_ВВОД'!$D$47 | K15: =K14*'01_ВВОД'!$D$47 | ... O15: =O14*'01_ВВОД'!$D$47 | P15: =SUM(D15:O15) | Q15: =P15/12 | R15: руб.
A16: COGS.BASE | B16: Кафе | C16: Продуктовая себестоимость до потерь | D16: =SUM(D7,D9,D11,D13,D15,D42) | E16: =SUM(E7,E9,E11,E13,E15,E42) | F16: =SUM(F7,F9,F11,F13,F15,F42) | G16: =SUM(G7,G9,G11,G13,G15,G42) | H16: =SUM(H7,H9,H11,H13,H15,H42) | I16: =SUM(I7,I9,I11,I13,I15,I42) | J16: =SUM(J7,J9,J11,J13,J15,J42) | K16: =SUM(K7,K9,K11,K13,K15,K42) | ... O16: =SUM(O7,O9,O11,O13,O15,O42) | P16: =SUM(D16:O16) | Q16: =P16/12 | R16: руб.
A17: COGS.SPOIL | B17: Кафе | C17: Списания и порча | D17: =D16*'01_ВВОД'!$D$16 | E17: =E16*'01_ВВОД'!$D$16 | F17: =F16*'01_ВВОД'!$D$16 | G17: =G16*'01_ВВОД'!$D$16 | H17: =H16*'01_ВВОД'!$D$16 | I17: =I16*'01_ВВОД'!$D$16 | J17: =J16*'01_ВВОД'!$D$16 | K17: =K16*'01_ВВОД'!$D$16 | ... O17: =O16*'01_ВВОД'!$D$16 | P17: =SUM(D17:O17) | Q17: =P17/12 | R17: руб.
A18: COGS.INV | B18: Кафе | C18: Инвентаризационные расхождения | D18: =D16*'01_ВВОД'!$D$17 | E18: =E16*'01_ВВОД'!$D$17 | F18: =F16*'01_ВВОД'!$D$17 | G18: =G16*'01_ВВОД'!$D$17 | H18: =H16*'01_ВВОД'!$D$17 | I18: =I16*'01_ВВОД'!$D$17 | J18: =J16*'01_ВВОД'!$D$17 | K18: =K16*'01_ВВОД'!$D$17 | ... O18: =O16*'01_ВВОД'!$D$17 | P18: =SUM(D18:O18) | Q18: =P18/12 | R18: руб.
A19: COGS.TOTAL | B19: Кафе | C19: ИТОГО СЕБЕСТОИМОСТЬ КАФЕ | D19: =SUM(D16:D18) | E19: =SUM(E16:E18) | F19: =SUM(F16:F18) | G19: =SUM(G16:G18) | H19: =SUM(H16:H18) | I19: =SUM(I16:I18) | J19: =SUM(J16:J18) | K19: =SUM(K16:K18) | ... O19: =SUM(O16:O18) | P19: =SUM(D19:O19) | Q19: =P19/12 | R19: руб.
A20: GROSS.PROFIT | B20: Кафе | C20: ВАЛОВАЯ ПРИБЫЛЬ КАФЕ | D20: ='03_ДОХОДЫ'!D26-D19 | E20: ='03_ДОХОДЫ'!E26-E19 | F20: ='03_ДОХОДЫ'!F26-F19 | G20: ='03_ДОХОДЫ'!G26-G19 | H20: ='03_ДОХОДЫ'!H26-H19 | I20: ='03_ДОХОДЫ'!I26-I19 | J20: ='03_ДОХОДЫ'!J26-J19 | K20: ='03_ДОХОДЫ'!K26-K19 | ... O20: ='03_ДОХОДЫ'!O26-O19 | P20: =SUM(D20:O20) | Q20: =P20/12 | R20: руб.
A22: БИЗНЕС 1 — КАФЕ: ПРОЧИЕ ПРЯМЫЕ ПЕРЕМЕННЫЕ РАСХОДЫ
A23: VAR.COURIER | B23: Доставка | C23: Доставщик | D23: ='03_ДОХОДЫ'!D14*'01_ВВОД'!$D$36 | E23: ='03_ДОХОДЫ'!E14*'01_ВВОД'!$D$36 | F23: ='03_ДОХОДЫ'!F14*'01_ВВОД'!$D$36 | G23: ='03_ДОХОДЫ'!G14*'01_ВВОД'!$D$36 | H23: ='03_ДОХОДЫ'!H14*'01_ВВОД'!$D$36 | I23: ='03_ДОХОДЫ'!I14*'01_ВВОД'!$D$36 | J23: ='03_ДОХОДЫ'!J14*'01_ВВОД'!$D$36 | K23: ='03_ДОХОДЫ'!K14*'01_ВВОД'!$D$36 | ... O23: ='03_ДОХОДЫ'!O14*'01_ВВОД'!$D$36 | P23: =SUM(D23:O23) | Q23: =P23/12 | R23: руб.
A24: VAR.DEL.PACK | B24: Доставка | C24: Упаковка | D24: ='03_ДОХОДЫ'!D14*'01_ВВОД'!$D$37 | E24: ='03_ДОХОДЫ'!E14*'01_ВВОД'!$D$37 | F24: ='03_ДОХОДЫ'!F14*'01_ВВОД'!$D$37 | G24: ='03_ДОХОДЫ'!G14*'01_ВВОД'!$D$37 | H24: ='03_ДОХОДЫ'!H14*'01_ВВОД'!$D$37 | I24: ='03_ДОХОДЫ'!I14*'01_ВВОД'!$D$37 | J24: ='03_ДОХОДЫ'!J14*'01_ВВОД'!$D$37 | K24: ='03_ДОХОДЫ'!K14*'01_ВВОД'!$D$37 | ... O24: ='03_ДОХОДЫ'!O14*'01_ВВОД'!$D$37 | P24: =SUM(D24:O24) | Q24: =P24/12 | R24: руб.
A25: VAR.PICK.PACK | B25: Самовывоз | C25: Упаковка | D25: ='03_ДОХОДЫ'!D18*'01_ВВОД'!$D$43 | E25: ='03_ДОХОДЫ'!E18*'01_ВВОД'!$D$43 | F25: ='03_ДОХОДЫ'!F18*'01_ВВОД'!$D$43 | G25: ='03_ДОХОДЫ'!G18*'01_ВВОД'!$D$43 | H25: ='03_ДОХОДЫ'!H18*'01_ВВОД'!$D$43 | I25: ='03_ДОХОДЫ'!I18*'01_ВВОД'!$D$43 | J25: ='03_ДОХОДЫ'!J18*'01_ВВОД'!$D$43 | K25: ='03_ДОХОДЫ'!K18*'01_ВВОД'!$D$43 | ... O25: ='03_ДОХОДЫ'!O18*'01_ВВОД'!$D$43 | P25: =SUM(D25:O25) | Q25: =P25/12 | R25: руб.
A26: VAR.HOTEL.PACK | B26: Гостиница | C26: Упаковка / расходники | D26: ='03_ДОХОДЫ'!D22*'01_ВВОД'!$D$48 | E26: ='03_ДОХОДЫ'!E22*'01_ВВОД'!$D$48 | F26: ='03_ДОХОДЫ'!F22*'01_ВВОД'!$D$48 | G26: ='03_ДОХОДЫ'!G22*'01_ВВОД'!$D$48 | H26: ='03_ДОХОДЫ'!H22*'01_ВВОД'!$D$48 | I26: ='03_ДОХОДЫ'!I22*'01_ВВОД'!$D$48 | J26: ='03_ДОХОДЫ'!J22*'01_ВВОД'!$D$48 | K26: ='03_ДОХОДЫ'!K22*'01_ВВОД'!$D$48 | ... O26: ='03_ДОХОДЫ'!O22*'01_ВВОД'!$D$48 | P26: =SUM(D26:O26) | Q26: =P26/12 | R26: руб.
A27: VAR.ACQ | B27: Кафе | C27: Эквайринг | D27: ='03_ДОХОДЫ'!D8*'01_ВВОД'!$D$25*'01_ВВОД'!$D$14+'03_ДОХОДЫ'!D12*'01_ВВОД'!$D$30*'01_ВВОД'!$D$14+'03_ДОХОДЫ'!D16*'01_ВВОД'!$D$38*'01_ВВОД'!$D$14+'03_ДОХОДЫ'!D20*'01_ВВОД'!$D$44*'01_ВВОД'!$D$14+'03_ДОХОДЫ'!D24*'01_ВВОД'!$D$49*'01_ВВОД'!$D$14 | E27: ='03_ДОХОДЫ'!E8*'01_ВВОД'!$D$25*'01_ВВОД'!$D$14+'03_ДОХОДЫ'!E12*'01_ВВОД'!$D$30*'01_ВВОД'!$D$14+'03_ДОХОДЫ'!E16*'01_ВВОД'!$D$38*'01_ВВОД'!$D$14+'03_ДОХОДЫ'!E20*'01_ВВОД'!$D$44*'01_ВВОД'!$D$14+'03_ДОХОДЫ'!E24*'01_ВВОД'!$D$49*'01_ВВОД'!$D$14 | F27: ='03_ДОХОДЫ'!F8*'01_ВВОД'!$D$25*'01_ВВОД'!$D$14+'03_ДОХОДЫ'!F12*'01_ВВОД'!$D$30*'01_ВВОД'!$D$14+'03_ДОХОДЫ'!F16*'01_ВВОД'!$D$38*'01_ВВОД'!$D$14+'03_ДОХОДЫ'!F20*'01_ВВОД'!$D$44*'01_ВВОД'!$D$14+'03_ДОХОДЫ'!F24*'01_ВВОД'!$D$49*'01_ВВОД'!$D$14 | G27: ='03_ДОХОДЫ'!G8*'01_ВВОД'!$D$25*'01_ВВОД'!$D$14+'03_ДОХОДЫ'!G12*'01_ВВОД'!$D$30*'01_ВВОД'!$D$14+'03_ДОХОДЫ'!G16*'01_ВВОД'!$D$38*'01_ВВОД'!$D$14+'03_ДОХОДЫ'!G20*'01_ВВОД'!$D$44*'01_ВВОД'!$D$14+'03_ДОХОДЫ'!G24*'01_ВВОД'!$D$49*'01_ВВОД'!$D$14 | H27: ='03_ДОХОДЫ'!H8*'01_ВВОД'!$D$25*'01_ВВОД'!$D$14+'03_ДОХОДЫ'!H12*'01_ВВОД'!$D$30*'01_ВВОД'!$D$14+'03_ДОХОДЫ'!H16*'01_ВВОД'!$D$38*'01_ВВОД'!$D$14+'03_ДОХОДЫ'!H20*'01_ВВОД'!$D$44*'01_ВВОД'!$D$14+'03_ДОХОДЫ'!H24*'01_ВВОД'!$D$49*'01_ВВОД'!$D$14 | I27: ='03_ДОХОДЫ'!I8*'01_ВВОД'!$D$25*'01_ВВОД'!$D$14+'03_ДОХОДЫ'!I12*'01_ВВОД'!$D$30*'01_ВВОД'!$D$14+'03_ДОХОДЫ'!I16*'01_ВВОД'!$D$38*'01_ВВОД'!$D$14+'03_ДОХОДЫ'!I20*'01_ВВОД'!$D$44*'01_ВВОД'!$D$14+'03_ДОХОДЫ'!I24*'01_ВВОД'!$D$49*'01_ВВОД'!$D$14 | J27: ='03_ДОХОДЫ'!J8*'01_ВВОД'!$D$25*'01_ВВОД'!$D$14+'03_ДОХОДЫ'!J12*'01_ВВОД'!$D$30*'01_ВВОД'!$D$14+'03_ДОХОДЫ'!J16*'01_ВВОД'!$D$38*'01_ВВОД'!$D$14+'03_ДОХОДЫ'!J20*'01_ВВОД'!$D$44*'01_ВВОД'!$D$14+'03_ДОХОДЫ'!J24*'01_ВВОД'!$D$49*'01_ВВОД'!$D$14 | K27: ='03_ДОХОДЫ'!K8*'01_ВВОД'!$D$25*'01_ВВОД'!$D$14+'03_ДОХОДЫ'!K12*'01_ВВОД'!$D$30*'01_ВВОД'!$D$14+'03_ДОХОДЫ'!K16*'01_ВВОД'!$D$38*'01_ВВОД'!$D$14+'03_ДОХОДЫ'!K20*'01_ВВОД'!$D$44*'01_ВВОД'!$D$14+'03_ДОХОДЫ'!K24*'01_ВВОД'!$D$49*'01_ВВОД'!$D$14 | ... O27: ='03_ДОХОДЫ'!O8*'01_ВВОД'!$D$25*'01_ВВОД'!$D$14+'03_ДОХОДЫ'!O12*'01_ВВОД'!$D$30*'01_ВВОД'!$D$14+'03_ДОХОДЫ'!O16*'01_ВВОД'!$D$38*'01_ВВОД'!$D$14+'03_ДОХОДЫ'!O20*'01_ВВОД'!$D$44*'01_ВВОД'!$D$14+'03_ДОХОДЫ'!O24*'01_ВВОД'!$D$49*'01_ВВОД'!$D$14 | P27: =SUM(D27:O27) | Q27: =P27/12 | R27: руб.
A28: VAR.TOTAL | B28: Кафе | C28: ИТОГО ПРОЧИЕ ПРЯМЫЕ РАСХОДЫ | D28: =SUM(D23:D27,D29) | E28: =SUM(E23:E27,E29) | F28: =SUM(F23:F27,F29) | G28: =SUM(G23:G27,G29) | H28: =SUM(H23:H27,H29) | I28: =SUM(I23:I27,I29) | J28: =SUM(J23:J27,J29) | K28: =SUM(K23:K27,K29) | ... O28: =SUM(O23:O27,O29) | P28: =SUM(D28:O28) | Q28: =P28/12 | R28: руб.
A29: VAR.DINNER.PACK | B29: Гостиница — ужины | C29: Упаковка / расходники ужинов | D29: ='03_ДОХОДЫ'!D39*'01_ВВОД'!$D$123 | E29: ='03_ДОХОДЫ'!E39*'01_ВВОД'!$D$123 | F29: ='03_ДОХОДЫ'!F39*'01_ВВОД'!$D$123 | G29: ='03_ДОХОДЫ'!G39*'01_ВВОД'!$D$123 | H29: ='03_ДОХОДЫ'!H39*'01_ВВОД'!$D$123 | I29: ='03_ДОХОДЫ'!I39*'01_ВВОД'!$D$123 | J29: ='03_ДОХОДЫ'!J39*'01_ВВОД'!$D$123 | K29: ='03_ДОХОДЫ'!K39*'01_ВВОД'!$D$123 | ... O29: ='03_ДОХОДЫ'!O39*'01_ВВОД'!$D$123 | P29: =SUM(D29:O29) | Q29: =P29/12 | R29: руб.
A30: CONTRIB.CAFE | B30: Кафе | C30: МАРЖИНАЛЬНЫЙ ДОХОД КАФЕ | D30: =D20-D28 | E30: =E20-E28 | F30: =F20-F28 | G30: =G20-G28 | H30: =H20-H28 | I30: =I20-I28 | J30: =J20-J28 | K30: =K20-K28 | ... O30: =O20-O28 | P30: =SUM(D30:O30) | Q30: =P30/12 | R30: руб.
A32: БИЗНЕС 2 — БАНКЕТЫ: ПРЯМОЙ ФИНАНСОВЫЙ РЕЗУЛЬТАТ
A33: BANQ.REV | B33: Банкеты | C33: Доходы банкетов | D33: ='03_ДОХОДЫ'!D36 | E33: ='03_ДОХОДЫ'!E36 | F33: ='03_ДОХОДЫ'!F36 | G33: ='03_ДОХОДЫ'!G36 | H33: ='03_ДОХОДЫ'!H36 | I33: ='03_ДОХОДЫ'!I36 | J33: ='03_ДОХОДЫ'!J36 | K33: ='03_ДОХОДЫ'!K36 | ... O33: ='03_ДОХОДЫ'!O36 | P33: =SUM(D33:O33) | Q33: =P33/12 | R33: руб.
A34: BANQ.COGS | B34: Банкеты | C34: Себестоимость 40% | D34: =D33*'01_ВВОД'!$D$55 | E34: =E33*'01_ВВОД'!$D$55 | F34: =F33*'01_ВВОД'!$D$55 | G34: =G33*'01_ВВОД'!$D$55 | H34: =H33*'01_ВВОД'!$D$55 | I34: =I33*'01_ВВОД'!$D$55 | J34: =J33*'01_ВВОД'!$D$55 | K34: =K33*'01_ВВОД'!$D$55 | ... O34: =O33*'01_ВВОД'!$D$55 | P34: =SUM(D34:O34) | Q34: =P34/12 | R34: руб.
A35: BANQ.GROSS | B35: Банкеты | C35: Валовая прибыль | D35: =D33-D34 | E35: =E33-E34 | F35: =F33-F34 | G35: =G33-G34 | H35: =H33-H34 | I35: =I33-I34 | J35: =J33-J34 | K35: =K33-K34 | ... O35: =O33-O34 | P35: =SUM(D35:O35) | Q35: =P35/12 | R35: руб.
A36: BANQ.AGENT | B36: Банкеты | C36: Комиссия агента 10% | D36: =D33*'01_ВВОД'!$D$56 | E36: =E33*'01_ВВОД'!$D$56 | F36: =F33*'01_ВВОД'!$D$56 | G36: =G33*'01_ВВОД'!$D$56 | H36: =H33*'01_ВВОД'!$D$56 | I36: =I33*'01_ВВОД'!$D$56 | J36: =J33*'01_ВВОД'!$D$56 | K36: =K33*'01_ВВОД'!$D$56 | ... O36: =O33*'01_ВВОД'!$D$56 | P36: =SUM(D36:O36) | Q36: =P36/12 | R36: руб.
A37: BANQ.ACQ | B37: Банкеты | C37: Эквайринг | D37: =D33*'01_ВВОД'!$D$57*'01_ВВОД'!$D$14 | E37: =E33*'01_ВВОД'!$D$57*'01_ВВОД'!$D$14 | F37: =F33*'01_ВВОД'!$D$57*'01_ВВОД'!$D$14 | G37: =G33*'01_ВВОД'!$D$57*'01_ВВОД'!$D$14 | H37: =H33*'01_ВВОД'!$D$57*'01_ВВОД'!$D$14 | I37: =I33*'01_ВВОД'!$D$57*'01_ВВОД'!$D$14 | J37: =J33*'01_ВВОД'!$D$57*'01_ВВОД'!$D$14 | K37: =K33*'01_ВВОД'!$D$57*'01_ВВОД'!$D$14 | ... O37: =O33*'01_ВВОД'!$D$57*'01_ВВОД'!$D$14 | P37: =SUM(D37:O37) | Q37: =P37/12 | R37: руб.
A38: BANQ.RESULT | B38: Банкеты | C38: ФИНАНСОВЫЙ РЕЗУЛЬТАТ ДО НАЛОГА | D38: =D35-D36-D37 | E38: =E35-E36-E37 | F38: =F35-F36-F37 | G38: =G35-G36-G37 | H38: =H35-H36-H37 | I38: =I35-I36-I37 | J38: =J35-J36-J37 | K38: =K35-K36-K37 | ... O38: =O35-O36-O37 | P38: =SUM(D38:O38) | Q38: =P38/12 | R38: руб.
A40: CONTRIB.PROJECT | B40: Проект | C40: СОВОКУПНЫЙ МАРЖИНАЛЬНЫЙ РЕЗУЛЬТАТ | D40: =D30+D38 | E40: =E30+E38 | F40: =F30+F38 | G40: =G30+G38 | H40: =H30+H38 | I40: =I30+I38 | J40: =J30+J38 | K40: =K30+K38 | ... O40: =O30+O38 | P40: =SUM(D40:O40) | Q40: =P40/12 | R40: руб.
A41: COGS.DINNER.REV | B41: Гостиница — ужины | C41: Доходы ужинов | D41: ='03_ДОХОДЫ'!D41 | E41: ='03_ДОХОДЫ'!E41 | F41: ='03_ДОХОДЫ'!F41 | G41: ='03_ДОХОДЫ'!G41 | H41: ='03_ДОХОДЫ'!H41 | I41: ='03_ДОХОДЫ'!I41 | J41: ='03_ДОХОДЫ'!J41 | K41: ='03_ДОХОДЫ'!K41 | ... O41: ='03_ДОХОДЫ'!O41 | P41: =SUM(D41:O41) | Q41: =P41/12 | R41: руб.
A42: COGS.DINNER | B42: Гостиница — ужины | C42: Food cost ужинов 30% — как a-la carte | D42: =D41*'01_ВВОД'!$D$122 | E42: =E41*'01_ВВОД'!$D$122 | F42: =F41*'01_ВВОД'!$D$122 | G42: =G41*'01_ВВОД'!$D$122 | H42: =H41*'01_ВВОД'!$D$122 | I42: =I41*'01_ВВОД'!$D$122 | J42: =J41*'01_ВВОД'!$D$122 | K42: =K41*'01_ВВОД'!$D$122 | ... O42: =O41*'01_ВВОД'!$D$122 | P42: =SUM(D42:O42) | Q42: =P42/12 | R42: руб.

Sheet 05_ФОТ
A1: ФОТ, НДФЛ, страховые взносы и подрядчики
A2: Ставки сотрудников заданы как суммы «на руки». Gross = Net / (1 − НДФЛ). Страховые взносы начисляются только на штат; бухгалтерия и ИТ — самозанятые.
A4: ДЕТАЛИЗАЦИЯ ШТАТА КАФЕ
A5: Код | B5: Должность | C5: Ставка net, руб./день | D5: Дней/мес. | E5: Net, руб./мес. | F5: Gross, руб./мес. | G5: НДФЛ | H5: Страховые взносы | I5: Стоимость работодателя | J5: USALI
A6: PAY.CHEF | B6: Шеф | C6: ='01_ВВОД'!$D$63 | D6: ='01_ВВОД'!$D$64 | E6: =C6*D6 | F6: =E6/(1-'01_ВВОД'!$D$60) | G6: =F6-E6 | H6: =F6*'01_ВВОД'!$D$61 | I6: =F6+H6 | J6: Kitchen Payroll
A7: PAY.SOUS | B7: Су-шеф | C7: ='01_ВВОД'!$D$65 | D7: ='01_ВВОД'!$D$66 | E7: =C7*D7 | F7: =E7/(1-'01_ВВОД'!$D$60) | G7: =F7-E7 | H7: =F7*'01_ВВОД'!$D$61 | I7: =F7+H7 | J7: Kitchen Payroll
A8: PAY.COOK | B8: Повар | C8: ='01_ВВОД'!$D$67 | D8: ='01_ВВОД'!$D$68 | E8: =C8*D8 | F8: =E8/(1-'01_ВВОД'!$D$60) | G8: =F8-E8 | H8: =F8*'01_ВВОД'!$D$61 | I8: =F8+H8 | J8: Kitchen Payroll
A9: PAY.BAR | B9: Бармен-бариста-кассир | C9: ='01_ВВОД'!$D$69 | D9: ='01_ВВОД'!$D$70 | E9: =C9*D9 | F9: =E9/(1-'01_ВВОД'!$D$60) | G9: =F9-E9 | H9: =F9*'01_ВВОД'!$D$61 | I9: =F9+H9 | J9: Restaurant Payroll
A10: PAY.GM | B10: Управляющий | C10: ='01_ВВОД'!$D$71 | D10: ='01_ВВОД'!$D$72 | E10: =C10*D10 | F10: =E10/(1-'01_ВВОД'!$D$60) | G10: =F10-E10 | H10: =F10*'01_ВВОД'!$D$61 | I10: =F10+H10 | J10: F&B Management
A11: PAY.MGR | B11: Менеджер | C11: ='01_ВВОД'!$D$73 | D11: ='01_ВВОД'!$D$74 | E11: =C11*D11 | F11: =E11/(1-'01_ВВОД'!$D$60) | G11: =F11-E11 | H11: =F11*'01_ВВОД'!$D$61 | I11: =F11+H11 | J11: F&B Management
A12: PAY.CLEAN | B12: Уборщица-посудомойка | C12: ='01_ВВОД'!$D$75 | D12: ='01_ВВОД'!$D$76 | E12: =C12*D12 | F12: =E12/(1-'01_ВВОД'!$D$60) | G12: =F12-E12 | H12: =F12*'01_ВВОД'!$D$61 | I12: =F12+H12 | J12: Stewarding Payroll
A13: PAY.BUY | B13: Снабженец | C13: ='01_ВВОД'!$D$77 | D13: ='01_ВВОД'!$D$78 | E13: =C13*D13 | F13: =E13/(1-'01_ВВОД'!$D$60) | G13: =F13-E13 | H13: =F13*'01_ВВОД'!$D$61 | I13: =F13+H13 | J13: Purchasing Payroll
A14: PAY.DELMGR | B14: Менеджер доставки | C14: ='01_ВВОД'!$D$79 | D14: ='01_ВВОД'!$D$80 | E14: =C14*D14 | F14: =E14/(1-'01_ВВОД'!$D$60) | G14: =F14-E14 | H14: =F14*'01_ВВОД'!$D$61 | I14: =F14+H14 | J14: Delivery Payroll
A15: ИТОГО ШТАТ | E15: =SUM(E6:E14) | F15: =SUM(F6:F14) | G15: =SUM(G6:G14) | H15: =SUM(H6:H14) | I15: =SUM(I6:I14)
A18: ПОДРЯДЧИКИ / САМОЗАНЯТЫЕ
A19: Код | B19: Исполнитель | C19: Сумма, руб./мес. | D19: НДФЛ работодателя | E19: Страховые взносы | F19: USALI
A20: CONT.ACC | B20: Бухгалтер + бухгалтер-калькулятор | C20: ='01_ВВОД'!$D$81 | D20: 0 | E20: 0 | F20: Administrative & General
A21: CONT.IT | B21: ИТ-специалист | C21: ='01_ВВОД'!$D$82 | D21: 0 | E21: 0 | F21: Information Systems / A&G
A22: ИТОГО ПОДРЯДЧИКИ | C22: =SUM(C20:C21)
A25: ПОМЕСЯЧНЫЙ РАСЧЁТ РАСХОДОВ НА ПЕРСОНАЛ КАФЕ
A26: Код | B26: Раздел | C26: Показатель | D26: Сен-26 | E26: Окт-26 | F26: Ноя-26 | G26: Дек-26 | H26: Янв-27 | I26: Фев-27 | J26: Мар-27 | K26: Апр-27 | L26: Май-27 | M26: Июн-27 | N26: Июл-27 | O26: Авг-27 | P26: Итого за год | Q26: Среднее за месяц | R26: Ед.
A27: PAY.NET | B27: Штат | C27: Net-ФОТ | D27: =$E$15 | E27: =$E$15 | F27: =$E$15 | G27: =$E$15 | H27: =$E$15 | I27: =$E$15 | J27: =$E$15 | K27: =$E$15 | ... O27: =$E$15 | P27: =SUM(D27:O27) | Q27: =P27/12 | R27: руб.
A28: PAY.GROSS | B28: Штат | C28: Gross-ФОТ | D28: =$F$15 | E28: =$F$15 | F28: =$F$15 | G28: =$F$15 | H28: =$F$15 | I28: =$F$15 | J28: =$F$15 | K28: =$F$15 | ... O28: =$F$15 | P28: =SUM(D28:O28) | Q28: =P28/12 | R28: руб.
A29: PAY.NDFL | B29: Штат | C29: НДФЛ | D29: =$G$15 | E29: =$G$15 | F29: =$G$15 | G29: =$G$15 | H29: =$G$15 | I29: =$G$15 | J29: =$G$15 | K29: =$G$15 | ... O29: =$G$15 | P29: =SUM(D29:O29) | Q29: =P29/12 | R29: руб.
A30: PAY.INS | B30: Штат | C30: Страховые взносы | D30: =$H$15 | E30: =$H$15 | F30: =$H$15 | G30: =$H$15 | H30: =$H$15 | I30: =$H$15 | J30: =$H$15 | K30: =$H$15 | ... O30: =$H$15 | P30: =SUM(D30:O30) | Q30: =P30/12 | R30: руб.
A31: PAY.EMPLOYER | B31: Штат | C31: Полная стоимость штата | D31: =$I$15 | E31: =$I$15 | F31: =$I$15 | G31: =$I$15 | H31: =$I$15 | I31: =$I$15 | J31: =$I$15 | K31: =$I$15 | ... O31: =$I$15 | P31: =SUM(D31:O31) | Q31: =P31/12 | R31: руб.
A32: PAY.RESERVE | B32: Штат | C32: Резерв отпусков / болезней / замещений | D32: =D28*'01_ВВОД'!$D$62 | E32: =E28*'01_ВВОД'!$D$62 | F32: =F28*'01_ВВОД'!$D$62 | G32: =G28*'01_ВВОД'!$D$62 | H32: =H28*'01_ВВОД'!$D$62 | I32: =I28*'01_ВВОД'!$D$62 | J32: =J28*'01_ВВОД'!$D$62 | K32: =K28*'01_ВВОД'!$D$62 | ... O32: =O28*'01_ВВОД'!$D$62 | P32: =SUM(D32:O32) | Q32: =P32/12 | R32: руб.
A33: PAY.CONTRACT | B33: Подрядчики | C33: Бухгалтерия и ИТ | D33: =$C$22 | E33: =$C$22 | F33: =$C$22 | G33: =$C$22 | H33: =$C$22 | I33: =$C$22 | J33: =$C$22 | K33: =$C$22 | ... O33: =$C$22 | P33: =SUM(D33:O33) | Q33: =P33/12 | R33: руб.
A34: PAY.TOTAL | B34: Кафе | C34: ИТОГО РАСХОДЫ НА ПЕРСОНАЛ | D34: =SUM(D31:D33) | E34: =SUM(E31:E33) | F34: =SUM(F31:F33) | G34: =SUM(G31:G33) | H34: =SUM(H31:H33) | I34: =SUM(I31:I33) | J34: =SUM(J31:J33) | K34: =SUM(K31:K33) | ... O34: =SUM(O31:O33) | P34: =SUM(D34:O34) | Q34: =P34/12 | R34: руб.

Sheet 06_OPEX_USALI
A1: Операционные расходы кафе по USALI
A2: Все постоянные операционные расходы относятся на кафе. Годовые расходы начисляются равномерно по 1/12; сервис ковров — только октябрь–апрель.
D3: 1 | E3: 2 | F3: 3 | G3: 4 | H3: 5 | I3: 6 | J3: 7 | K3: 8 | L3: 9 | M3: 10 | N3: 11 | O3: 12
A4: Код | B4: USALI-группа | C4: Статья | D4: Сен-26 | E4: Окт-26 | F4: Ноя-26 | G4: Дек-26 | H4: Янв-27 | I4: Фев-27 | J4: Мар-27 | K4: Апр-27 | L4: Май-27 | M4: Июн-27 | N4: Июл-27 | O4: Авг-27 | P4: Итого за год | Q4: Среднее за месяц | R4: Основание / статус
A5: F&B DEPARTMENTAL EXPENSES
A6: OPEX.HOUSEHOLD | B6: F&B DEPARTMENTAL EXPENSES | C6: Хозяйственные расходы | D6: ='01_ВВОД'!$D$87 | E6: ='01_ВВОД'!$D$87 | F6: ='01_ВВОД'!$D$87 | G6: ='01_ВВОД'!$D$87 | H6: ='01_ВВОД'!$D$87 | I6: ='01_ВВОД'!$D$87 | J6: ='01_ВВОД'!$D$87 | K6: ='01_ВВОД'!$D$87 | ... O6: ='01_ВВОД'!$D$87 | P6: =SUM(D6:O6) | Q6: =P6/12 | R6: ежемесячно; Подтверждено
A7: OPEX.COFFEE_RENT | B7: F&B DEPARTMENTAL EXPENSES | C7: Аренда кофемашины | D7: ='01_ВВОД'!$D$90 | E7: ='01_ВВОД'!$D$90 | F7: ='01_ВВОД'!$D$90 | G7: ='01_ВВОД'!$D$90 | H7: ='01_ВВОД'!$D$90 | I7: ='01_ВВОД'!$D$90 | J7: ='01_ВВОД'!$D$90 | K7: ='01_ВВОД'!$D$90 | ... O7: ='01_ВВОД'!$D$90 | P7: =SUM(D7:O7) | Q7: =P7/12 | R7: ежемесячно; Подтверждено
A8: OPEX.SES | B8: F&B DEPARTMENTAL EXPENSES | C8: СЭС / санитарные услуги | D8: ='01_ВВОД'!$D$91 | E8: ='01_ВВОД'!$D$91 | F8: ='01_ВВОД'!$D$91 | G8: ='01_ВВОД'!$D$91 | H8: ='01_ВВОД'!$D$91 | I8: ='01_ВВОД'!$D$91 | J8: ='01_ВВОД'!$D$91 | K8: ='01_ВВОД'!$D$91 | ... O8: ='01_ВВОД'!$D$91 | P8: =SUM(D8:O8) | Q8: =P8/12 | R8: ежемесячно; Подтверждено
A9: OPEX.MUSIC | B9: F&B DEPARTMENTAL EXPENSES | C9: Музыка / авторские права | D9: ='01_ВВОД'!$D$92 | E9: ='01_ВВОД'!$D$92 | F9: ='01_ВВОД'!$D$92 | G9: ='01_ВВОД'!$D$92 | H9: ='01_ВВОД'!$D$92 | I9: ='01_ВВОД'!$D$92 | J9: ='01_ВВОД'!$D$92 | K9: ='01_ВВОД'!$D$92 | ... O9: ='01_ВВОД'!$D$92 | P9: =SUM(D9:O9) | Q9: =P9/12 | R9: ежемесячно; Подтверждено
A10: OPEX.SMALLWARE | B10: F&B DEPARTMENTAL EXPENSES | C10: Малоценка и инвентарь | D10: ='01_ВВОД'!$D$94 | E10: ='01_ВВОД'!$D$94 | F10: ='01_ВВОД'!$D$94 | G10: ='01_ВВОД'!$D$94 | H10: ='01_ВВОД'!$D$94 | I10: ='01_ВВОД'!$D$94 | J10: ='01_ВВОД'!$D$94 | K10: ='01_ВВОД'!$D$94 | ... O10: ='01_ВВОД'!$D$94 | P10: =SUM(D10:O10) | Q10: =P10/12 | R10: ежемесячно; Подтверждено
A11: OPEX.PEST | B11: F&B DEPARTMENTAL EXPENSES | C11: Дезинсекция и дератизация | D11: ='01_ВВОД'!$D$99 | E11: ='01_ВВОД'!$D$99 | F11: ='01_ВВОД'!$D$99 | G11: ='01_ВВОД'!$D$99 | H11: ='01_ВВОД'!$D$99 | I11: ='01_ВВОД'!$D$99 | J11: ='01_ВВОД'!$D$99 | K11: ='01_ВВОД'!$D$99 | ... O11: ='01_ВВОД'!$D$99 | P11: =SUM(D11:O11) | Q11: =P11/12 | R11: ежемесячно; Допущение
A12: OPEX.GEN_CLEAN | B12: F&B DEPARTMENTAL EXPENSES | C12: Генеральная уборка | D12: ='01_ВВОД'!$D$100 | E12: ='01_ВВОД'!$D$100 | F12: ='01_ВВОД'!$D$100 | G12: ='01_ВВОД'!$D$100 | H12: ='01_ВВОД'!$D$100 | I12: ='01_ВВОД'!$D$100 | J12: ='01_ВВОД'!$D$100 | K12: ='01_ВВОД'!$D$100 | ... O12: ='01_ВВОД'!$D$100 | P12: =SUM(D12:O12) | Q12: =P12/12 | R12: ежемесячно; Допущение
A13: OPEX.GREASE | B13: F&B DEPARTMENTAL EXPENSES | C13: Жироуловитель / канализация | D13: ='01_ВВОД'!$D$101 | E13: ='01_ВВОД'!$D$101 | F13: ='01_ВВОД'!$D$101 | G13: ='01_ВВОД'!$D$101 | H13: ='01_ВВОД'!$D$101 | I13: ='01_ВВОД'!$D$101 | J13: ='01_ВВОД'!$D$101 | K13: ='01_ВВОД'!$D$101 | ... O13: ='01_ВВОД'!$D$101 | P13: =SUM(D13:O13) | Q13: =P13/12 | R13: ежемесячно; Допущение
A14: OPEX.LAUNDRY | B14: F&B DEPARTMENTAL EXPENSES | C14: Стирка текстиля / униформы | D14: ='01_ВВОД'!$D$102 | E14: ='01_ВВОД'!$D$102 | F14: ='01_ВВОД'!$D$102 | G14: ='01_ВВОД'!$D$102 | H14: ='01_ВВОД'!$D$102 | I14: ='01_ВВОД'!$D$102 | J14: ='01_ВВОД'!$D$102 | K14: ='01_ВВОД'!$D$102 | ... O14: ='01_ВВОД'!$D$102 | P14: =SUM(D14:O14) | Q14: =P14/12 | R14: ежемесячно; Допущение
A15: OPEX.MEDICAL | B15: F&B DEPARTMENTAL EXPENSES | C15: Медкнижки и обучение | D15: ='01_ВВОД'!$D$112/12 | E15: ='01_ВВОД'!$D$112/12 | F15: ='01_ВВОД'!$D$112/12 | G15: ='01_ВВОД'!$D$112/12 | H15: ='01_ВВОД'!$D$112/12 | I15: ='01_ВВОД'!$D$112/12 | J15: ='01_ВВОД'!$D$112/12 | K15: ='01_ВВОД'!$D$112/12 | ... O15: ='01_ВВОД'!$D$112/12 | P15: =SUM(D15:O15) | Q15: =P15/12 | R15: год / 12; Допущение
A16: OPEX.UNIFORM | B16: F&B DEPARTMENTAL EXPENSES | C16: Униформа | D16: ='01_ВВОД'!$D$113/12 | E16: ='01_ВВОД'!$D$113/12 | F16: ='01_ВВОД'!$D$113/12 | G16: ='01_ВВОД'!$D$113/12 | H16: ='01_ВВОД'!$D$113/12 | I16: ='01_ВВОД'!$D$113/12 | J16: ='01_ВВОД'!$D$113/12 | K16: ='01_ВВОД'!$D$113/12 | ... O16: ='01_ВВОД'!$D$113/12 | P16: =SUM(D16:O16) | Q16: =P16/12 | R16: год / 12; Допущение
A17: OPEX.STAFF_MEALS | B17: F&B DEPARTMENTAL EXPENSES | C17: Питание персонала | D17: ='01_ВВОД'!$D$116 | E17: ='01_ВВОД'!$D$116 | F17: ='01_ВВОД'!$D$116 | G17: ='01_ВВОД'!$D$116 | H17: ='01_ВВОД'!$D$116 | I17: ='01_ВВОД'!$D$116 | J17: ='01_ВВОД'!$D$116 | K17: ='01_ВВОД'!$D$116 | ... O17: ='01_ВВОД'!$D$116 | P17: =SUM(D17:O17) | Q17: =P17/12 | R17: ежемесячно; Требует уточнения
A18: OPEX.F&B DEPARTMENTAL EXPENSES.TOTAL | B18: F&B DEPARTMENTAL EXPENSES | C18: ИТОГО F&B DEPARTMENTAL EXPENSES | D18: =SUM(D6:D17) | E18: =SUM(E6:E17) | F18: =SUM(F6:F17) | G18: =SUM(G6:G17) | H18: =SUM(H6:H17) | I18: =SUM(I6:I17) | J18: =SUM(J6:J17) | K18: =SUM(K6:K17) | ... P18: =SUM(P6:P17) | Q18: =P18/12
A19: ADMINISTRATIVE & GENERAL
A20: OPEX.INTERNET | B20: ADMINISTRATIVE & GENERAL | C20: Интернет и связь | D20: ='01_ВВОД'!$D$85 | E20: ='01_ВВОД'!$D$85 | F20: ='01_ВВОД'!$D$85 | G20: ='01_ВВОД'!$D$85 | H20: ='01_ВВОД'!$D$85 | I20: ='01_ВВОД'!$D$85 | J20: ='01_ВВОД'!$D$85 | K20: ='01_ВВОД'!$D$85 | ... O20: ='01_ВВОД'!$D$85 | P20: =SUM(D20:O20) | Q20: =P20/12 | R20: ежемесячно; Подтверждено
A21: OPEX.CASH_RENT | B21: ADMINISTRATIVE & GENERAL | C21: Аренда кассового оборудования | D21: ='01_ВВОД'!$D$89 | E21: ='01_ВВОД'!$D$89 | F21: ='01_ВВОД'!$D$89 | G21: ='01_ВВОД'!$D$89 | H21: ='01_ВВОД'!$D$89 | I21: ='01_ВВОД'!$D$89 | J21: ='01_ВВОД'!$D$89 | K21: ='01_ВВОД'!$D$89 | ... O21: ='01_ВВОД'!$D$89 | P21: =SUM(D21:O21) | Q21: =P21/12 | R21: ежемесячно; Подтверждено
A22: OPEX.POS | B22: ADMINISTRATIVE & GENERAL | C22: POS / учётная система | D22: ='01_ВВОД'!$D$104 | E22: ='01_ВВОД'!$D$104 | F22: ='01_ВВОД'!$D$104 | G22: ='01_ВВОД'!$D$104 | H22: ='01_ВВОД'!$D$104 | I22: ='01_ВВОД'!$D$104 | J22: ='01_ВВОД'!$D$104 | K22: ='01_ВВОД'!$D$104 | ... O22: ='01_ВВОД'!$D$104 | P22: =SUM(D22:O22) | Q22: =P22/12 | R22: ежемесячно; Допущение
A23: OPEX.BANK_FEES | B23: ADMINISTRATIVE & GENERAL | C23: Банковские комиссии и РКО | D23: ='01_ВВОД'!$D$106 | E23: ='01_ВВОД'!$D$106 | F23: ='01_ВВОД'!$D$106 | G23: ='01_ВВОД'!$D$106 | H23: ='01_ВВОД'!$D$106 | I23: ='01_ВВОД'!$D$106 | J23: ='01_ВВОД'!$D$106 | K23: ='01_ВВОД'!$D$106 | ... O23: ='01_ВВОД'!$D$106 | P23: =SUM(D23:O23) | Q23: =P23/12 | R23: ежемесячно; Допущение
A24: OPEX.LEGAL | B24: ADMINISTRATIVE & GENERAL | C24: Юридическое сопровождение | D24: ='01_ВВОД'!$D$107 | E24: ='01_ВВОД'!$D$107 | F24: ='01_ВВОД'!$D$107 | G24: ='01_ВВОД'!$D$107 | H24: ='01_ВВОД'!$D$107 | I24: ='01_ВВОД'!$D$107 | J24: ='01_ВВОД'!$D$107 | K24: ='01_ВВОД'!$D$107 | ... O24: ='01_ВВОД'!$D$107 | P24: =SUM(D24:O24) | Q24: =P24/12 | R24: ежемесячно; Допущение
A25: OPEX.CLOUD | B25: ADMINISTRATIVE & GENERAL | C25: Резервный интернет / облачные сервисы | D25: ='01_ВВОД'!$D$108 | E25: ='01_ВВОД'!$D$108 | F25: ='01_ВВОД'!$D$108 | G25: ='01_ВВОД'!$D$108 | H25: ='01_ВВОД'!$D$108 | I25: ='01_ВВОД'!$D$108 | J25: ='01_ВВОД'!$D$108 | K25: ='01_ВВОД'!$D$108 | ... O25: ='01_ВВОД'!$D$108 | P25: =SUM(D25:O25) | Q25: =P25/12 | R25: ежемесячно; Допущение
A26: OPEX.OFD_EDO | B26: ADMINISTRATIVE & GENERAL | C26: ОФД, ЭЦП, ЭДО | D26: ='01_ВВОД'!$D$114/12 | E26: ='01_ВВОД'!$D$114/12 | F26: ='01_ВВОД'!$D$114/12 | G26: ='01_ВВОД'!$D$114/12 | H26: ='01_ВВОД'!$D$114/12 | I26: ='01_ВВОД'!$D$114/12 | J26: ='01_ВВОД'!$D$114/12 | K26: ='01_ВВОД'!$D$114/12 | ... O26: ='01_ВВОД'!$D$114/12 | P26: =SUM(D26:O26) | Q26: =P26/12 | R26: год / 12; Допущение
A27: OPEX.ADMINISTRATIVE & GENERAL.TOTAL | B27: ADMINISTRATIVE & GENERAL | C27: ИТОГО ADMINISTRATIVE & GENERAL | D27: =SUM(D20:D26) | E27: =SUM(E20:E26) | F27: =SUM(F20:F26) | G27: =SUM(G20:G26) | H27: =SUM(H20:H26) | I27: =SUM(I20:I26) | J27: =SUM(J20:J26) | K27: =SUM(K20:K26) | ... P27: =SUM(P20:P26) | Q27: =P27/12
A28: SALES & MARKETING
A29: OPEX.MARKETING | B29: SALES & MARKETING | C29: Маркетинг | D29: ='01_ВВОД'!$D$86 | E29: ='01_ВВОД'!$D$86 | F29: ='01_ВВОД'!$D$86 | G29: ='01_ВВОД'!$D$86 | H29: ='01_ВВОД'!$D$86 | I29: ='01_ВВОД'!$D$86 | J29: ='01_ВВОД'!$D$86 | K29: ='01_ВВОД'!$D$86 | ... O29: ='01_ВВОД'!$D$86 | P29: =SUM(D29:O29) | Q29: =P29/12 | R29: ежемесячно; Подтверждено
A30: OPEX.SALES & MARKETING.TOTAL | B30: SALES & MARKETING | C30: ИТОГО SALES & MARKETING | D30: =SUM(D29:D29) | E30: =SUM(E29:E29) | F30: =SUM(F29:F29) | G30: =SUM(G29:G29) | H30: =SUM(H29:H29) | I30: =SUM(I29:I29) | J30: =SUM(J29:J29) | K30: =SUM(K29:K29) | ... P30: =SUM(P29:P29) | Q30: =P30/12
A31: PROPERTY OPERATIONS & MAINTENANCE
A32: OPEX.EQUIP_MAINT | B32: PROPERTY OPERATIONS & MAINTENANCE | C32: Обслуживание холодильного и теплового оборудования | D32: ='01_ВВОД'!$D$88 | E32: ='01_ВВОД'!$D$88 | F32: ='01_ВВОД'!$D$88 | G32: ='01_ВВОД'!$D$88 | H32: ='01_ВВОД'!$D$88 | I32: ='01_ВВОД'!$D$88 | J32: ='01_ВВОД'!$D$88 | K32: ='01_ВВОД'!$D$88 | ... O32: ='01_ВВОД'!$D$88 | P32: =SUM(D32:O32) | Q32: =P32/12 | R32: ежемесячно; Подтверждено
A33: OPEX.VENT | B33: PROPERTY OPERATIONS & MAINTENANCE | C33: Обслуживание вентиляции | D33: ='01_ВВОД'!$D$93 | E33: ='01_ВВОД'!$D$93 | F33: ='01_ВВОД'!$D$93 | G33: ='01_ВВОД'!$D$93 | H33: ='01_ВВОД'!$D$93 | I33: ='01_ВВОД'!$D$93 | J33: ='01_ВВОД'!$D$93 | K33: ='01_ВВОД'!$D$93 | ... O33: ='01_ВВОД'!$D$93 | P33: =SUM(D33:O33) | Q33: =P33/12 | R33: ежемесячно; Подтверждено
A34: OPEX.CARPETS | B34: PROPERTY OPERATIONS & MAINTENANCE | C34: Сервис грязезащитных ковров | D34: =IF(AND(D$3>=2,D$3<=8),'01_ВВОД'!$D$95,0) | E34: =IF(AND(E$3>=2,E$3<=8),'01_ВВОД'!$D$95,0) | F34: =IF(AND(F$3>=2,F$3<=8),'01_ВВОД'!$D$95,0) | G34: =IF(AND(G$3>=2,G$3<=8),'01_ВВОД'!$D$95,0) | H34: =IF(AND(H$3>=2,H$3<=8),'01_ВВОД'!$D$95,0) | I34: =IF(AND(I$3>=2,I$3<=8),'01_ВВОД'!$D$95,0) | J34: =IF(AND(J$3>=2,J$3<=8),'01_ВВОД'!$D$95,0) | K34: =IF(AND(K$3>=2,K$3<=8),'01_ВВОД'!$D$95,0) | ... O34: =IF(AND(O$3>=2,O$3<=8),'01_ВВОД'!$D$95,0) | P34: =SUM(D34:O34) | Q34: =P34/12 | R34: октябрь–апрель; Допущение
A35: OPEX.CURRENT_REPAIR | B35: PROPERTY OPERATIONS & MAINTENANCE | C35: Текущий ремонт помещений | D35: ='01_ВВОД'!$D$97 | E35: ='01_ВВОД'!$D$97 | F35: ='01_ВВОД'!$D$97 | G35: ='01_ВВОД'!$D$97 | H35: ='01_ВВОД'!$D$97 | I35: ='01_ВВОД'!$D$97 | J35: ='01_ВВОД'!$D$97 | K35: ='01_ВВОД'!$D$97 | ... O35: ='01_ВВОД'!$D$97 | P35: =SUM(D35:O35) | Q35: =P35/12 | R35: ежемесячно; Допущение
A36: OPEX.EMERG_REPAIR | B36: PROPERTY OPERATIONS & MAINTENANCE | C36: Аварийный ремонт оборудования | D36: ='01_ВВОД'!$D$98 | E36: ='01_ВВОД'!$D$98 | F36: ='01_ВВОД'!$D$98 | G36: ='01_ВВОД'!$D$98 | H36: ='01_ВВОД'!$D$98 | I36: ='01_ВВОД'!$D$98 | J36: ='01_ВВОД'!$D$98 | K36: ='01_ВВОД'!$D$98 | ... O36: ='01_ВВОД'!$D$98 | P36: =SUM(D36:O36) | Q36: =P36/12 | R36: ежемесячно; Допущение
A37: OPEX.FIRE_ALARM | B37: PROPERTY OPERATIONS & MAINTENANCE | C37: Обслуживание пожарной сигнализации | D37: ='01_ВВОД'!$D$103 | E37: ='01_ВВОД'!$D$103 | F37: ='01_ВВОД'!$D$103 | G37: ='01_ВВОД'!$D$103 | H37: ='01_ВВОД'!$D$103 | I37: ='01_ВВОД'!$D$103 | J37: ='01_ВВОД'!$D$103 | K37: ='01_ВВОД'!$D$103 | ... O37: ='01_ВВОД'!$D$103 | P37: =SUM(D37:O37) | Q37: =P37/12 | R37: ежемесячно; Допущение
A38: OPEX.SECURITY | B38: PROPERTY OPERATIONS & MAINTENANCE | C38: Охрана / тревожная кнопка | D38: ='01_ВВОД'!$D$105 | E38: ='01_ВВОД'!$D$105 | F38: ='01_ВВОД'!$D$105 | G38: ='01_ВВОД'!$D$105 | H38: ='01_ВВОД'!$D$105 | I38: ='01_ВВОД'!$D$105 | J38: ='01_ВВОД'!$D$105 | K38: ='01_ВВОД'!$D$105 | ... O38: ='01_ВВОД'!$D$105 | P38: =SUM(D38:O38) | Q38: =P38/12 | R38: ежемесячно; Допущение
A39: OPEX.DUCT_CLEAN | B39: PROPERTY OPERATIONS & MAINTENANCE | C39: Очистка вытяжки и воздуховодов | D39: ='01_ВВОД'!$D$109/12 | E39: ='01_ВВОД'!$D$109/12 | F39: ='01_ВВОД'!$D$109/12 | G39: ='01_ВВОД'!$D$109/12 | H39: ='01_ВВОД'!$D$109/12 | I39: ='01_ВВОД'!$D$109/12 | J39: ='01_ВВОД'!$D$109/12 | K39: ='01_ВВОД'!$D$109/12 | ... O39: ='01_ВВОД'!$D$109/12 | P39: =SUM(D39:O39) | Q39: =P39/12 | R39: год / 12; Допущение
A40: OPEX.ELECTRO | B40: PROPERTY OPERATIONS & MAINTENANCE | C40: Электроизмерения | D40: ='01_ВВОД'!$D$110/12 | E40: ='01_ВВОД'!$D$110/12 | F40: ='01_ВВОД'!$D$110/12 | G40: ='01_ВВОД'!$D$110/12 | H40: ='01_ВВОД'!$D$110/12 | I40: ='01_ВВОД'!$D$110/12 | J40: ='01_ВВОД'!$D$110/12 | K40: ='01_ВВОД'!$D$110/12 | ... O40: ='01_ВВОД'!$D$110/12 | P40: =SUM(D40:O40) | Q40: =P40/12 | R40: год / 12; Допущение
A41: OPEX.FIRE_CHECK | B41: PROPERTY OPERATIONS & MAINTENANCE | C41: Огнетушители и пожарные проверки | D41: ='01_ВВОД'!$D$111/12 | E41: ='01_ВВОД'!$D$111/12 | F41: ='01_ВВОД'!$D$111/12 | G41: ='01_ВВОД'!$D$111/12 | H41: ='01_ВВОД'!$D$111/12 | I41: ='01_ВВОД'!$D$111/12 | J41: ='01_ВВОД'!$D$111/12 | K41: ='01_ВВОД'!$D$111/12 | ... O41: ='01_ВВОД'!$D$111/12 | P41: =SUM(D41:O41) | Q41: =P41/12 | R41: год / 12; Допущение
A42: OPEX.WINDOWS | B42: PROPERTY OPERATIONS & MAINTENANCE | C42: Мытьё окон / чистка мебели | D42: ='01_ВВОД'!$D$115/12 | E42: ='01_ВВОД'!$D$115/12 | F42: ='01_ВВОД'!$D$115/12 | G42: ='01_ВВОД'!$D$115/12 | H42: ='01_ВВОД'!$D$115/12 | I42: ='01_ВВОД'!$D$115/12 | J42: ='01_ВВОД'!$D$115/12 | K42: ='01_ВВОД'!$D$115/12 | ... O42: ='01_ВВОД'!$D$115/12 | P42: =SUM(D42:O42) | Q42: =P42/12 | R42: год / 12; Допущение
A43: OPEX.PROPERTY OPERATIONS & MAINTENANCE.TOTAL | B43: PROPERTY OPERATIONS & MAINTENANCE | C43: ИТОГО PROPERTY OPERATIONS & MAINTENANCE | D43: =SUM(D32:D42) | E43: =SUM(E32:E42) | F43: =SUM(F32:F42) | G43: =SUM(G32:G42) | H43: =SUM(H32:H42) | I43: =SUM(I32:I42) | J43: =SUM(J32:J42) | K43: =SUM(K32:K42) | ... P43: =SUM(P32:P42) | Q43: =P43/12
A44: UTILITIES
A45: OPEX.UTILITIES | B45: UTILITIES | C45: Коммунальные платежи | D45: ='01_ВВОД'!$D$83 | E45: ='01_ВВОД'!$D$83 | F45: ='01_ВВОД'!$D$83 | G45: ='01_ВВОД'!$D$83 | H45: ='01_ВВОД'!$D$83 | I45: ='01_ВВОД'!$D$83 | J45: ='01_ВВОД'!$D$83 | K45: ='01_ВВОД'!$D$83 | ... O45: ='01_ВВОД'!$D$83 | P45: =SUM(D45:O45) | Q45: =P45/12 | R45: ежемесячно; Подтверждено
A46: OPEX.WASTE | B46: UTILITIES | C46: Вывоз мусора | D46: ='01_ВВОД'!$D$84 | E46: ='01_ВВОД'!$D$84 | F46: ='01_ВВОД'!$D$84 | G46: ='01_ВВОД'!$D$84 | H46: ='01_ВВОД'!$D$84 | I46: ='01_ВВОД'!$D$84 | J46: ='01_ВВОД'!$D$84 | K46: ='01_ВВОД'!$D$84 | ... O46: ='01_ВВОД'!$D$84 | P46: =SUM(D46:O46) | Q46: =P46/12 | R46: ежемесячно; Подтверждено
A47: OPEX.UTILITIES.TOTAL | B47: UTILITIES | C47: ИТОГО UTILITIES | D47: =SUM(D45:D46) | E47: =SUM(E45:E46) | F47: =SUM(F45:F46) | G47: =SUM(G45:G46) | H47: =SUM(H45:H46) | I47: =SUM(I45:I46) | J47: =SUM(J45:J46) | K47: =SUM(K45:K46) | ... P47: =SUM(P45:P46) | Q47: =P47/12
A48: FIXED CHARGES
A49: OPEX.RENT_MONTH | B49: FIXED CHARGES | C49: Аренда: 80,9 м² × 1 000 руб./м² | D49: ='01_ВВОД'!$D$9 | E49: ='01_ВВОД'!$D$9 | F49: ='01_ВВОД'!$D$9 | G49: ='01_ВВОД'!$D$9 | H49: ='01_ВВОД'!$D$9 | I49: ='01_ВВОД'!$D$9 | J49: ='01_ВВОД'!$D$9 | K49: ='01_ВВОД'!$D$9 | ... O49: ='01_ВВОД'!$D$9 | P49: =SUM(D49:O49) | Q49: =P49/12 | R49: ежемесячно; Расчёт
A50: OPEX.INSURANCE | B50: FIXED CHARGES | C50: Страхование имущества и ответственности | D50: ='01_ВВОД'!$D$96/12 | E50: ='01_ВВОД'!$D$96/12 | F50: ='01_ВВОД'!$D$96/12 | G50: ='01_ВВОД'!$D$96/12 | H50: ='01_ВВОД'!$D$96/12 | I50: ='01_ВВОД'!$D$96/12 | J50: ='01_ВВОД'!$D$96/12 | K50: ='01_ВВОД'!$D$96/12 | ... O50: ='01_ВВОД'!$D$96/12 | P50: =SUM(D50:O50) | Q50: =P50/12 | R50: год / 12; Допущение
A51: OPEX.FIXED CHARGES.TOTAL | B51: FIXED CHARGES | C51: ИТОГО FIXED CHARGES | D51: =SUM(D49:D50) | E51: =SUM(E49:E50) | F51: =SUM(F49:F50) | G51: =SUM(G49:G50) | H51: =SUM(H49:H50) | I51: =SUM(I49:I50) | J51: =SUM(J49:J50) | K51: =SUM(K49:K50) | ... P51: =SUM(P49:P50) | Q51: =P51/12
A52: OPEX.TOTAL | B52: Кафе | C52: ИТОГО OPEX КАФЕ БЕЗ ПЕРСОНАЛА | D52: =SUM(D18,D27,D30,D43,D47,D51) | E52: =SUM(E18,E27,E30,E43,E47,E51) | F52: =SUM(F18,F27,F30,F43,F47,F51) | G52: =SUM(G18,G27,G30,G43,G47,G51) | H52: =SUM(H18,H27,H30,H43,H47,H51) | I52: =SUM(I18,I27,I30,I43,I47,I51) | J52: =SUM(J18,J27,J30,J43,J47,J51) | K52: =SUM(K18,K27,K30,K43,K47,K51) | ... O52: =SUM(O18,O27,O30,O43,O47,O51) | P52: =SUM(D52:O52) | Q52: =P52/12

Sheet 07_PNL_НАЛОГИ
A1: P&L, налоги и прибыль
A2: Два управленческих бизнеса: КАФЕ несёт весь ФОТ и OPEX; БАНКЕТЫ имеют только собственную себестоимость, агента и эквайринг. УСН считается консолидированно и распределяется по выручке для управленческого результата.
D3: 1 | E3: 2 | F3: 3 | G3: 4 | H3: 5 | I3: 6 | J3: 7 | K3: 8 | L3: 9 | M3: 10 | N3: 11 | O3: 12
A4: Код | B4: Бизнес / уровень | C4: Показатель | D4: Сен-26 | E4: Окт-26 | F4: Ноя-26 | G4: Дек-26 | H4: Янв-27 | I4: Фев-27 | J4: Мар-27 | K4: Апр-27 | L4: Май-27 | M4: Июн-27 | N4: Июл-27 | O4: Авг-27 | P4: Итого за год | Q4: Среднее за месяц | R4: Ед.
A5: БИЗНЕС 1 — КАФЕ
A6: PNL.CAFE.REV | B6: Кафе | C6: Доходы кафе | D6: ='03_ДОХОДЫ'!D26 | E6: ='03_ДОХОДЫ'!E26 | F6: ='03_ДОХОДЫ'!F26 | G6: ='03_ДОХОДЫ'!G26 | H6: ='03_ДОХОДЫ'!H26 | I6: ='03_ДОХОДЫ'!I26 | J6: ='03_ДОХОДЫ'!J26 | K6: ='03_ДОХОДЫ'!K26 | ... O6: ='03_ДОХОДЫ'!O26 | P6: =SUM(D6:O6) | Q6: =P6/12 | R6: руб.
A7: PNL.CAFE.COGS | B7: Кафе | C7: Себестоимость кафе | D7: ='04_СЕБЕСТОИМОСТЬ'!D19 | E7: ='04_СЕБЕСТОИМОСТЬ'!E19 | F7: ='04_СЕБЕСТОИМОСТЬ'!F19 | G7: ='04_СЕБЕСТОИМОСТЬ'!G19 | H7: ='04_СЕБЕСТОИМОСТЬ'!H19 | I7: ='04_СЕБЕСТОИМОСТЬ'!I19 | J7: ='04_СЕБЕСТОИМОСТЬ'!J19 | K7: ='04_СЕБЕСТОИМОСТЬ'!K19 | ... O7: ='04_СЕБЕСТОИМОСТЬ'!O19 | P7: =SUM(D7:O7) | Q7: =P7/12 | R7: руб.
A8: PNL.CAFE.GROSS | B8: Кафе | C8: ВАЛОВАЯ ПРИБЫЛЬ | D8: =D6-D7 | E8: =E6-E7 | F8: =F6-F7 | G8: =G6-G7 | H8: =H6-H7 | I8: =I6-I7 | J8: =J6-J7 | K8: =K6-K7 | ... O8: =O6-O7 | P8: =SUM(D8:O8) | Q8: =P8/12 | R8: руб.
A9: PNL.CAFE.VAR | B9: Кафе | C9: Прочие прямые переменные расходы | D9: ='04_СЕБЕСТОИМОСТЬ'!D28 | E9: ='04_СЕБЕСТОИМОСТЬ'!E28 | F9: ='04_СЕБЕСТОИМОСТЬ'!F28 | G9: ='04_СЕБЕСТОИМОСТЬ'!G28 | H9: ='04_СЕБЕСТОИМОСТЬ'!H28 | I9: ='04_СЕБЕСТОИМОСТЬ'!I28 | J9: ='04_СЕБЕСТОИМОСТЬ'!J28 | K9: ='04_СЕБЕСТОИМОСТЬ'!K28 | ... O9: ='04_СЕБЕСТОИМОСТЬ'!O28 | P9: =SUM(D9:O9) | Q9: =P9/12 | R9: руб.
A10: PNL.CAFE.CONTRIB | B10: Кафе | C10: МАРЖИНАЛЬНЫЙ ДОХОД | D10: =D8-D9 | E10: =E8-E9 | F10: =F8-F9 | G10: =G8-G9 | H10: =H8-H9 | I10: =I8-I9 | J10: =J8-J9 | K10: =K8-K9 | ... O10: =O8-O9 | P10: =SUM(D10:O10) | Q10: =P10/12 | R10: руб.
A11: PNL.CAFE.PAY | B11: Кафе | C11: ФОТ и подрядчики | D11: ='05_ФОТ'!D34 | E11: ='05_ФОТ'!E34 | F11: ='05_ФОТ'!F34 | G11: ='05_ФОТ'!G34 | H11: ='05_ФОТ'!H34 | I11: ='05_ФОТ'!I34 | J11: ='05_ФОТ'!J34 | K11: ='05_ФОТ'!K34 | ... O11: ='05_ФОТ'!O34 | P11: =SUM(D11:O11) | Q11: =P11/12 | R11: руб.
A12: PNL.CAFE.FB | B12: Кафе | C12: F&B Departmental Expenses | D12: ='06_OPEX_USALI'!D18 | E12: ='06_OPEX_USALI'!E18 | F12: ='06_OPEX_USALI'!F18 | G12: ='06_OPEX_USALI'!G18 | H12: ='06_OPEX_USALI'!H18 | I12: ='06_OPEX_USALI'!I18 | J12: ='06_OPEX_USALI'!J18 | K12: ='06_OPEX_USALI'!K18 | ... O12: ='06_OPEX_USALI'!O18 | P12: =SUM(D12:O12) | Q12: =P12/12 | R12: руб.
A13: PNL.CAFE.DEP | B13: Кафе | C13: ПРИБЫЛЬ ПОДРАЗДЕЛЕНИЯ | D13: =D10-D11-D12 | E13: =E10-E11-E12 | F13: =F10-F11-F12 | G13: =G10-G11-G12 | H13: =H10-H11-H12 | I13: =I10-I11-I12 | J13: =J10-J11-J12 | K13: =K10-K11-K12 | ... O13: =O10-O11-O12 | P13: =SUM(D13:O13) | Q13: =P13/12 | R13: руб.
A14: PNL.CAFE.AG | B14: Кафе | C14: Administrative & General | D14: ='06_OPEX_USALI'!D27 | E14: ='06_OPEX_USALI'!E27 | F14: ='06_OPEX_USALI'!F27 | G14: ='06_OPEX_USALI'!G27 | H14: ='06_OPEX_USALI'!H27 | I14: ='06_OPEX_USALI'!I27 | J14: ='06_OPEX_USALI'!J27 | K14: ='06_OPEX_USALI'!K27 | ... O14: ='06_OPEX_USALI'!O27 | P14: =SUM(D14:O14) | Q14: =P14/12 | R14: руб.
A15: PNL.CAFE.SM | B15: Кафе | C15: Sales & Marketing | D15: ='06_OPEX_USALI'!D30 | E15: ='06_OPEX_USALI'!E30 | F15: ='06_OPEX_USALI'!F30 | G15: ='06_OPEX_USALI'!G30 | H15: ='06_OPEX_USALI'!H30 | I15: ='06_OPEX_USALI'!I30 | J15: ='06_OPEX_USALI'!J30 | K15: ='06_OPEX_USALI'!K30 | ... O15: ='06_OPEX_USALI'!O30 | P15: =SUM(D15:O15) | Q15: =P15/12 | R15: руб.
A16: PNL.CAFE.POM | B16: Кафе | C16: Property Operations & Maintenance | D16: ='06_OPEX_USALI'!D43 | E16: ='06_OPEX_USALI'!E43 | F16: ='06_OPEX_USALI'!F43 | G16: ='06_OPEX_USALI'!G43 | H16: ='06_OPEX_USALI'!H43 | I16: ='06_OPEX_USALI'!I43 | J16: ='06_OPEX_USALI'!J43 | K16: ='06_OPEX_USALI'!K43 | ... O16: ='06_OPEX_USALI'!O43 | P16: =SUM(D16:O16) | Q16: =P16/12 | R16: руб.
A17: PNL.CAFE.UTIL | B17: Кафе | C17: Utilities | D17: ='06_OPEX_USALI'!D47 | E17: ='06_OPEX_USALI'!E47 | F17: ='06_OPEX_USALI'!F47 | G17: ='06_OPEX_USALI'!G47 | H17: ='06_OPEX_USALI'!H47 | I17: ='06_OPEX_USALI'!I47 | J17: ='06_OPEX_USALI'!J47 | K17: ='06_OPEX_USALI'!K47 | ... O17: ='06_OPEX_USALI'!O47 | P17: =SUM(D17:O17) | Q17: =P17/12 | R17: руб.
A18: PNL.CAFE.GOP | B18: Кафе | C18: GOP / ОПЕРАЦИОННАЯ ПРИБЫЛЬ | D18: =D13-SUM(D14:D17) | E18: =E13-SUM(E14:E17) | F18: =F13-SUM(F14:F17) | G18: =G13-SUM(G14:G17) | H18: =H13-SUM(H14:H17) | I18: =I13-SUM(I14:I17) | J18: =J13-SUM(J14:J17) | K18: =K13-SUM(K14:K17) | ... O18: =O13-SUM(O14:O17) | P18: =SUM(D18:O18) | Q18: =P18/12 | R18: руб.
A19: PNL.CAFE.FIX | B19: Кафе | C19: Fixed Charges: аренда и страхование | D19: ='06_OPEX_USALI'!D51 | E19: ='06_OPEX_USALI'!E51 | F19: ='06_OPEX_USALI'!F51 | G19: ='06_OPEX_USALI'!G51 | H19: ='06_OPEX_USALI'!H51 | I19: ='06_OPEX_USALI'!I51 | J19: ='06_OPEX_USALI'!J51 | K19: ='06_OPEX_USALI'!K51 | ... O19: ='06_OPEX_USALI'!O51 | P19: =SUM(D19:O19) | Q19: =P19/12 | R19: руб.
A20: PNL.CAFE.PBT | B20: Кафе | C20: ПРИБЫЛЬ КАФЕ ДО НАЛОГА | D20: =D18-D19 | E20: =E18-E19 | F20: =F18-F19 | G20: =G18-G19 | H20: =H18-H19 | I20: =I18-I19 | J20: =J18-J19 | K20: =K18-K19 | ... O20: =O18-O19 | P20: =SUM(D20:O20) | Q20: =P20/12 | R20: руб.
A21: PNL.DINNER.REV | B21: Кафе — гостиница | C21: Доходы ужинов | D21: ='03_ДОХОДЫ'!D41 | E21: ='03_ДОХОДЫ'!E41 | F21: ='03_ДОХОДЫ'!F41 | G21: ='03_ДОХОДЫ'!G41 | H21: ='03_ДОХОДЫ'!H41 | I21: ='03_ДОХОДЫ'!I41 | J21: ='03_ДОХОДЫ'!J41 | K21: ='03_ДОХОДЫ'!K41 | ... O21: ='03_ДОХОДЫ'!O41 | P21: =SUM(D21:O21) | Q21: =P21/12 | R21: руб.
A22: PNL.DINNER.COGS | B22: Кафе — гостиница | C22: Себестоимость ужинов — 30% как a-la carte | D22: ='04_СЕБЕСТОИМОСТЬ'!D42+'04_СЕБЕСТОИМОСТЬ'!D29 | E22: ='04_СЕБЕСТОИМОСТЬ'!E42+'04_СЕБЕСТОИМОСТЬ'!E29 | F22: ='04_СЕБЕСТОИМОСТЬ'!F42+'04_СЕБЕСТОИМОСТЬ'!F29 | G22: ='04_СЕБЕСТОИМОСТЬ'!G42+'04_СЕБЕСТОИМОСТЬ'!G29 | H22: ='04_СЕБЕСТОИМОСТЬ'!H42+'04_СЕБЕСТОИМОСТЬ'!H29 | I22: ='04_СЕБЕСТОИМОСТЬ'!I42+'04_СЕБЕСТОИМОСТЬ'!I29 | J22: ='04_СЕБЕСТОИМОСТЬ'!J42+'04_СЕБЕСТОИМОСТЬ'!J29 | K22: ='04_СЕБЕСТОИМОСТЬ'!K42+'04_СЕБЕСТОИМОСТЬ'!K29 | ... O22: ='04_СЕБЕСТОИМОСТЬ'!O42+'04_СЕБЕСТОИМОСТЬ'!O29 | P22: =SUM(D22:O22) | Q22: =P22/12 | R22: руб.
A23: PNL.DINNER.CONTRIB | B23: Кафе — гостиница | C23: Маржинальный результат ужинов | D23: =D21-D22 | E23: =E21-E22 | F23: =F21-F22 | G23: =G21-G22 | H23: =H21-H22 | I23: =I21-I22 | J23: =J21-J22 | K23: =K21-K22 | ... O23: =O21-O22 | P23: =SUM(D23:O23) | Q23: =P23/12 | R23: руб.
A24: БИЗНЕС 2 — БАНКЕТЫ
A25: PNL.BANQ.REV | B25: Банкеты | C25: Доходы банкетов | D25: ='03_ДОХОДЫ'!D36 | E25: ='03_ДОХОДЫ'!E36 | F25: ='03_ДОХОДЫ'!F36 | G25: ='03_ДОХОДЫ'!G36 | H25: ='03_ДОХОДЫ'!H36 | I25: ='03_ДОХОДЫ'!I36 | J25: ='03_ДОХОДЫ'!J36 | K25: ='03_ДОХОДЫ'!K36 | ... O25: ='03_ДОХОДЫ'!O36 | P25: =SUM(D25:O25) | Q25: =P25/12 | R25: руб.
A26: PNL.BANQ.COGS | B26: Банкеты | C26: Себестоимость | D26: ='04_СЕБЕСТОИМОСТЬ'!D34 | E26: ='04_СЕБЕСТОИМОСТЬ'!E34 | F26: ='04_СЕБЕСТОИМОСТЬ'!F34 | G26: ='04_СЕБЕСТОИМОСТЬ'!G34 | H26: ='04_СЕБЕСТОИМОСТЬ'!H34 | I26: ='04_СЕБЕСТОИМОСТЬ'!I34 | J26: ='04_СЕБЕСТОИМОСТЬ'!J34 | K26: ='04_СЕБЕСТОИМОСТЬ'!K34 | ... O26: ='04_СЕБЕСТОИМОСТЬ'!O34 | P26: =SUM(D26:O26) | Q26: =P26/12 | R26: руб.
A27: PNL.BANQ.GROSS | B27: Банкеты | C27: Валовая прибыль | D27: =D25-D26 | E27: =E25-E26 | F27: =F25-F26 | G27: =G25-G26 | H27: =H25-H26 | I27: =I25-I26 | J27: =J25-J26 | K27: =K25-K26 | ... O27: =O25-O26 | P27: =SUM(D27:O27) | Q27: =P27/12 | R27: руб.
A28: PNL.BANQ.AGENT | B28: Банкеты | C28: Агент и эквайринг | D28: ='04_СЕБЕСТОИМОСТЬ'!D36+'04_СЕБЕСТОИМОСТЬ'!D37 | E28: ='04_СЕБЕСТОИМОСТЬ'!E36+'04_СЕБЕСТОИМОСТЬ'!E37 | F28: ='04_СЕБЕСТОИМОСТЬ'!F36+'04_СЕБЕСТОИМОСТЬ'!F37 | G28: ='04_СЕБЕСТОИМОСТЬ'!G36+'04_СЕБЕСТОИМОСТЬ'!G37 | H28: ='04_СЕБЕСТОИМОСТЬ'!H36+'04_СЕБЕСТОИМОСТЬ'!H37 | I28: ='04_СЕБЕСТОИМОСТЬ'!I36+'04_СЕБЕСТОИМОСТЬ'!I37 | J28: ='04_СЕБЕСТОИМОСТЬ'!J36+'04_СЕБЕСТОИМОСТЬ'!J37 | K28: ='04_СЕБЕСТОИМОСТЬ'!K36+'04_СЕБЕСТОИМОСТЬ'!K37 | ... O28: ='04_СЕБЕСТОИМОСТЬ'!O36+'04_СЕБЕСТОИМОСТЬ'!O37 | P28: =SUM(D28:O28) | Q28: =P28/12 | R28: руб.
A29: PNL.BANQ.PBT | B29: Банкеты | C29: ПРИБЫЛЬ БАНКЕТОВ ДО НАЛОГА | D29: =D27-D28 | E29: =E27-E28 | F29: =F27-F28 | G29: =G27-G28 | H29: =H27-H28 | I29: =I27-I28 | J29: =J27-J28 | K29: =K27-K28 | ... O29: =O27-O28 | P29: =SUM(D29:O29) | Q29: =P29/12 | R29: руб.
A32: КОНСОЛИДИРОВАННЫЙ НАЛОГ И ЧИСТАЯ ПРИБЫЛЬ
A33: PNL.PROJ.REV | B33: Проект | C33: Совокупные доходы | D33: =D6+D25 | E33: =E6+E25 | F33: =F6+F25 | G33: =G6+G25 | H33: =H6+H25 | I33: =I6+I25 | J33: =J6+J25 | K33: =K6+K25 | ... O33: =O6+O25 | P33: =SUM(D33:O33) | Q33: =P33/12 | R33: руб.
A34: PNL.PROJ.PBT | B34: Проект | C34: Совокупная прибыль до налога | D34: =D20+D29 | E34: =E20+E29 | F34: =F20+F29 | G34: =G20+G29 | H34: =H20+H29 | I34: =I20+I29 | J34: =J20+J29 | K34: =K20+K29 | ... O34: =O20+O29 | P34: =SUM(D34:O34) | Q34: =P34/12 | R34: руб.
A35: TAX.USN15 | B35: Налоги | C35: УСН 15% от положительной базы | D35: =IF($P$33=0,0,$P$35*D33/$P$33) | E35: =IF($P$33=0,0,$P$35*E33/$P$33) | F35: =IF($P$33=0,0,$P$35*F33/$P$33) | G35: =IF($P$33=0,0,$P$35*G33/$P$33) | H35: =IF($P$33=0,0,$P$35*H33/$P$33) | I35: =IF($P$33=0,0,$P$35*I33/$P$33) | J35: =IF($P$33=0,0,$P$35*J33/$P$33) | K35: =IF($P$33=0,0,$P$35*K33/$P$33) | ... O35: =IF($P$33=0,0,$P$35*O33/$P$33) | P35: =MAX(P34,0)*'01_ВВОД'!$D$12 | Q35: =P35/12 | R35: руб.
A36: TAX.MIN1 | B36: Налоги | C36: Минимальный налог 1% доходов | D36: =IF($P$33=0,0,$P$36*D33/$P$33) | E36: =IF($P$33=0,0,$P$36*E33/$P$33) | F36: =IF($P$33=0,0,$P$36*F33/$P$33) | G36: =IF($P$33=0,0,$P$36*G33/$P$33) | H36: =IF($P$33=0,0,$P$36*H33/$P$33) | I36: =IF($P$33=0,0,$P$36*I33/$P$33) | J36: =IF($P$33=0,0,$P$36*J33/$P$33) | K36: =IF($P$33=0,0,$P$36*K33/$P$33) | ... O36: =IF($P$33=0,0,$P$36*O33/$P$33) | P36: =P33*'01_ВВОД'!$D$13 | Q36: =P36/12 | R36: руб.
A37: TAX.PAYABLE | B37: Налоги | C37: НАЛОГ К УПЛАТЕ | D37: =IF($P$33=0,0,$P$37*D33/$P$33) | E37: =IF($P$33=0,0,$P$37*E33/$P$33) | F37: =IF($P$33=0,0,$P$37*F33/$P$33) | G37: =IF($P$33=0,0,$P$37*G33/$P$33) | H37: =IF($P$33=0,0,$P$37*H33/$P$33) | I37: =IF($P$33=0,0,$P$37*I33/$P$33) | J37: =IF($P$33=0,0,$P$37*J33/$P$33) | K37: =IF($P$33=0,0,$P$37*K33/$P$33) | ... O37: =IF($P$33=0,0,$P$37*O33/$P$33) | P37: =MAX(P35,P36) | Q37: =P37/12 | R37: руб.
A38: TAX.CAFE | B38: Кафе | C38: Налог, распределённый по выручке | D38: =IF($P$33=0,0,$P$37*D6/$P$33) | E38: =IF($P$33=0,0,$P$37*E6/$P$33) | F38: =IF($P$33=0,0,$P$37*F6/$P$33) | G38: =IF($P$33=0,0,$P$37*G6/$P$33) | H38: =IF($P$33=0,0,$P$37*H6/$P$33) | I38: =IF($P$33=0,0,$P$37*I6/$P$33) | J38: =IF($P$33=0,0,$P$37*J6/$P$33) | K38: =IF($P$33=0,0,$P$37*K6/$P$33) | ... O38: =IF($P$33=0,0,$P$37*O6/$P$33) | P38: =SUM(D38:O38) | Q38: =P38/12 | R38: руб.
A39: TAX.BANQ | B39: Банкеты | C39: Налог, распределённый по выручке | D39: =IF($P$33=0,0,$P$37*D25/$P$33) | E39: =IF($P$33=0,0,$P$37*E25/$P$33) | F39: =IF($P$33=0,0,$P$37*F25/$P$33) | G39: =IF($P$33=0,0,$P$37*G25/$P$33) | H39: =IF($P$33=0,0,$P$37*H25/$P$33) | I39: =IF($P$33=0,0,$P$37*I25/$P$33) | J39: =IF($P$33=0,0,$P$37*J25/$P$33) | K39: =IF($P$33=0,0,$P$37*K25/$P$33) | ... O39: =IF($P$33=0,0,$P$37*O25/$P$33) | P39: =SUM(D39:O39) | Q39: =P39/12 | R39: руб.
A40: PNL.CAFE.NET | B40: Кафе | C40: ЧИСТЫЙ РЕЗУЛЬТАТ КАФЕ | D40: =D20-D38 | E40: =E20-E38 | F40: =F20-F38 | G40: =G20-G38 | H40: =H20-H38 | I40: =I20-I38 | J40: =J20-J38 | K40: =K20-K38 | ... O40: =O20-O38 | P40: =SUM(D40:O40) | Q40: =P40/12 | R40: руб.
A41: PNL.BANQ.NET | B41: Банкеты | C41: ЧИСТЫЙ РЕЗУЛЬТАТ БАНКЕТОВ | D41: =D29-D39 | E41: =E29-E39 | F41: =F29-F39 | G41: =G29-G39 | H41: =H29-H39 | I41: =I29-I39 | J41: =J29-J39 | K41: =K29-K39 | ... O41: =O29-O39 | P41: =SUM(D41:O41) | Q41: =P41/12 | R41: руб.
A42: PNL.PROJ.NET | B42: Проект | C42: ЧИСТАЯ ПРИБЫЛЬ ПРОЕКТА | D42: =D40+D41 | E42: =E40+E41 | F42: =F40+F41 | G42: =G40+G41 | H42: =H40+H41 | I42: =I40+I41 | J42: =J40+J41 | K42: =K40+K41 | ... O42: =O40+O41 | P42: =SUM(D42:O42) | Q42: =P42/12 | R42: руб.

Sheet 08_ПРОВЕРКИ
A1: Контроль качества модели
A2: Статус OK означает, что ключевые связи и ограничения модели соблюдены.
A4: Код | B4: Проверка | C4: Ожидается | D4: Факт | E4: Отклонение | F4: Статус | G4: Комментарий
A5: CHK.DAYS | B5: Количество календарных дней | C5: 365 | D5: =COUNTA('02_КАЛЕНДАРЬ'!$A$5:$A$369) | E5: =D5-C5 | F5: =IF(E5=0,"OK","ОШИБКА") | G5: Период 01.09.2026–31.08.2027
A6: CHK.MONTHS | B6: Количество месяцев | C6: 12 | D6: =COUNTA('03_ДОХОДЫ'!$D$4:$O$4) | E6: =D6-C6 | F6: =IF(E6=0,"OK","ОШИБКА")
A7: CHK.BANQ | B7: Количество банкетов | C7: 60 | D7: =SUM('02_КАЛЕНДАРЬ'!$H$5:$H$369) | E7: =D7-C7 | F7: =IF(E7=0,"OK","ОШИБКА")
A8: CHK.BANQ.SEP.OCT | B8: Банкеты в сентябре–октябре | C8: 0 | D8: =SUMIFS('02_КАЛЕНДАРЬ'!$H$5:$H$369,'02_КАЛЕНДАРЬ'!$B$5:$B$369,"<=2") | E8: =D8-C8 | F8: =IF(E8=0,"OK","ОШИБКА")
A9: CHK.BANQ.FSS | B9: Банкеты пятница–воскресенье | C9: 42 | D9: =COUNTIFS('02_КАЛЕНДАРЬ'!$H$5:$H$369,1,'02_КАЛЕНДАРЬ'!$I$5:$I$369,"Пт–Вс") | E9: =D9-C9 | F9: =IF(E9=0,"OK","ОШИБКА") | G9: 70%
A10: CHK.BANQ.WD | B10: Банкеты понедельник–четверг | C10: 18 | D10: =COUNTIFS('02_КАЛЕНДАРЬ'!$H$5:$H$369,1,'02_КАЛЕНДАРЬ'!$I$5:$I$369,"Пн–Чт") | E10: =D10-C10 | F10: =IF(E10=0,"OK","ОШИБКА") | G10: 30%
A11: CHK.HOTEL | B11: Гостиничные заказы за год | C11: 7300 | D11: ='03_ДОХОДЫ'!P22 | E11: =D11-C11 | F11: =IF(E11=0,"OK","ОШИБКА") | G11: 20 заказов × 365 дней
A12: CHK.BANQ.ACTIVE | B12: Продажи кафе в банкетные дни | C12: Больше 0 | D12: =SUM('02_КАЛЕНДАРЬ'!$T$5:$T$369) | E12: =IF(D12>0,0,1) | F12: =IF(D12>0,"OK","ОШИБКА") | G12: Без завтраков/ужинов
A13: CHK.REV.LINK | B13: Связь доходов проекта | C13: 0 | D13: ='03_ДОХОДЫ'!P38-'07_PNL_НАЛОГИ'!P33 | E13: =D13-C13 | F13: =IF(ABS(E13)<0.01,"OK","ОШИБКА")
A14: CHK.CONTRIB.LINK | B14: Связь маржинального дохода кафе | C14: 0 | D14: ='04_СЕБЕСТОИМОСТЬ'!P30-'07_PNL_НАЛОГИ'!P10 | E14: =D14-C14 | F14: =IF(ABS(E14)<0.01,"OK","ОШИБКА")
A15: CHK.PAY.LINK | B15: Связь расходов на персонал | C15: 0 | D15: ='05_ФОТ'!P34-'07_PNL_НАЛОГИ'!P11 | E15: =D15-C15 | F15: =IF(ABS(E15)<0.01,"OK","ОШИБКА")
A16: CHK.OPEX.LINK | B16: Связь OPEX | C16: 0 | D16: ='06_OPEX_USALI'!P52-SUM('07_PNL_НАЛОГИ'!P12,'07_PNL_НАЛОГИ'!P14:P17,'07_PNL_НАЛОГИ'!P19) | E16: =D16-C16 | F16: =IF(ABS(E16)<0.01,"OK","ОШИБКА")
A17: CHK.TAX.ALLOC | B17: Распределение налога | C17: 0 | D17: ='07_PNL_НАЛОГИ'!P38+'07_PNL_НАЛОГИ'!P39-'07_PNL_НАЛОГИ'!P37 | E17: =D17-C17 | F17: =IF(ABS(E17)<0.01,"OK","ОШИБКА")
A18: CHK.NET | B18: Консолидация чистой прибыли | C18: 0 | D18: ='07_PNL_НАЛОГИ'!P40+'07_PNL_НАЛОГИ'!P41-'07_PNL_НАЛОГИ'!P42 | E18: =D18-C18 | F18: =IF(ABS(E18)<0.01,"OK","ОШИБКА")
A19: CHK.S03.ALA | B19: А-ля карт в банкетный день = 20% | C19: 0 | D19: =ABS(SUMPRODUCT('02_КАЛЕНДАРЬ'!$H$5:$H$369,'02_КАЛЕНДАРЬ'!$M$5:$M$369)-SUMPRODUCT('02_КАЛЕНДАРЬ'!$H$5:$H$369,'02_КАЛЕНДАРЬ'!$L$5:$L$369)*'01_ВВОД'!$D$118) | E19: =D19 | F19: =IF(ABS(E19)<0.01,"OK","ОШИБКА") | G19: Проверка 60 банкетных дат
A20: CHK.S03.LUNCH
A21: CHK.S03.DEL | B21: Доставка не обнуляется в банкетный день | C21: 0 | D21: =SUMPRODUCT('02_КАЛЕНДАРЬ'!$H$5:$H$369,--('02_КАЛЕНДАРЬ'!$P$5:$P$369=0)) | E21: =D21 | F21: =IF(ABS(E21)<0.01,"OK","ОШИБКА") | G21: 100% нормы
A22: CHK.S03.PICK | B22: Самовывоз не обнуляется в банкетный день | C22: 0 | D22: =SUMPRODUCT('02_КАЛЕНДАРЬ'!$H$5:$H$369,--('02_КАЛЕНДАРЬ'!$Q$5:$Q$369=0)) | E22: =D22 | F22: =IF(ABS(E22)<0.01,"OK","ОШИБКА") | G22: 100% нормы
A23: CHK.S03.DINNER | B23: Ужины = 50% завтраков | C23: 0 | D23: =ABS(SUM('02_КАЛЕНДАРЬ'!$U$5:$U$369)-SUM('02_КАЛЕНДАРЬ'!$R$5:$R$369)*'01_ВВОД'!$D$120) | E23: =D23 | F23: =IF(ABS(E23)<0.01,"OK","ОШИБКА") | G23: Все 365 дней
A24: CHK.S03.DINNER.REV | B24: Доходы ужинов связаны с календарём | C24: 0 | D24: =ABS('03_ДОХОДЫ'!P41-SUM('02_КАЛЕНДАРЬ'!$U$5:$U$369)*'01_ВВОД'!$D$121) | E24: =D24 | F24: =IF(ABS(E24)<0.01,"OK","ОШИБКА") | G24: Годовая сверка
A25: CHK.S03.BASE | B25: Базовый файл не перезаписан | C25: Отдельный сценарий | D25: S03 | E25: 0 | F25: OK | G25: Отдельное имя файла сценария S03
A26: CHK.S03.DINNER.COGS | B26: Food cost ужина связан с food cost a-la carte | C26: 0 | D26: =ABS('01_ВВОД'!$D$122-'01_ВВОД'!$D$24) | E26: =D26-C26 | F26: =IF(ABS(E26)<0.000001,"OK","ERROR") | G26: S03_DINNER_COGS = ALA_COGS
A27: ВНИМАНИЕ: чек ужина и OPEX требуют подтверждения. Food cost ужина связан с ALA_COGS и равен 30%.

Sheet 09_СРАВНЕНИЕ_S03
A1: Сценарий S03 — сравнение с базовой моделью v0.1.0
A2: Issue #9 | Ветка scenario/9-revised-dinner-pricing-and-opex
A4: Показатель | B4: Базовая модель, руб. | C4: Сценарий S03, руб. | D4: Изменение, руб. | E4: Изменение, %
A5: Доходы кафе | B5: 32989000 | C5: ='07_PNL_НАЛОГИ'!P6 | D5: =C5-B5 | E5: =IF(B5=0,IF(C5=0,0,1),D5/ABS(B5))
A6: Доходы банкетов | B6: 3600000 | C6: ='07_PNL_НАЛОГИ'!P25 | D6: =C6-B6 | E6: =IF(B6=0,IF(C6=0,0,1),D6/ABS(B6))
A7: Совокупные доходы | B7: 36589000 | C7: ='07_PNL_НАЛОГИ'!P33 | D7: =C7-B7 | E7: =IF(B7=0,IF(C7=0,0,1),D7/ABS(B7))
A8: Себестоимость кафе | B8: 11769707 | C8: ='07_PNL_НАЛОГИ'!P7 | D8: =C8-B8 | E8: =IF(B8=0,IF(C8=0,0,1),D8/ABS(B8))
A9: Маржинальный доход кафе | B9: 19015883 | C9: ='07_PNL_НАЛОГИ'!P10 | D9: =C9-B9 | E9: =IF(B9=0,IF(C9=0,0,1),D9/ABS(B9))
A10: GOP кафе | B10: -9063186.1 | C10: ='07_PNL_НАЛОГИ'!P18 | D10: =C10-B10 | E10: =IF(B10=0,IF(C10=0,0,1),D10/ABS(B10))
A11: Чистый результат кафе | B11: -10463876 | C11: ='07_PNL_НАЛОГИ'!P40 | D11: =C11-B11 | E11: =IF(B11=0,IF(C11=0,0,1),D11/ABS(B11))
A12: Чистый результат банкетов | B12: 1710000 | C12: ='07_PNL_НАЛОГИ'!P41 | D12: =C12-B12 | E12: =IF(B12=0,IF(C12=0,0,1),D12/ABS(B12))
A13: Чистая прибыль проекта | B13: -8753876.1 | C13: ='07_PNL_НАЛОГИ'!P42 | D13: =C13-B13 | E13: =IF(B13=0,IF(C13=0,0,1),D13/ABS(B13))
A14: Упущенная выручка кафе | B14: 6082000 | C14: ='03_ДОХОДЫ'!P30 | D14: =C14-B14 | E14: =IF(B14=0,IF(C14=0,0,1),D14/ABS(B14))
A15: Доходы ужинов | B15: 0 | C15: ='03_ДОХОДЫ'!P41 | D15: =C15-B15 | E15: =IF(B15=0,IF(C15=0,0,1),D15/ABS(B15))
A18: Ключевые правила S03 | B18: Завтраки 100% | C18: Бизнес-ланч 100% | D18: А-ля карт 20% | E18: Доставка/самовывоз 100%
A19: Ужины гостиницы | B19: 50% завтраков | C19: Ежедневно | D19: Включая банкеты | E19: Редактируемые inputs

Sheet 10_СРАВНЕНИЕ_S02_S03
A1: Сравнение сценариев S02 и S03
A2: S03 повышает чек ужина, связывает food cost ужина с a-la carte и пересматривает OPEX.
A4: Показатель | B4: S02, руб. | C4: S03, руб. | D4: Изменение, руб. | E4: Изменение, %
A5: Доходы кафе | B5: 38497700 | C5: ='07_PNL_НАЛОГИ'!P6 | D5: =C5-B5 | E5: =IF(B5=0,0,D5/ABS(B5))
A6: Доходы банкетов | B6: 3600000 | C6: ='07_PNL_НАЛОГИ'!P25 | D6: =C6-B6 | E6: =IF(B6=0,0,D6/ABS(B6))
A7: Совокупные доходы | B7: 42097700 | C7: ='07_PNL_НАЛОГИ'!P33 | D7: =C7-B7 | E7: =IF(B7=0,0,D7/ABS(B7))
A8: Себестоимость кафе | B8: 14006708 | C8: ='07_PNL_НАЛОГИ'!P7 | D8: =C8-B8 | E8: =IF(B8=0,0,D8/ABS(B8))
A9: Маржинальный доход кафе | B9: 21864414 | C9: ='07_PNL_НАЛОГИ'!P10 | D9: =C9-B9 | E9: =IF(B9=0,0,D9/ABS(B9))
A10: OPEX кафе | B10: 4917000 | C10: =SUM('07_PNL_НАЛОГИ'!P12,'07_PNL_НАЛОГИ'!P14:P17) | D10: =C10-B10 | E10: =IF(B10=0,0,D10/ABS(B10))
A11: GOP кафе | B11: -6214655.5 | C11: ='07_PNL_НАЛОГИ'!P18 | D11: =C11-B11 | E11: =IF(B11=0,0,D11/ABS(B11))
A12: Прибыль проекта до налога | B12: -5539455.5 | C12: ='07_PNL_НАЛОГИ'!P34 | D12: =C12-B12 | E12: =IF(B12=0,0,D12/ABS(B12))
A13: Налог к уплате | B13: 420977 | C13: ='07_PNL_НАЛОГИ'!P37 | D13: =C13-B13 | E13: =IF(B13=0,0,D13/ABS(B13))
A14: Чистая прибыль проекта | B14: -5960432.5 | C14: ='07_PNL_НАЛОГИ'!P42 | D14: =C14-B14 | E14: =IF(B14=0,0,D14/ABS(B14))
A15: Доходы ужинов | B15: 2007500 | C15: ='07_PNL_НАЛОГИ'!P21 | D15: =C15-B15 | E15: =IF(B15=0,0,D15/ABS(B15))
A16: Себестоимость ужинов | B16: 1003750 | C16: ='07_PNL_НАЛОГИ'!P22 | D16: =C16-B16 | E16: =IF(B16=0,0,D16/ABS(B16))
A19: Код input | B19: Параметр | C19: S02 | D19: S03 | E19: Изменение | F19: Статус | G19: Комментарий
A20: CARPETS | B20: Ковры | C20: 12000 | D20: 5000 | E20: -7000 | F20: Допущение | G20: Изменение зафиксировано в S03 v0.1.4.
A21: CASH_RENT | B21: Аренда касс | C21: 9000 | D21: 0 | E21: -9000 | F21: Подтверждено | G21: Изменение зафиксировано в S03 v0.1.4.
A22: COFFEE_RENT | B22: Аренда кофемашины | C22: 10000 | D22: 0 | E22: -10000 | F22: Подтверждено | G22: Изменение зафиксировано в S03 v0.1.4.
A23: EQUIP_MAINT | B23: Обслуживание оборудования | C23: 10000 | D23: 0 | E23: -10000 | F23: Подтверждено | G23: Изменение зафиксировано в S03 v0.1.4.
A24: GREASE | B24: Жироуловитель | C24: 8000 | D24: 0 | E24: -8000 | F24: Допущение | G24: Изменение зафиксировано в S03 v0.1.4.
A25: LAUNDRY | B25: Стирка | C25: 15000 | D25: 0 | E25: -15000 | F25: Допущение | G25: Изменение зафиксировано в S03 v0.1.4.
A26: LEGAL | B26: Юридические услуги | C26: 10000 | D26: 0 | E26: -10000 | F26: Допущение | G26: Изменение зафиксировано в S03 v0.1.4.
A27: S03_DINNER_CHECK | B27: Средний чек ужина | C27: 550 | D27: 1000 | E27: 450 | F27: Рабочее допущение | G27: Изменение зафиксировано в S03 v0.1.4.
A28: SES | B28: СЭС | C28: 15000 | D28: 2000 | E28: -13000 | F28: Подтверждено | G28: Изменение зафиксировано в S03 v0.1.4.
A29: STAFF_MEALS | B29: Питание персонала | C29: 0 | D29: 15000 | E29: 15000 | F29: Требует уточнения | G29: Изменение зафиксировано в S03 v0.1.4.
A30: VENT | B30: Вентиляция | C30: 6000 | D30: 2000 | E30: -4000 | F30: Подтверждено | G30: Изменение зафиксировано в S03 v0.1.4.
A31: S03_DINNER_COGS | B31: Food cost ужина | C31: 0.5 | D31: 0.3 | E31: -0.2 | F31: Расчёт / связано | G31: Изменение зафиксировано в S03 v0.1.4.
A33: Техническая проверка | B33: S02 | C33: Source v0.2.0 | D33: Публикационный S03
A34: Количество формул | B34: 6588 | C34: 6588 | D34: 6589
A35: Контрольные строки | B35: 21 | C35: 21 | D35: 22
A36: Формульные ошибки | B36: 0 | C36: 0 | D36: 0
